[{"gpt-4-1106-preview_direct_sole-planning_results": "Travel Plan:\n\nDay 1: March 16, 2022\nCurrent City: from St. Petersburg to Rockford\nTransportation: Flight Number: F3573659, from St. Petersburg to Rockford, Departure Time: 15:40, Arrival Time: 17:04, Cost: $474\nBreakfast: - (Assuming the traveler will have breakfast before departure)\nAttraction: Anderson Japanese Gardens, Rockford, Cost: $0 (Assuming free entry or covered by a pass)\nLunch: Flying Mango, Rockford, Cost: $20, Cuisines: \"American, BBQ, Seafood\"\nDinner: Coco Bambu, Rockford, Cost: $72, Cuisines: \"Tea, French, Bakery, BBQ, Cafe\"\nAccommodation: Private Room in a two bedroom apt., Rockford, Cost: $210, Maximum Occupancy: 2, House Rules: No visitors & No smoking, Minimum Nights: 1\n\nNumber of People = 1\nTotal Cost = $474 (Flight) + $20 (Lunch) + $72 (Dinner) + $210 (Accommodation) = $776\nAccommodation Minimum Nights: 1/1\n\nDay 2: March 17, 2022\nCurrent City: Rockford\nTransportation: -\nBreakfast: Cafe Coffee Day, Rockford, Cost: $28, Cuisines: \"Chinese, Desserts, Pizza, Cafe, Mediterranean\"\nAttraction: Burpee Museum of Natural History, Rockford, Cost: $0 (Assuming free entry or covered by a pass)\nLunch: Nutri Punch, Rockford, Cost: $34, Cuisines: \"Tea, Chinese, Cafe, Desserts\"\nDinner: Cafe Southall, Rockford, Cost: $56, Cuisines: \"Seafood, Pizza, Cafe, Fast Food\"\nAccommodation: Private Room in a two bedroom apt., Rockford, Cost: $210, Maximum Occupancy: 2, House Rules: No visitors & No smoking, Minimum Nights: 1\n\nNumber of People = 1\nTotal Cost = $28 (Breakfast) + $34 (Lunch) + $56 (Dinner) + $210 (Accommodation) = $328\nAccommodation Minimum Nights: 1/1\n\nDay 3: March 18, 2022\nCurrent City: from Rockford to St. Petersburg\nTransportation: Flight Number: F3573120, from Rockford to St. Petersburg, Departure Time: 19:00, Arrival Time: 22:43, Cost: $346\nBreakfast: Dunkin' Donuts, Rockford, Cost: $24, Cuisines: \"Cafe, Bakery, BBQ, Seafood\"\nAttraction: Discovery Center Museum, Rockford, Cost: $0 (Assuming free entry or covered by a pass)\nLunch: Moets Arabica, Rockford, Cost: $43, Cuisines: \"Tea, Bakery, Indian, Fast Food\"\nDinner: - (Assuming the traveler will have dinner after arrival at the destination)\nAccommodation: -\n\nNumber of People = 1\nTotal Cost = $346 (Flight) + $24 (Breakfast) + $43 (Lunch) = $413\n\nTotal cost across all days = $776 (Day 1) + $328 (Day 2) + $413 (Day 3) = $1517\nRemaining Budget: $1700 - $1517 = $183\n\nCuisines: The prompt specifies no cuisines, so all cuisines constraints are satisfied.\nAttractions: Visited different attractions each day, no repeats.\nAccommodations: Stayed the required minimum nights and followed house rules.\nTransportation: Used flights as the only available transportation option.\n\nNote: The cost of attractions is assumed to be free or covered by a pass since no pricing information is provided. If there are entry fees, they would need to be factored into the budget.", "gpt-4-1106-preview_direct_sole-planning_parsed_results": [{"day": 1, "current_city": "from St. Petersburg to Rockford", "transportation": "Flight Number: F3573659, from St. Petersburg to Rockford, Departure Time: 15:40, Arrival Time: 17:04", "breakfast": "-", "attraction": "Anderson Japanese Gardens, Rockford;", "lunch": "Flying Mango, Rockford", "dinner": "Coco Bambu, Rockford", "accommodation": "Private Room in a two bedroom apt., Rockford"}, {"day": 2, "current_city": "Rockford", "transportation": "-", "breakfast": "Cafe Coffee Day, Rockford", "attraction": "Burpee Museum of Natural History, Rockford;", "lunch": "Nutri Punch, Rockford", "dinner": "Cafe Southall, Rockford", "accommodation": "Private Room in a two bedroom apt., Rockford"}, {"day": 3, "current_city": "from Rockford to St. Petersburg", "transportation": "Flight Number: F3573120, from Rockford to St. Petersburg, Departure Time: 19:00, Arrival Time: 22:43", "breakfast": "Dunkin' Donuts, Rockford", "attraction": "Discovery Center Museum, Rockford;", "lunch": "Moets Arabica, Rockford", "dinner": "-", "accommodation": "-"}]}]