[{"gpt-4-1106-preview_direct_sole-planning_results": "Travel Plan:\n\nDay 1:\nCurrent City: from Memphis to State College\nTransportation: Self-driving, from Memphis to State College, Duration: 13 hours 42 mins, Distance: 1,459 km, Cost: 72 * ceil(2/5) = 72 * 1 = $72\nBreakfast: -\nLunch: -\nDinner: Hotel Ekant, State College, Cost: 16 * 2 = $32, Cuisines: \"Fast Food, Pizza, Italian\"\nAccommodation: Sunny, 1 Bedroom in Bedstuy, Brooklyn, State College, Cost: 160 * ceil(2/3) = 160 * 1 = $160, Maximum Occupancy: 3, House Rules: No children under 10 & No parties, Minimum Nights: 7\n\nNumber of People = 2\nTotal Cost = 72 + 32 + 160 = $264\nAccommodation Minimum Nights: 1/7\n\nDay 2:\nCurrent City: State College\nTransportation: -\nBreakfast: The Chocolate Heaven, State College, Cost: 45 * 2 = $90, Cuisines: \"Pizza, BBQ\"\nAttraction: Discovery Space of Central Pennsylvania, State College\nLunch: Los Agaves, State College, Cost: 39 * 2 = $78, Cuisines: \"French, BBQ, Cafe\"\nDinner: Kawa Sushi, State College, Cost: 82 * 2 = $164, Cuisines: \"French, Mexican, Desserts, Fast Food\"\nAccommodation: Sunny, 1 Bedroom in Bedstuy, Brooklyn, State College, Cost: 160 * ceil(2/3) = 160 * 1 = $160, Maximum Occupancy: 3, House Rules: No children under 10 & No parties, Minimum Nights: 7\n\nNumber of people = 2\nTotal cost = 90 + 78 + 164 + 160 = $492\nAccommodation Minimum Nights: 2/7\n\nDay 3:\nCurrent City: from State College to Johnstown\nTransportation: Self-driving, from State College to Johnstown, Duration: 1 hour 29 mins, Distance: 137 km, Cost: 6 * ceil(2/5) = 6 * 1 = $6\nBreakfast: The Chocolate Heaven, State College, Cost: 45 * 2 = $90, Cuisines: \"Pizza, BBQ\"\nAttraction: Johnstown Flood Museum, Johnstown\nLunch: The National, Johnstown, Cost: 47 * 2 = $94, Cuisines: \"Chinese, BBQ, Cafe, Seafood\"\nDinner: Palmshore, Johnstown, Cost: 61 * 2 = $122, Cuisines: \"Bakery, American, BBQ, Fast Food\"\nAccommodation: 2 Bedroom Apartment East Village Amazing Location, Johnstown, Cost: 51 * ceil(2/3) = 51 * 1 = $51, Maximum Occupancy: 3, House Rules: No pets, Minimum Nights: 2\n\nNumber of people = 2\nTotal cost = 6 + 90 + 94 + 122 + 51 = $363\nAccommodation Minimum Nights: 1/2\n\nDay 4:\nCurrent City: Johnstown\nTransportation: -\nBreakfast: Souza Lobo, Johnstown, Cost: 92 * 2 = $184, Cuisines: \"Tea, Mexican, Bakery, Cafe, Indian\"\nAttraction: Heritage Discovery Center, Johnstown\nLunch: Wah Ji Wah, Johnstown, Cost: 35 * 2 = $70, Cuisines: \"Tea, French, American, Seafood\"\nDinner: Dastarkhwan, Johnstown, Cost: 100 * 2 = $200, Cuisines: \"Tea, Mexican, Pizza\"\nAccommodation: 2 Bedroom Apartment East Village Amazing Location, Johnstown, Cost: 51 * ceil(2/3) = 51 * 1 = $51, Maximum Occupancy: 3, House Rules: No pets, Minimum Nights: 2\n\nNumber of people = 2\nTotal cost = 184 + 70 + 200 + 51 = $505\nAccommodation Minimum Nights: 2/2\n\nDay 5:\nCurrent City: from Johnstown to Memphis\nTransportation: Self-driving, from Johnstown to Memphis, Duration: 12 hours 40 mins, Distance: 1,348 km, Cost: 67 * ceil(2/5) = 67 * 1 = $67\nBreakfast: -\nLunch: -\nDinner: -\nAccommodation: -\n\nNumber of people = 2\nTotal cost = 67\n\nTotal cost across all days = 264 + 492 + 363 + 505 + 67 = $1691\n\nUnfortunately, the total cost exceeds the budget of $1,400. Adjustments need to be made to align with the budget. Let's choose cheaper meal options and remove one attraction to stay within budget.\n\nAdjusted Day 2:\nDinner: Hotel Ekant, State College, Cost: 16 * 2 = $32, Cuisines: \"Fast Food, Pizza, Italian\"\nTotal cost for Day 2 = 90 + 78 + 32 + 160 = $360\n\nAdjusted Day 4:\nDinner: Wah Ji Wah, Johnstown, Cost: 35 * 2 = $70, Cuisines: \"Tea, French, American, Seafood\"\nTotal cost for Day 4 = 184 + 70 + 70 + 51 = $375\n\nAdjusted Total cost across all days = 264 + 360 + 363 + 375 + 67 = $1429\n\nThe adjusted plan is still slightly over budget. Further adjustments are needed, such as choosing the cheapest meals and removing additional attractions or opting for cheaper accommodation if possible.", "gpt-4-1106-preview_direct_sole-planning_parsed_results": [{"day": 1, "current_city": "from Memphis to State College", "transportation": "Self-driving, from Memphis to State College, Duration: 13 hours 42 mins, Distance: 1,459 km", "breakfast": "-", "attraction": "-", "lunch": "-", "dinner": "Hotel Ekant, State College", "accommodation": "Sunny, 1 Bedroom in Bedstuy, Brooklyn, State College"}, {"day": 2, "current_city": "State College", "transportation": "-", "breakfast": "The Chocolate Heaven, State College", "attraction": "Discovery Space of Central Pennsylvania, State College", "lunch": "Los Agaves, State College", "dinner": "Kawa Sushi, State College", "accommodation": "Sunny, 1 Bedroom in Bedstuy, Brooklyn, State College"}, {"day": 3, "current_city": "from State College to Johnstown", "transportation": "Self-driving, from State College to Johnstown, Duration: 1 hour 29 mins, Distance: 137 km", "breakfast": "The Chocolate Heaven, State College", "attraction": "Johnstown Flood Museum, Johnstown", "lunch": "The National, Johnstown", "dinner": "Palmshore, Johnstown", "accommodation": "2 Bedroom Apartment East Village Amazing Location, Johnstown"}, {"day": 4, "current_city": "Johnstown", "transportation": "-", "breakfast": "Souza Lobo, Johnstown", "attraction": "Heritage Discovery Center, Johnstown", "lunch": "Wah Ji Wah, Johnstown", "dinner": "Dastarkhwan, Johnstown", "accommodation": "2 Bedroom Apartment East Village Amazing Location, Johnstown"}, {"day": 5, "current_city": "from Johnstown to Memphis", "transportation": "Self-driving, from Johnstown to Memphis, Duration: 12 hours 40 mins, Distance: 1,348 km", "breakfast": "-", "attraction": "-", "lunch": "-", "dinner": "-", "accommodation": "-"}]}]