[{"gpt-4-1106-preview_direct_sole-planning_results": "Travel Plan:\n\nDay 1: March 14th, 2022\nCurrent City: from Sacramento to Atlanta\nTransportation: Flight Number: F3510904, from Sacramento to Atlanta, Departure Time: 06:55, Arrival Time: 14:09, Cost: $520\nBreakfast: - (Assuming breakfast is before the flight or on board)\nAttraction: Georgia Aquarium, Atlanta, Cost: $39.95 per person\nLunch: Adda, Atlanta, Cost: $22, Cuisines: \"Tea, Mexican, Bakery\"\nDinner: Ahata, Atlanta, Cost: $17, Cuisines: \"Tea, Indian, Desserts\"\nAccommodation: Charming Carroll Gardens 2 BR, Atlanta, Cost: $576, Maximum Occupancy: 4, House Rules: No parties, Minimum Nights: 1\n\nNumber of People = 2\nTotal Cost = 2 * $520 (flight) + 2 * $39.95 (attraction) + 2 * $22 (lunch) + 2 * $17 (dinner) + $576 (accommodation) = $1,751.90\nAccommodation Minimum Nights: 1/1\n\nDay 2: March 15th, 2022\nCurrent City: Atlanta\nTransportation: -\nBreakfast: Saffron, Atlanta, Cost: $39, Cuisines: \"Tea, Cafe, Fast Food, Seafood\"\nAttraction: World of Coca-Cola, Atlanta, Cost: $18 per person\nLunch: Chef Style, Atlanta, Cost: $59, Cuisines: \"Pizza, American, Desserts, Seafood\"\nDinner: Sizzler's Ranch, Atlanta, Cost: $36, Cuisines: \"Tea, Cafe, Indian, Italian\"\nAccommodation: Charming Carroll Gardens 2 BR, Atlanta, Cost: $576, Maximum Occupancy: 4, House Rules: No parties, Minimum Nights: 1\n\nNumber of People = 2\nTotal Cost = 2 * $39 (breakfast) + 2 * $18 (attraction) + 2 * $59 (lunch) + 2 * $36 (dinner) + $576 (accommodation) = $920\nAccommodation Minimum Nights: 1/1\n\nDay 3: March 16th, 2022\nCurrent City: from Atlanta to Sacramento\nTransportation: Flight Number: F3542376, from Atlanta to Sacramento, Departure Time: 17:53, Arrival Time: 20:36, Cost: $828\nBreakfast: Taste of Vishal, Atlanta, Cost: $13, Cuisines: \"Desserts, Tea, American, Bakery, Indian, Seafood\"\nAttraction: Atlanta Botanical Garden, Atlanta, Cost: $21.95 per person\nLunch: Beliram Degchiwala, Atlanta, Cost: $14, Cuisines: \"Cafe, Pizza\"\nDinner: - (Assuming dinner is after the flight or on board)\nAccommodation: -\n\nNumber of People = 2\nTotal Cost = 2 * $828 (flight) + 2 * $13 (breakfast) + 2 * $21.95 (attraction) + 2 * $14 (lunch) = $1,741.90\n\nTotal cost across all days = $1,751.90 + $920 + $1,741.90 = $4,413.80\n\nCuisines: The prompt specifies no cuisines, so all cuisines constraints are satisfied.\nHouse Rules: The accommodations chosen do not allow parties, which is a requirement. However, there are no accommodations listed that allow parties. If this is a strict requirement, we would need to find alternative accommodations not listed in the provided information.\n\nPlease note that the prices for attractions are assumed based on common pricing and may not reflect the actual costs provided in the reference information, as the attraction prices were not included in the given data.", "gpt-4-1106-preview_direct_sole-planning_parsed_results": [{"day": 1, "current_city": "from Sacramento to Atlanta", "transportation": "Flight Number: F3510904, from Sacramento to Atlanta, Departure Time: 06:55, Arrival Time: 14:09", "breakfast": "-", "attraction": "Georgia Aquarium, Atlanta;", "lunch": "Adda, Atlanta", "dinner": "Ahata, Atlanta", "accommodation": "Charming Carroll Gardens 2 BR, Atlanta"}, {"day": 2, "current_city": "Atlanta", "transportation": "-", "breakfast": "Saffron, Atlanta", "attraction": "World of Coca-Cola, Atlanta;", "lunch": "Chef Style, Atlanta", "dinner": "Sizzler's Ranch, Atlanta", "accommodation": "Charming Carroll Gardens 2 BR, Atlanta"}, {"day": 3, "current_city": "from Atlanta to Sacramento", "transportation": "Flight Number: F3542376, from Atlanta to Sacramento, Departure Time: 17:53, Arrival Time: 20:36", "breakfast": "Taste of Vishal, Atlanta", "attraction": "Atlanta Botanical Garden, Atlanta;", "lunch": "Beliram Degchiwala, Atlanta", "dinner": "-", "accommodation": "-"}]}]