[{"gpt-4-1106-preview_direct_sole-planning_results": "Travel Plan:\n\nDay 1:\nCurrent City: from Las Vegas to Stockton\nTransportation: Flight Number: F3576711, from Las Vegas to Stockton, Departure Time: 06:01, Arrival Time: 07:28, Cost: $96\nBreakfast: Choo Choo Eastside, Stockton, Cost: $40, Cuisines: \"Tea, Chinese, Bakery\"\nAttraction: Children's Museum, Stockton, Cost: $0 (assuming free entry as no price is provided)\nLunch: Biaggi's Ristorante Italiano, Stockton, Cost: $20, Cuisines: \"French, Bakery, Cafe, Seafood\"\nDinner: Twin Brothers, Stockton, Cost: $32, Cuisines: \"Tea, Pizza, French, Bakery, Seafood\"\nAccommodation: Private Apt 2BR/1Bath/Kitchen/Parking in OUR HOME, Stockton, Cost: $420, Maximum Occupancy: 4, House Rules: No pets, Minimum Nights: 1\n\nNumber of People = 1\nTotal Cost = $96 + $40 + $20 + $32 + $420 = $608\nAccommodation Minimum Nights: 1/1\n\nDay 2:\nCurrent City: Stockton\nTransportation: -\nBreakfast: Muffins, Stockton, Cost: $26, Cuisines: \"Seafood, Desserts, Italian\"\nAttraction: Haggin Museum, Stockton, Cost: $0 (assuming free entry as no price is provided)\nLunch: Dimsum & Co., Stockton, Cost: $40, Cuisines: \"Chinese, Bakery, BBQ, Seafood\"\nDinner: Konetto Pizza, Stockton, Cost: $47, Cuisines: \"Pizza, BBQ, Mediterranean\"\nAccommodation: Private Apt 2BR/1Bath/Kitchen/Parking in OUR HOME, Stockton, Cost: $420, Maximum Occupancy: 4, House Rules: No pets, Minimum Nights: 1\n\nNumber of People = 1\nTotal Cost = $26 + $40 + $47 + $420 = $533\nAccommodation Minimum Nights: 1/1\n\nDay 3:\nCurrent City: from Stockton to Las Vegas\nTransportation: Flight Number: F3576850, from Stockton to Las Vegas, Departure Time: 13:42, Arrival Time: 15:03, Cost: $165\nBreakfast: Subway, Stockton, Cost: $58, Cuisines: \"Cafe, Mexican, Bakery, Fast Food\"\nAttraction: Louis Park, Stockton, Cost: $0 (assuming free entry as no price is provided)\nLunch: Twenty Four Seven, Stockton, Cost: $92, Cuisines: \"Desserts, Tea, Italian, BBQ, Fast Food, American\"\nDinner: - (Assuming the flight includes a meal or the traveler will eat after returning to Las Vegas)\nAccommodation: -\n\nNumber of People = 1\nTotal Cost = $165 + $58 + $92 = $315\n\nTotal cost across all days = $608 + $533 + $315 = $1456\n\nUnfortunately, the total cost exceeds the budget of $1,400. To adjust the plan to fit the budget, we can opt for cheaper transportation options:\n\nAdjusted Day 1 Transportation: Self-driving from Las Vegas to Stockton, duration: 7 hours 46 mins, distance: 835 km, cost: $41\nAdjusted Day 3 Transportation: Self-driving from Stockton to Las Vegas, duration: 7 hours 50 mins, distance: 836 km, cost: $41\n\nAdjusted Total Cost for Transportation = $41 + $41 = $82\n\nAdjusted Total cost across all days = $608 - $96 + $41 + $533 + $315 - $165 + $41 = $1372\n\nNow the travel plan fits within the budget of $1,400.", "gpt-4-1106-preview_direct_sole-planning_parsed_results": [{"day": 1, "current_city": "from Las Vegas to Stockton", "transportation": "Flight Number: F3576711, from Las Vegas to Stockton, Departure Time: 06:01, Arrival Time: 07:28", "breakfast": "Choo Choo Eastside, Stockton", "attraction": "Children's Museum, Stockton;", "lunch": "Biaggi's Ristorante Italiano, Stockton", "dinner": "Twin Brothers, Stockton", "accommodation": "Private Apt 2BR/1Bath/Kitchen/Parking in OUR HOME, Stockton"}, {"day": 2, "current_city": "Stockton", "transportation": "-", "breakfast": "Muffins, Stockton", "attraction": "Haggin Museum, Stockton;", "lunch": "Dimsum & Co., Stockton", "dinner": "Konetto Pizza, Stockton", "accommodation": "Private Apt 2BR/1Bath/Kitchen/Parking in OUR HOME, Stockton"}, {"day": 3, "current_city": "from Stockton to Las Vegas", "transportation": "Flight Number: F3576850, from Stockton to Las Vegas, Departure Time: 13:42, Arrival Time: 15:03", "breakfast": "Subway, Stockton", "attraction": "Louis Park, Stockton;", "lunch": "Twenty Four Seven, Stockton", "dinner": "-", "accommodation": "-"}]}]