[{"gpt-4-1106-preview_direct_sole-planning_results": "Travel Plan:\n\nDay 1: March 15, 2022\nCurrent City: from Sault Ste. Marie to Pellston\nTransportation: Self-driving, Duration: 1 hour 16 mins, Distance: 122 km, Cost: $6 * ceil(5/5) = $6\nBreakfast: -\nAttraction: Pellston Pioneer Park, Pellston, Cost: Free\nLunch: Johnnie Mars, Pellston, Average Cost: $33, Cuisines: \"Tea, Fast Food\"\nDinner: Aroos Damascus, Pellston, Average Cost: $44, Cuisines: \"Desserts, Tea, Italian, Cafe, American\"\nAccommodation: Beautiful apartment ~25min from Times Square, Pellston, Cost: $571, Entire home/apt, Minimum Nights: 5, Maximum Occupancy: 5\n\nNumber of People = 5\nTotal Cost = 5 * $6 + 5 * $33 + 5 * $44 + $571 = $30 + $165 + $220 + $571 = $986\nAccommodation Minimum Nights: 1/5\n\nDay 2: March 16, 2022\nCurrent City: Pellston\nTransportation: -\nBreakfast: Aroos Damascus, Pellston, Average Cost: $44, Cuisines: \"Desserts, Tea, Italian, Cafe, American\"\nAttraction: Headlands International Dark Sky Park, Pellston, Cost: Free\nLunch: Sagar Gaire Fast Food, Pellston, Average Cost: $64, Cuisines: \"Desserts, Tea, Pizza, Italian, BBQ, Mediterranean\"\nDinner: The Great Kabab Factory - Park Plaza, Pellston, Average Cost: $84, Cuisines: \"Desserts, Pizza, Mexican, BBQ, Seafood\"\nAccommodation: Beautiful apartment ~25min from Times Square, Pellston, Cost: $571, Entire home/apt, Minimum Nights: 5, Maximum Occupancy: 5\n\nNumber of People = 5\nTotal Cost = 5 * $44 + 5 * $64 + 5 * $84 + $571 = $220 + $320 + $420 + $571 = $1531\nAccommodation Minimum Nights: 2/5\n\nDay 3: March 17, 2022\nCurrent City: from Pellston to Traverse City\nTransportation: Self-driving, Duration: 1 hour 49 mins, Distance: 137 km, Cost: $6 * ceil(5/5) = $6\nBreakfast: Premier Bite, Pellston, Average Cost: $53, Cuisines: \"Tea, Bakery, Seafood\"\nAttraction: Clinch Park, Traverse City, Cost: Free\nLunch: Daily Eats, Traverse City, Average Cost: $44, Cuisines: \"Desserts, Seafood\"\nDinner: Arigato Sushi, Traverse City, Average Cost: $96, Cuisines: \"Desserts, Mexican, Bakery, BBQ, Fast Food, Mediterranean\"\nAccommodation: Heart of Soho! Cute studio with clean finishes!, Traverse City, Cost: $969, Entire home/apt, Minimum Nights: 4, Maximum Occupancy: 2\n\nNumber of People = 5\nTotal Cost = 5 * $6 + 5 * $53 + 5 * $44 + 5 * $96 + $969 * ceil(5/2) = $30 + $265 + $220 + $480 + $2422.5 = $3417.5\nAccommodation Minimum Nights: 1/4\n\nDay 4: March 18, 2022\nCurrent City: Traverse City\nTransportation: -\nBreakfast: Tasty Bites, Traverse City, Average Cost: $27, Cuisines: \"Chinese, Bakery, Desserts, Seafood\"\nAttraction: Great Wolf Lodge Water Park | Traverse City, Cost: Free\nLunch: India on my Plate - Fortune Select Excalibur, Traverse City, Average Cost: $53, Cuisines: \"Tea, Chinese, Seafood\"\nDinner: Whipped, Traverse City, Average Cost: $90, Cuisines: \"Cafe, Indian, BBQ\"\nAccommodation: Heart of Soho! Cute studio with clean finishes!, Traverse City, Cost: $969, Entire home/apt, Minimum Nights: 4, Maximum Occupancy: 2\n\nNumber of People = 5\nTotal Cost = 5 * $27 + 5 * $53 + 5 * $90 + $969 * ceil(5/2) = $135 + $265 + $450 + $2422.5 = $3272.5\nAccommodation Minimum Nights: 2/4\n\nDay 5: March 19, 2022\nCurrent City: from Traverse City to Alpena\nTransportation: Self-driving, Duration: 2 hours 29 mins, Distance: 204 km, Cost: $10 * ceil(5/5) = $10\nBreakfast: Desserts 83, Traverse City, Average Cost: $78, Cuisines: \"Tea, Cafe, Chinese, American, Seafood\"\nAttraction: Great Lakes Maritime Heritage Center, Alpena, Cost: Free\nLunch: @Mango, Alpena, Average Cost: $38, Cuisines: \"BBQ, Cafe, American, Desserts\"\nDinner: Maplai, Alpena, Average Cost: $63, Cuisines: \"Tea, Indian, Bakery, Fast Food, American\"\nAccommodation: Ultimate 50th Floor Downtown Penthouse - 4000SqFt, Alpena, Cost: $1043, Entire home/apt, Minimum Nights: 2, Maximum Occupancy: 9\n\nNumber of People = 5\nTotal Cost = 5 * $10 + 5 * $78 + 5 * $38 + 5 * $63 + $1043 = $50 + $390 + $190 + $315 + $1043 = $1988\nAccommodation Minimum Nights: 1/2\n\nDay 6: March 20, 2022\nCurrent City: Alpena\nTransportation: -\nBreakfast: Shudh Restaurant, Alpena, Average Cost: $56, Cuisines: \"Cafe, BBQ, Fast Food\"\nAttraction: Besser Museum for Northeast Michigan, Alpena, Cost: Free\nLunch: Zaffran - The Bristol Hotel, Alpena, Average Cost: $33, Cuisines: \"Pizza, Desserts, Seafood\"\nDinner: Kylin Express, Alpena, Average Cost: $30, Cuisines: \"Chinese, Bakery, BBQ, Seafood\"\nAccommodation: Ultimate 50th Floor Downtown Penthouse - 4000SqFt, Alpena, Cost: $1043, Entire home/apt, Minimum Nights: 2, Maximum Occupancy: 9\n\nNumber of People = 5\nTotal Cost = 5 * $56 + 5 * $33 + 5 * $30 + $1043 = $280 + $165 + $150 + $1043 = $1638\nAccommodation Minimum Nights: 2/2\n\nDay 7: March 21, 2022\nCurrent City: from Alpena to Sault Ste. Marie\nTransportation: Self-driving, Duration: 2 hours 39 mins, Distance: 247 km, Cost: $12 * ceil(5/5) = $12\nBreakfast: Jain Chawal Wale, Alpena, Average Cost: $20, Cuisines: \"Desserts, Pizza, Italian, Mexican, Cafe\"\nAttraction: -\nLunch: -\nDinner: -\nAccommodation: -\n\nNumber of People = 5\nTotal Cost = 5 * $12 + 5 * $20 = $60 + $100 = $160\n\nTotal cost across all days = $986 + $1531 + $3417.5 + $3272.5 + $1988 + $1638 + $160 = $12995\n\nRemaining Budget: $12,700 - $12,995 = -$295 (Over budget by $295)\n\nNote: The plan has gone slightly over budget. To adjust, consider choosing cheaper meal options or reducing the cost of transportation by opting for a less expensive vehicle or accommodation that fits within the budget.", "gpt-4-1106-preview_direct_sole-planning_parsed_results": [{"day": 1, "current_city": "from Sault Ste. Marie to Pellston", "transportation": "Self-driving, Duration: 1 hour 16 mins, Distance: 122 km", "breakfast": "-", "attraction": "Pellston Pioneer Park, Pellston", "lunch": "Johnnie Mars, Pellston", "dinner": "Aroos Damascus, Pellston", "accommodation": "Beautiful apartment ~25min from Times Square, Pellston"}, {"day": 2, "current_city": "Pellston", "transportation": "-", "breakfast": "Aroos Damascus, Pellston", "attraction": "Headlands International Dark Sky Park, Pellston", "lunch": "Sagar Gaire Fast Food, Pellston", "dinner": "The Great Kabab Factory - Park Plaza, Pellston", "accommodation": "Beautiful apartment ~25min from Times Square, Pellston"}, {"day": 3, "current_city": "from Pellston to Traverse City", "transportation": "Self-driving, Duration: 1 hour 49 mins, Distance: 137 km", "breakfast": "Premier Bite, Pellston", "attraction": "Clinch Park, Traverse City", "lunch": "Daily Eats, Traverse City", "dinner": "Arigato Sushi, Traverse City", "accommodation": "Heart of Soho! Cute studio with clean finishes!, Traverse City"}, {"day": 4, "current_city": "Traverse City", "transportation": "-", "breakfast": "Tasty Bites, Traverse City", "attraction": "Great Wolf Lodge Water Park | Traverse City", "lunch": "India on my Plate - Fortune Select Excalibur, Traverse City", "dinner": "Whipped, Traverse City", "accommodation": "Heart of Soho! Cute studio with clean finishes!, Traverse City"}, {"day": 5, "current_city": "from Traverse City to Alpena", "transportation": "Self-driving, Duration: 2 hours 29 mins, Distance: 204 km", "breakfast": "Desserts 83, Traverse City", "attraction": "Great Lakes Maritime Heritage Center, Alpena", "lunch": "@Mango, Alpena", "dinner": "Maplai, Alpena", "accommodation": "Ultimate 50th Floor Downtown Penthouse - 4000SqFt, Alpena"}, {"day": 6, "current_city": "Alpena", "transportation": "-", "breakfast": "Shudh Restaurant, Alpena", "attraction": "Besser Museum for Northeast Michigan, Alpena", "lunch": "Zaffran - The Bristol Hotel, Alpena", "dinner": "Kylin Express, Alpena", "accommodation": "Ultimate 50th Floor Downtown Penthouse - 4000SqFt, Alpena"}, {"day": 7, "current_city": "from Alpena to Sault Ste. Marie", "transportation": "Self-driving, Duration: 2 hours 39 mins, Distance: 247 km", "breakfast": "Jain Chawal Wale, Alpena", "attraction": "-", "lunch": "-", "dinner": "-", "accommodation": "-"}]}]