[{"gpt-4-1106-preview_direct_sole-planning_results": "Travel Plan:\n\nDay 1: March 1, 2022\nCurrent City: from Memphis to Minneapolis\nTransportation: Flight Number: F3836157, from Memphis to Minneapolis, Departure Time: 05:57, Arrival Time: 08:10, Cost: $260 * 4 = $1040\nBreakfast: The Cafe, Minneapolis, Cost: $14 * 4 = $56, Cuisines: \"Indian, Mediterranean, Desserts, Seafood\"\nAttraction: Minneapolis Sculpture Garden, Minneapolis, Cost: $0 (Assuming no entry fee)\nLunch: Texas Roadhouse, Minneapolis, Cost: $22 * 4 = $88, Cuisines: \"Cafe, Pizza, BBQ, Desserts\"\nDinner: Troll Tavern, Minneapolis, Cost: $71 * 4 = $284, Cuisines: \"Tea, BBQ, Mediterranean\"\nAccommodation: Light-filled Apartment in great area, close 2 all!, Minneapolis, Cost: $343 * 2 = $686, Maximum Occupancy: 2, House Rules: No Visitors, Minimum Nights: 1\n\nNumber of People = 4\nTotal Cost = $1040 + $56 + $88 + $284 + $686 = $2154\nAccommodation Minimum Nights: 1/1\n\nDay 2: March 2, 2022\nCurrent City: Minneapolis\nTransportation: -\nBreakfast: Giani, Minneapolis, Cost: $17 * 4 = $68, Cuisines: \"Cafe, Mexican, Bakery, Desserts\"\nAttraction: Mill City Museum, Minneapolis, Cost: $0 (Assuming no entry fee)\nLunch: FreshMenu, Minneapolis, Cost: $88 * 4 = $352, Cuisines: \"Seafood, Desserts, Fast Food\"\nDinner: Monkeypod Kitchen by Merriman, Minneapolis, Cost: $50 * 4 = $200, Cuisines: \"Desserts, Pizza, Bakery, Fast Food, Indian, Mediterranean\"\nAccommodation: ROOM TWO, Minneapolis, Cost: $112 * 2 = $224, Maximum Occupancy: 2, House Rules: No Children under 10, Minimum Nights: 3\n\nNumber of People = 4\nTotal Cost = $68 + $352 + $200 + $224 = $844\nAccommodation Minimum Nights: 1/3\n\nDay 3: March 3, 2022\nCurrent City: Minneapolis to Gustavus\nTransportation: Self-driving, from Minneapolis to Gustavus, Cost: $5 * ceil(4/5) = $5\nBreakfast: Playboy Cafe, Minneapolis, Cost: $60 * 4 = $240, Cuisines: \"Cafe, Mexican, Bakery\"\nAttraction: Glacier Bay National Park Visitor Center, Gustavus, Cost: $0 (Assuming no entry fee)\nLunch: That Madras Place, Gustavus, Cost: $36 * 4 = $144, Cuisines: \"Desserts, Italian, Bakery, BBQ, Cafe\"\nDinner: Hofer's Bakery & Cafe, Gustavus, Cost: $34 * 4 = $136, Cuisines: \"Mexican, Bakery, BBQ, Fast Food, Cafe, American\"\nAccommodation: Large Private Room in 3 bdr apt-East Village, Gustavus, Cost: $684 * 2 = $1368, Maximum Occupancy: 2, House Rules: No Smoking & No Parties, Minimum Nights: 1\n\nNumber of People = 4\nTotal Cost = $5 + $240 + $144 + $136 + $1368 = $1893\nAccommodation Minimum Nights: 1/1\n\nDay 4: March 4, 2022\nCurrent City: Gustavus\nTransportation: -\nBreakfast: Tobasco Kitchen, Gustavus, Cost: $21 * 4 = $84, Cuisines: \"Desserts, Tea, Italian, Mexican, Bakery, Seafood\"\nAttraction: NatVenture Tours, Gustavus, Cost: $0 (Assuming no entry fee)\nLunch: Imperfecto, Gustavus, Cost: $10 * 4 = $40, Cuisines: \"Tea, Cafe, BBQ, Fast Food\"\nDinner: Jamie's Italian, Gustavus, Cost: $94 * 4 = $376, Cuisines: \"Tea, Bakery, Fast Food, Cafe, American\"\nAccommodation: New Furnished Modern Two-Bedroom Apartment, Gustavus, Cost: $644 * 2 = $1288, Maximum Occupancy: 3, House Rules: No Pets, Minimum Nights: 30\n\nNumber of People = 4\nTotal Cost = $84 + $40 + $376 + $1288 = $1788\nAccommodation Minimum Nights: 1/30 (Not meeting the minimum nights requirement, but no other options available)\n\nDay 5: March 5, 2022\nCurrent City: from Gustavus to Memphis\nTransportation: Self-driving, from Gustavus to Memphis, Cost: $64 * ceil(4/5) = $64\nBreakfast: For the Love of Cake, Gustavus, Cost: $93 * 4 = $372, Cuisines: \"French, American, Desserts, Seafood\"\nAttraction: Sea Wolf Adventures, Gustavus, Cost: $0 (Assuming no entry fee)\nLunch: Wood Box Cafe, Gustavus, Cost: $91 * 4 = $364, Cuisines: \"Desserts, Bakery, Cafe, Mediterranean, Seafood\"\nDinner: - (Assuming travelers will have dinner after arriving in Memphis)\nAccommodation: -\n\nNumber of People = 4\nTotal Cost = $64 + $372 + $364 = $800\n\nTotal cost across all days = $2154 + $844 + $1893 + $1788 + $800 = $7479\nCuisines: The prompt specifies no cuisines, so all cuisines constraints are satisfied.\n\nNote: The accommodations chosen are the only ones that provide private rooms and meet the house rules requirement. The minimum nights requirement for accommodations is not fully met due to limited options. Attractions are assumed to have no entry fee as no cost information is provided. The budget is well within the limit of $13,800.", "gpt-4-1106-preview_direct_sole-planning_parsed_results": [{"day": 1, "current_city": "from Memphis to Minneapolis", "transportation": "Flight Number: F3836157, from Memphis to Minneapolis, Departure Time: 05:57, Arrival Time: 08:10", "breakfast": "-", "attraction": "Minneapolis Sculpture Garden, Minneapolis;", "lunch": "Texas Roadhouse, Minneapolis", "dinner": "Troll Tavern, Minneapolis", "accommodation": "Light-filled Apartment in great area, close 2 all!, Minneapolis"}, {"day": 2, "current_city": "Minneapolis", "transportation": "-", "breakfast": "Giani, Minneapolis", "attraction": "Mill City Museum, Minneapolis;", "lunch": "FreshMenu, Minneapolis", "dinner": "Monkeypod Kitchen by Merriman, Minneapolis", "accommodation": "ROOM TWO, Minneapolis"}, {"day": 3, "current_city": "from Minneapolis to Gustavus", "transportation": "Self-driving, from Minneapolis to Gustavus", "breakfast": "Playboy Cafe, Minneapolis", "attraction": "Glacier Bay National Park Visitor Center, Gustavus;", "lunch": "That Madras Place, Gustavus", "dinner": "Hofer's Bakery & Cafe, Gustavus", "accommodation": "Large Private Room in 3 bdr apt-East Village, Gustavus"}, {"day": 4, "current_city": "Gustavus", "transportation": "-", "breakfast": "Tobasco Kitchen, Gustavus", "attraction": "NatVenture Tours, Gustavus;", "lunch": "Imperfecto, Gustavus", "dinner": "Jamie's Italian, Gustavus", "accommodation": "New Furnished Modern Two-Bedroom Apartment, Gustavus"}, {"day": 5, "current_city": "from Gustavus to Memphis", "transportation": "Self-driving, from Gustavus to Memphis", "breakfast": "For the Love of Cake, Gustavus", "attraction": "Sea Wolf Adventures, Gustavus;", "lunch": "Wood Box Cafe, Gustavus", "dinner": "-", "accommodation": "-"}]}]