[{"gpt-4-1106-preview_direct_sole-planning_results": "Travel Plan:\n\nDay 1:\nCurrent City: from Asheville to Baltimore\nTransportation: Self-driving, from Asheville to Baltimore, Duration: 7 hours 43 mins, Distance: 819 km, Cost: 320 (40 * ceil(8/5))\nBreakfast: - (Assuming breakfast is had before departure)\nAttraction: National Aquarium, Baltimore, Cost: 0 (Assuming free entry or covered by a separate budget)\nLunch: Los Pablos, Baltimore, Cost: 376 (47 * 8), Cuisines: \"Indian, BBQ, Cafe, American, Seafood\"\nDinner: The Retriever, Baltimore, Cost: 96 (12 * 8), Cuisines: \"Seafood, Cafe, Italian\"\nAccommodation: Contemporary Home Away from Home, Entire house, Cost: 580 (290 * ceil(8/2)), Maximum Occupancy: 2, House Rules: No visitors, Minimum Nights: 2\n\nNumber of People = 8\nTotal Cost = 320 + 376 + 96 + 580 = 1372\nAccommodation Minimum Nights: 1/2\n\nDay 2:\nCurrent City: Baltimore\nTransportation: -\nBreakfast: Mocha Bar, Baltimore, Cost: 256 (32 * 8), Cuisines: \"BBQ, Desserts, Italian\"\nAttraction: The Maryland Zoo in Baltimore, Cost: 0 (Assuming free entry or covered by a separate budget)\nLunch: New Kadimi, Baltimore, Cost: 728 (91 * 8), Cuisines: \"Desserts, Pizza, BBQ, Fast Food, Chinese\"\nDinner: Tibb's Frankie, Baltimore, Cost: 192 (24 * 8), Cuisines: \"Tea, Cafe, BBQ\"\nAccommodation: Contemporary Home Away from Home, Entire house, Cost: 580 (290 * ceil(8/2)), Maximum Occupancy: 2, House Rules: No visitors, Minimum Nights: 2\n\nNumber of people = 8\nTotal cost = 256 + 728 + 192 + 580 = 1756\nAccommodation Minimum Nights: 2/2\n\nDay 3:\nCurrent City: from Baltimore to Asheville\nTransportation: Self-driving, from Baltimore to Asheville, Duration: 7 hours 42 mins, Distance: 819 km, Cost: 320 (40 * ceil(8/5))\nBreakfast: Rajshree, Baltimore, Cost: 104 (13 * 8), Cuisines: \"Italian, Bakery, BBQ, Cafe, Mediterranean, Seafood\"\nAttraction: Fort McHenry National Monument and Historic Shrine, Cost: 0 (Assuming free entry or covered by a separate budget)\nLunch: Green Chick Chop, Baltimore, Cost: 120 (15 * 8), Cuisines: \"Pizza, Mexican, Bakery, Mediterranean, Seafood\"\nDinner: - (Assuming dinner will be had after arrival back in Asheville)\nAccommodation: -\n\nNumber of people = 8\nTotal cost = 320 + 104 + 120 = 544\n\nTotal cost across all days = 1372 + 1756 + 544 = 3672\nCuisines: The prompt specifies no cuisines, so all cuisines constraints are satisfied.\nAccommodations: All chosen accommodations are suitable for children under 10 as per the house rules.\n\nPlease note that the attractions are assumed to be free or have their costs covered by a separate budget, as the provided information does not include attraction prices. If there are entry fees for the attractions, they would need to be factored into the budget accordingly.", "gpt-4-1106-preview_direct_sole-planning_parsed_results": [{"day": 1, "current_city": "from Asheville to Baltimore", "transportation": "Self-driving, from Asheville to Baltimore, Duration: 7 hours 43 mins, Distance: 819 km", "breakfast": "-", "attraction": "National Aquarium, Baltimore;", "lunch": "Los Pablos, Baltimore", "dinner": "The Retriever, Baltimore", "accommodation": "Contemporary Home Away from Home, Baltimore"}, {"day": 2, "current_city": "Baltimore", "transportation": "-", "breakfast": "Mocha Bar, Baltimore", "attraction": "The Maryland Zoo in Baltimore;", "lunch": "New Kadimi, Baltimore", "dinner": "Tibb's Frankie, Baltimore", "accommodation": "Contemporary Home Away from Home, Baltimore"}, {"day": 3, "current_city": "from Baltimore to Asheville", "transportation": "Self-driving, from Baltimore to Asheville, Duration: 7 hours 42 mins, Distance: 819 km", "breakfast": "Rajshree, Baltimore", "attraction": "Fort McHenry National Monument and Historic Shrine;", "lunch": "Green Chick Chop, Baltimore", "dinner": "-", "accommodation": "-"}]}]