[{"gpt-4-1106-preview_direct_sole-planning_results": "Travel Plan:\n\nDay 1: March 18, 2022\nCurrent City: from Daytona Beach to Corpus Christi\nTransportation: Self-driving, Duration: 16 hours 54 mins, Distance: 1,874 km, Cost: $93\nBreakfast: -\nAttraction: -\nLunch: -\nDinner: -\nAccommodation: My Little Guest Apartment, Corpus Christi, Cost: $524, Maximum Occupancy: 4, House Rules: No children under 10, Minimum Nights: 2\n\nNumber of People = 1\nTotal Cost = $93 (Transportation) + $524 (Accommodation) = $617\nAccommodation Minimum Nights: 1/2\n\nDay 2: March 19, 2022\nCurrent City: Corpus Christi\nTransportation: -\nBreakfast: Confeitaria Colombo, Corpus Christi, Cost: $11, Cuisines: \"Tea, Chinese, Bakery, Cafe\"\nAttraction: Texas State Aquarium, Corpus Christi\nLunch: The Binge Box Cafe, Corpus Christi, Cost: $32, Cuisines: \"Desserts, Italian, Bakery, Indian, Seafood\"\nDinner: Sangeetha Vegetarian Restaurant, Corpus Christi, Cost: $91, Cuisines: \"Desserts, Tea, Pizza, French, BBQ\"\nAccommodation: My Little Guest Apartment, Corpus Christi, Cost: $524, Maximum Occupancy: 4, House Rules: No children under 10, Minimum Nights: 2\n\nNumber of People = 1\nTotal Cost = $11 (Breakfast) + $32 (Lunch) + $91 (Dinner) + $524 (Accommodation) = $658\nAccommodation Minimum Nights: 2/2\n\nDay 3: March 20, 2022\nCurrent City: from Corpus Christi to San Antonio\nTransportation: Self-driving, Duration: 2 hours 3 mins, Distance: 231 km, Cost: $11\nBreakfast: -\nAttraction: San Antonio River Walk, San Antonio\nLunch: Cafe Le Rue @ The Landings, San Antonio, Cost: $19, Cuisines: \"French, Mexican, Cafe, Seafood\"\nDinner: Barbeque Nation, San Antonio, Cost: $16, Cuisines: \"Tea, Cafe, Fast Food, Chinese, American\"\nAccommodation: Williamsburg Gardens Flat, Large Room Private Bath, San Antonio, Cost: $172, Maximum Occupancy: 1, House Rules: \"No smoking & No children under 10\", Minimum Nights: 3\n\nNumber of People = 1\nTotal Cost = $11 (Transportation) + $19 (Lunch) + $16 (Dinner) + $172 (Accommodation) = $218\nAccommodation Minimum Nights: 1/3\n\nDay 4: March 21, 2022\nCurrent City: San Antonio\nTransportation: -\nBreakfast: The Kylin Experience - Holiday Inn, San Antonio, Cost: $23, Cuisines: \"Tea, Cafe, Pizza, Fast Food\"\nAttraction: The Alamo, San Antonio\nLunch: Cream Stone, San Antonio, Cost: $53, Cuisines: \"Cafe, BBQ, Mediterranean, Desserts\"\nDinner: Martin's BBQ, San Antonio, Cost: $71, Cuisines: \"Tea, BBQ, Fast Food, Indian, Seafood\"\nAccommodation: Williamsburg Gardens Flat, Large Room Private Bath, San Antonio, Cost: $172, Maximum Occupancy: 1, House Rules: \"No smoking & No children under 10\", Minimum Nights: 3\n\nNumber of People = 1\nTotal Cost = $23 (Breakfast) + $53 (Lunch) + $71 (Dinner) + $172 (Accommodation) = $319\nAccommodation Minimum Nights: 2/3\n\nDay 5: March 22, 2022\nCurrent City: from San Antonio to Dallas\nTransportation: Flight Number: F3984244, from San Antonio to Dallas, Departure Time: 10:10, Arrival Time: 11:10, Cost: $53\nBreakfast: -\nAttraction: The Dallas World Aquarium, Dallas\nLunch: Coconuts Fish Cafe, Dallas, Cost: $38, Cuisines: \"Cafe, BBQ, Mediterranean, Fast Food\"\nDinner: 1918 Bistro & Grill, Dallas, Cost: $90, Cuisines: \"Tea, Pizza, BBQ, Seafood\"\nAccommodation: Luxury Williamsburg duplex, private roof terrace, Dallas, Cost: $241, Maximum Occupancy: 3, House Rules: No visitors, Minimum Nights: 4\n\nNumber of People = 1\nTotal Cost = $53 (Transportation) + $38 (Lunch) + $90 (Dinner) + $241 (Accommodation) = $422\nAccommodation Minimum Nights: 1/4\n\nDay 6: March 23, 2022\nCurrent City: Dallas\nTransportation: -\nBreakfast: Cafe Coffee Day, Dallas, Cost: $22, Cuisines: \"Tea, BBQ, Desserts, Italian\"\nAttraction: Reunion Tower, Dallas\nLunch: Aravali Owls, Dallas, Cost: $53, Cuisines: \"Pizza, Italian, Bakery, Fast Food, Cafe\"\nDinner: Yanki Sizzlers, Dallas, Cost: $96, Cuisines: \"Cafe, French, Tea, Mediterranean\"\nAccommodation: Luxury Williamsburg duplex, private roof terrace, Dallas, Cost: $241, Maximum Occupancy: 3, House Rules: No visitors, Minimum Nights: 4\n\nNumber of People = 1\nTotal Cost = $22 (Breakfast) + $53 (Lunch) + $96 (Dinner) + $241 (Accommodation) = $412\nAccommodation Minimum Nights: 2/4\n\nDay 7: March 24, 2022\nCurrent City: from Dallas to Daytona Beach\nTransportation: Flight Number: F4045344, from Dallas to Daytona Beach, Departure Time: 12:44, Arrival Time: 16:33, Cost: $222\nBreakfast: -\nAttraction: -\nLunch: -\nDinner: -\nAccommodation: -\n\nNumber of People = 1\nTotal Cost = $222 (Transportation) = $222\n\nTotal cost across all days = $617 + $658 + $218 + $319 + $422 + $412 + $222 = $2868\n\nRemaining Budget: $3600 - $2868 = $732\n\nCuisines: The prompt specifies no cuisines, so all cuisines constraints are satisfied.", "gpt-4-1106-preview_direct_sole-planning_parsed_results": [{"day": 1, "current_city": "from Daytona Beach to Corpus Christi", "transportation": "Self-driving, from Daytona Beach to Corpus Christi, Duration: 16 hours 54 mins, Distance: 1874 km", "breakfast": "-", "attraction": "-", "lunch": "-", "dinner": "-", "accommodation": "My Little Guest Apartment, Corpus Christi"}, {"day": 2, "current_city": "Corpus Christi", "transportation": "-", "breakfast": "Confeitaria Colombo, Corpus Christi", "attraction": "Texas State Aquarium, Corpus Christi", "lunch": "The Binge Box Cafe, Corpus Christi", "dinner": "Sangeetha Vegetarian Restaurant, Corpus Christi", "accommodation": "My Little Guest Apartment, Corpus Christi"}, {"day": 3, "current_city": "from Corpus Christi to San Antonio", "transportation": "Self-driving, from Corpus Christi to San Antonio, Duration: 2 hours 3 mins, Distance: 231 km", "breakfast": "-", "attraction": "San Antonio River Walk, San Antonio", "lunch": "Cafe Le Rue @ The Landings, San Antonio", "dinner": "Barbeque Nation, San Antonio", "accommodation": "Williamsburg Gardens Flat, Large Room Private Bath, San Antonio"}, {"day": 4, "current_city": "San Antonio", "transportation": "-", "breakfast": "The Kylin Experience - Holiday Inn, San Antonio", "attraction": "The Alamo, San Antonio", "lunch": "Cream Stone, San Antonio", "dinner": "Martin's BBQ, San Antonio", "accommodation": "Williamsburg Gardens Flat, Large Room Private Bath, San Antonio"}, {"day": 5, "current_city": "from San Antonio to Dallas", "transportation": "Flight Number: F3984244, from San Antonio to Dallas, Departure Time: 10:10, Arrival Time: 11:10", "breakfast": "-", "attraction": "The Dallas World Aquarium, Dallas", "lunch": "Coconuts Fish Cafe, Dallas", "dinner": "1918 Bistro & Grill, Dallas", "accommodation": "Luxury Williamsburg duplex, private roof terrace, Dallas"}, {"day": 6, "current_city": "Dallas", "transportation": "-", "breakfast": "Cafe Coffee Day, Dallas", "attraction": "Reunion Tower, Dallas", "lunch": "Aravali Owls, Dallas", "dinner": "Yanki Sizzlers, Dallas", "accommodation": "Luxury Williamsburg duplex, private roof terrace, Dallas"}, {"day": 7, "current_city": "from Dallas to Daytona Beach", "transportation": "Flight Number: F4045344, from Dallas to Daytona Beach, Departure Time: 12:44, Arrival Time: 16:33", "breakfast": "-", "attraction": "-", "lunch": "-", "dinner": "-", "accommodation": "-"}]}]