[{"gpt-4-1106-preview_direct_sole-planning_results": "Travel Plan:\n\nDay 1: March 12, 2022\nCurrent City: from Nashville to Pittsburgh\nTransportation: Flight Number: F3947470, from Nashville to Pittsburgh, Departure Time: 09:54, Arrival Time: 12:15, Cost: 142 * 6 = 852\nBreakfast: - (Assuming breakfast is had before departure or during the flight)\nAttraction: Pittsburgh Zoo & Aquarium, Pittsburgh, Cost: Free\nLunch: Beijing Cafe, Pittsburgh, Cost: 33 * 6 = 198, Cuisines: \"Desserts, Tea, Pizza, Mexican, Indian\"\nAttraction: The Andy Warhol Museum, Pittsburgh, Cost: Free\nDinner: Gian Ji Punjabi Dhaba, Pittsburgh, Cost: 19 * 6 = 114, Cuisines: \"Tea, Cafe, Pizza, Fast Food, Chinese\"\nAccommodation: Sunny 1 BR Brooklyn Loft Apartment, Pittsburgh, Cost: 60 * 6 / 2 = 180, Maximum Occupancy: 2, House Rules: No Visitors, Minimum Nights: 4\n\nNumber of People = 6\nTotal Cost = 852 + 198 + 114 + 180 = 1344\nAccommodation Minimum Nights: 1/4\n\nDay 2: March 13, 2022\nCurrent City: Pittsburgh\nTransportation: -\nBreakfast: Embassy, Pittsburgh, Cost: 97 * 6 = 582, Cuisines: \"French, Bakery, Indian, Pizza\"\nAttraction: Carnegie Museum of Art, Pittsburgh, Cost: Free\nLunch: Maharaja Bhog, Pittsburgh, Cost: 52 * 6 = 312, Cuisines: \"Cafe, Pizza\"\nAttraction: Point State Park, Pittsburgh, Cost: Free\nDinner: Indus Flavour, Pittsburgh, Cost: 67 * 6 = 402, Cuisines: \"Tea, Italian, French, Bakery, Cafe, Seafood\"\nAccommodation: Sunny 1 BR Brooklyn Loft Apartment, Pittsburgh, Cost: 180\n\nNumber of People = 6\nTotal Cost = 582 + 312 + 402 + 180 = 1476\nAccommodation Minimum Nights: 2/4\n\nDay 3: March 14, 2022\nCurrent City: from Pittsburgh to Philadelphia\nTransportation: Flight Number: F4059511, from Pittsburgh to Philadelphia, Departure Time: 06:52, Arrival Time: 07:56, Cost: 77 * 6 = 462\nBreakfast: - (Assuming breakfast is had before departure or during the flight)\nAttraction: Independence National Historical Park, Philadelphia, Cost: Free\nLunch: Hong Kong Cafe, Philadelphia, Cost: 47 * 6 = 282, Cuisines: \"Tea, Pizza, Italian, BBQ, Cafe\"\nAttraction: Philadelphia's Magic Gardens, Philadelphia, Cost: Free\nDinner: Red Mesa Cantina, Philadelphia, Cost: 36 * 6 = 216, Cuisines: \"Tea, Cafe, American, Fast Food\"\nAccommodation: Industrial Loft Living in NYC, Philadelphia, Cost: 178 * 6 / 3 = 356, Maximum Occupancy: 3, House Rules: No Smoking, Minimum Nights: 4\n\nNumber of People = 6\nTotal Cost = 462 + 282 + 216 + 356 = 1316\nAccommodation Minimum Nights: 1/4\n\nDay 4: March 15, 2022\nCurrent City: Philadelphia\nTransportation: -\nBreakfast: Red Ginger Sushi, Grill & Bar, Philadelphia, Cost: 98 * 6 = 588, Cuisines: \"Tea, Cafe, Indian, Fast Food\"\nAttraction: Philadelphia Museum of Art, Philadelphia, Cost: Free\nLunch: Marukame Udon, Philadelphia, Cost: 100 * 6 = 600, Cuisines: \"Tea, Pizza, Italian, BBQ, Fast Food, Chinese\"\nAttraction: Liberty Bell, Philadelphia, Cost: Free\nDinner: The Moon Under Water, Philadelphia, Cost: 94 * 6 = 564, Cuisines: \"Pizza, Italian, BBQ, Bakery, Fast Food, Mediterranean\"\nAccommodation: Industrial Loft Living in NYC, Philadelphia, Cost: 356\n\nNumber of People = 6\nTotal Cost = 588 + 600 + 564 + 356 = 2108\nAccommodation Minimum Nights: 2/4\n\nDay 5: March 16, 2022\nCurrent City: from Philadelphia to Nashville\nTransportation: Flight Number: F4006254, from Philadelphia to Nashville, Departure Time: 05:13, Arrival Time: 06:07, Cost: 142 * 6 = 852\nBreakfast: - (Assuming breakfast is had before departure or during the flight)\nAttraction: - (Assuming the group will head directly to the airport)\nLunch: - (Assuming lunch is had after arrival in Nashville)\nDinner: - (Assuming dinner is had in Nashville)\nAccommodation: -\n\nNumber of People = 6\nTotal Cost = 852\n\nTotal cost across all days = 1344 + 1476 + 1316 + 2108 + 852 = 7096\nCuisines: The prompt specifies no cuisines, so all cuisines constraints are satisfied.\n\nRemaining Budget: $15,100 - $7,096 = $8,004\n\nNote: The attractions listed as \"Cost: Free\" are assumed to be free of charge based on the provided information. If there is an entry fee, it was not listed in the reference information provided.", "gpt-4-1106-preview_direct_sole-planning_parsed_results": [{"day": 1, "current_city": "from Nashville to Pittsburgh", "transportation": "Flight Number: F3947470, from Nashville to Pittsburgh, Departure Time: 09:54, Arrival Time: 12:15", "breakfast": "-", "attraction": "Pittsburgh Zoo & Aquarium, Pittsburgh;The Andy Warhol Museum, Pittsburgh;", "lunch": "Beijing Cafe, Pittsburgh", "dinner": "Gian Ji Punjabi Dhaba, Pittsburgh", "accommodation": "Sunny 1 BR Brooklyn Loft Apartment, Pittsburgh"}, {"day": 2, "current_city": "Pittsburgh", "transportation": "-", "breakfast": "Embassy, Pittsburgh", "attraction": "Carnegie Museum of Art, Pittsburgh;Point State Park, Pittsburgh;", "lunch": "Maharaja Bhog, Pittsburgh", "dinner": "Indus Flavour, Pittsburgh", "accommodation": "Sunny 1 BR Brooklyn Loft Apartment, Pittsburgh"}, {"day": 3, "current_city": "from Pittsburgh to Philadelphia", "transportation": "Flight Number: F4059511, from Pittsburgh to Philadelphia, Departure Time: 06:52, Arrival Time: 07:56", "breakfast": "-", "attraction": "Independence National Historical Park, Philadelphia;Philadelphia's Magic Gardens, Philadelphia;", "lunch": "Hong Kong Cafe, Philadelphia", "dinner": "Red Mesa Cantina, Philadelphia", "accommodation": "Industrial Loft Living in NYC, Philadelphia"}, {"day": 4, "current_city": "Philadelphia", "transportation": "-", "breakfast": "Red Ginger Sushi, Grill & Bar, Philadelphia", "attraction": "Philadelphia Museum of Art, Philadelphia;Liberty Bell, Philadelphia;", "lunch": "Marukame Udon, Philadelphia", "dinner": "The Moon Under Water, Philadelphia", "accommodation": "Industrial Loft Living in NYC, Philadelphia"}, {"day": 5, "current_city": "from Philadelphia to Nashville", "transportation": "Flight Number: F4006254, from Philadelphia to Nashville, Departure Time: 05:13, Arrival Time: 06:07", "breakfast": "-", "attraction": "-", "lunch": "-", "dinner": "-", "accommodation": "-"}]}]