[{"gpt-4-1106-preview_direct_sole-planning_results": "Travel Plan:\n\nDay 1: March 13, 2022\nCurrent City: from Asheville to New York\nTransportation: Flight Number: F3641730, from Asheville to New York, Departure Time: 13:49, Arrival Time: 15:40, Cost: $428 (214 * 2)\nBreakfast: - \nAttraction: Central Park, New York, Cost: $0 (Free entry)\nLunch: Gurgaon Hights, New York, Cost: $92 (46 * 2), Cuisines: \"Cafe, American, Indian, Fast Food\"\nDinner: G Dot, New York, Cost: $150 (75 * 2), Cuisines: \"Cafe, Mexican, BBQ\"\nAccommodation: A Contemporary Homelike Stay in the Best of BK, New York, Cost: $456 (228 * 2), Maximum Occupancy: 2, House Rules: No pets & No visitors & No children under 10, Minimum Nights: 2\n\nNumber of People = 2\nTotal Cost = 428 + 92 + 150 + 456 = $1126\nAccommodation Minimum Nights: 1/2\n\nDay 2: March 14, 2022\nCurrent City: New York\nTransportation: -\nBreakfast: Green Chick Chop, New York, Cost: $52 (26 * 2), Cuisines: \"Tea, French, Cafe, Seafood\"\nAttraction: Statue of Liberty, New York, Cost: $0 (Free entry)\nLunch: Goosebumps, New York, Cost: $188 (94 * 2), Cuisines: \"Chinese, Pizza, Bakery\"\nDinner: Rambhog, New York, Cost: $190 (95 * 2), Cuisines: \"Tea, Seafood, Mexican, Fast Food\"\nAccommodation: A Contemporary Homelike Stay in the Best of BK, New York, Cost: $456, Maximum Occupancy: 2, House Rules: No pets & No visitors & No children under 10, Minimum Nights: 2\n\nNumber of People = 2\nTotal Cost = 52 + 188 + 190 + 456 = $886\nAccommodation Minimum Nights: 2/2\n\nDay 3: March 15, 2022\nCurrent City: from New York to Buffalo\nTransportation: Flight Number: F3641101, from New York to Buffalo, Departure Time: 11:59, Arrival Time: 13:09, Cost: $122 (61 * 2)\nBreakfast: Sir John Bakery Cafe, New York, Cost: $156 (78 * 2), Cuisines: \"Pizza, Bakery, Desserts\"\nAttraction: Buffalo and Erie County Botanical Gardens, Buffalo, Cost: $0 (Free entry)\nLunch: Shokitini, Buffalo, Cost: $82 (41 * 2), Cuisines: \"Tea, Cafe, Pizza, Mexican, Chinese, Seafood\"\nDinner: Tibby's New Orleans Kitchen, Buffalo, Cost: $96 (48 * 2), Cuisines: \"Seafood, Indian, BBQ, Italian\"\nAccommodation: Cozy Studio in Heart of Ft Greene, Buffalo, Cost: $400 (200 * 2), Maximum Occupancy: 3, House Rules: No pets & No children under 10, Minimum Nights: 4\n\nNumber of People = 2\nTotal Cost = 122 + 156 + 82 + 96 + 400 = $856\nAccommodation Minimum Nights: 1/4\n\nDay 4: March 16, 2022\nCurrent City: Buffalo\nTransportation: -\nBreakfast: Punjab Grill, Buffalo, Cost: $50 (25 * 2), Cuisines: \"Bakery, BBQ, Desserts, Seafood\"\nAttraction: The Buffalo Zoo, Buffalo, Cost: $0 (Free entry)\nLunch: Pinch Of Spice, Buffalo, Cost: $168 (84 * 2), Cuisines: \"Cafe, Desserts, Seafood\"\nDinner: Red Mango, Buffalo, Cost: $36 (18 * 2), Cuisines: \"Mexican, Bakery, BBQ, Fast Food, Cafe, American\"\nAccommodation: Cozy Studio in Heart of Ft Greene, Buffalo, Cost: $400, Maximum Occupancy: 3, House Rules: No pets & No children under 10, Minimum Nights: 4\n\nNumber of People = 2\nTotal Cost = 50 + 168 + 36 + 400 = $654\nAccommodation Minimum Nights: 2/4\n\nDay 5: March 17, 2022\nCurrent City: from Buffalo to Asheville\nTransportation: Self-driving, from Buffalo to Asheville, Cost: $110 (55 * 2)\nBreakfast: Shama Chicken Corner, Buffalo, Cost: $50 (25 * 2), Cuisines: \"Tea, Chinese, Desserts\"\nAttraction: -\nLunch: -\nDinner: -\nAccommodation: -\n\nNumber of People = 2\nTotal Cost = 110 + 50 = $160\n\nTotal cost across all days = 1126 + 886 + 856 + 654 + 160 = $3682\nCuisines: Mexican and Chinese cuisines were included in the plan as requested.\n\nRemaining Budget: $4700 - $3682 = $1018\n\nPlease note that the attractions listed as free entry may have other associated costs not listed in the reference information, such as transportation to the site or special exhibit fees. The plan assumes no additional costs for these attractions.", "gpt-4-1106-preview_direct_sole-planning_parsed_results": [{"day": 1, "current_city": "from Asheville to New York", "transportation": "Flight Number: F3641730, from Asheville to New York, Departure Time: 13:49, Arrival Time: 15:40", "breakfast": "-", "attraction": "Central Park, New York;", "lunch": "Gurgaon Hights, New York", "dinner": "G Dot, New York", "accommodation": "A Contemporary Homelike Stay in the Best of BK, New York"}, {"day": 2, "current_city": "New York", "transportation": "-", "breakfast": "Green Chick Chop, New York", "attraction": "Statue of Liberty, New York;", "lunch": "Goosebumps, New York", "dinner": "Rambhog, New York", "accommodation": "A Contemporary Homelike Stay in the Best of BK, New York"}, {"day": 3, "current_city": "from New York to Buffalo", "transportation": "Flight Number: F3641101, from New York to Buffalo, Departure Time: 11:59, Arrival Time: 13:09", "breakfast": "Sir John Bakery Cafe, New York", "attraction": "Buffalo and Erie County Botanical Gardens, Buffalo;", "lunch": "Shokitini, Buffalo", "dinner": "Tibby's New Orleans Kitchen, Buffalo", "accommodation": "Cozy Studio in Heart of Ft Greene, Buffalo"}, {"day": 4, "current_city": "Buffalo", "transportation": "-", "breakfast": "Punjab Grill, Buffalo", "attraction": "The Buffalo Zoo, Buffalo;", "lunch": "Pinch Of Spice, Buffalo", "dinner": "Red Mango, Buffalo", "accommodation": "Cozy Studio in Heart of Ft Greene, Buffalo"}, {"day": 5, "current_city": "from Buffalo to Asheville", "transportation": "Self-driving, from Buffalo to Asheville", "breakfast": "Shama Chicken Corner, Buffalo", "attraction": "-", "lunch": "-", "dinner": "-", "accommodation": "-"}]}]