[{"gpt-4-1106-preview_direct_sole-planning_results": "Travel Plan:\n\nDays: 1,\nCurrent City: from Oklahoma City to Alamosa (Colorado),\nTransportation: Self-driving, from Oklahoma City to Alamosa, duration: 8 hours 53 mins, distance: 922 km, cost: 46\nBreakfast: -,\nAttraction: -,\nLunch: -,\nDinner: Atlanta Highway Seafood Market, Alamosa (Colorado), cost: 68, cuisines: \u201cFast Food, Desserts, Seafood\u201d\nAccommodation: Comfortable studio suite in midtown Manhattan, Alamosa (Colorado), cost: 67, room type: Entire home/apt, house rules: No parties & No smoking & No visitors, minimum nights: 30, maximum occupancy: 2\n\nNumber of people = 1\nTotal cost = 46 + 68 + 67 = 181\nAccommodation minimum nights:  1/30\n\nDays: 2,\nCurrent City: Alamosa (Colorado),\nTransportation: -,\nBreakfast: Riverwalk Cafe, Alamosa (Colorado), cost: 97, cuisines: \u201cTea, Pizza, Fast Food\u201d\nAttraction: San Luis Valley Museum | Alamosa, Alamosa (Colorado); Rio Grande Farm Park, Alamosa (Colorado);\nLunch: Cafe LazyMojo, Alamosa (Colorado), cost: 26, cuisines: \u201cTea, Pizza, American, Fast Food\u201d\nDinner: The Arena, Alamosa (Colorado), cost: 85, cuisines: \u201cTea, French, Desserts\u201d\nAccommodation: Comfortable studio suite in midtown Manhattan, Alamosa (Colorado), cost: 67, room type: Entire home/apt, house rules: No parties & No smoking & No visitors, minimum nights: 30, maximum occupancy: 2\n\nNumber of people = 1\nTotal cost = 97 + 26 + 85 + 67 = 275\nAccommodation minimum nights:  2/30\n\nDays: 3,\nCurrent City: from Alamosa to Grand Junction (Colorado),\nTransportation: Self-driving, from Alamosa to Grand Junction, duration: 4 hours 29 mins, distance: 396 km, cost: 19\nBreakfast: -,\nAttraction: Museum of the West, Museums of Western Colorado, Grand Junction (Colorado); Eureka! McConnell Science Museum, Grand Junction (Colorado);\nLunch: 2 Dog, Grand Junction (Colorado), cost: 29, cuisines: \u201cDesserts, BBQ, Fast Food, Cafe, American\u201d\nDinner: Punjab Da Pind, Grand Junction (Colorado), cost: 52, cuisines: \u201cDesserts, Pizza, Bakery, Chinese, Mediterranean, Seafood\u201d\nAccommodation: NYC Apartment near Central Park!, Grand Junction (Colorado), cost: 1118, room type: Entire home/apt, house rules: No children under 10, minimum nights: 3, maximum occupancy: 5\n\nNumber of people = 1\nTotal cost = 19 + 29 + 52 + 1118 = 1218\nAccommodation minimum nights:  1/3\n\nDays: 4,\nCurrent City: Grand Junction (Colorado),\nTransportation: -,\nBreakfast: Austin's BBQ and Oyster Bar, Grand Junction (Colorado), cost: 15, cuisines: \u201cTea, Bakery, Fast Food, Indian, Seafood\u201d\nAttraction: Bananas Fun Park, Grand Junction (Colorado); Western Colorado Botanical Gardens, Grand Junction (Colorado);\nLunch: Shanghai Bar & Lounge - The Bristol Hotel, Grand Junction (Colorado), cost: 31, cuisines: \u201cCafe, Pizza\u201d\nDinner: Food Daddy, Grand Junction (Colorado), cost: 64, cuisines: \u201cBakery, Desserts, Seafood\u201d\nAccommodation: NYC Apartment near Central Park!, Grand Junction (Colorado), cost: 1118, room type: Entire home/apt, house rules: No children under 10, minimum nights: 3, maximum occupancy: 5\n\nNumber of people = 1\nTotal cost = 15 + 31 + 64 + 1118 = 1228\nAccommodation minimum nights:  2/3\n\nDays: 5,\nCurrent City: from Grand Junction to Durango (Colorado),\nTransportation: Self-driving, from Grand Junction to Durango, duration: 3 hours 33 mins, distance: 269 km, cost: 13\nBreakfast: -,\nAttraction: Animas Museum, Durango (Colorado); The Powerhouse, Durango (Colorado);\nLunch: Samurai Japanese Cuisine & Sushi Bar, Durango (Colorado), cost: 67, cuisines: \u201cBakery, Desserts, Fast Food\u201d\nDinner: Dub's High on the Hog, Durango (Colorado), cost: 98, cuisines: \u201cTea, Italian, French, Cafe, Seafood\u201d\nAccommodation: Lux 1BR in the heart of NYC Theater district!, Durango (Colorado), cost: 81, room type: Entire home/apt, house rules: No children under 10, minimum nights: 30, maximum occupancy: 3\n\nNumber of people = 1\nTotal cost = 13 + 67 + 98 + 81 = 259\nAccommodation minimum nights:  1/30\n\nDays: 6,\nCurrent City: Durango (Colorado),\nTransportation: -,\nBreakfast: Asian Haus, Durango (Colorado), cost: 26, cuisines: \u201cFast Food, Seafood, Pizza, Italian\u201d\nAttraction: Durango & Silverton Narrow Gauge Railroad, Durango (Colorado); Oxbow Park and Preserve, Durango (Colorado);\nLunch: The Mashal, Durango (Colorado), cost: 85, cuisines: \u201cItalian, BBQ, Fast Food, Cafe, American, Seafood\u201d\nDinner: Kansar Gujarati Thali, Durango (Colorado), cost: 96, cuisines: \u201cPizza, American, Seafood\u201d\nAccommodation: Lux 1BR in the heart of NYC Theater district!, Durango (Colorado), cost: 81, room type: Entire home/apt, house rules: No children under 10, minimum nights: 30, maximum occupancy: 3\n\nNumber of people = 1\nTotal cost = 26 + 85 + 96 + 81 = 288\nAccommodation minimum nights:  2/30\n\nDays: 7,\nCurrent City: from Durango to Oklahoma City,\nTransportation: Self-driving, from Durango to Oklahoma City, duration: 11 hours 13 mins, distance: 1,212 km, cost: 60\nBreakfast: -,\nAttraction: -,\nLunch: -,\nDinner: -,\nAccommodation: -\n\nNumber of people = 1\nTotal cost = 60\n\nTotal cost across all days = 181 + 275 + 1218 + 1228 + 259 + 288 + 60 = 3509\n\nUnfortunately, the total cost exceeds the budget of $3,000. To adjust the plan within the budget, we can consider changing the accommodation to a more affordable option or reducing the number of attractions and meals at restaurants. Please let me know how you would like to proceed, or if you have any specific preferences for adjustments.", "gpt-4-1106-preview_direct_sole-planning_parsed_results": [{"day": 1, "current_city": "from Oklahoma City to Alamosa", "transportation": "Self-driving, from Oklahoma City to Alamosa, duration: 8 hours 53 mins, distance: 922 km", "breakfast": "-", "attraction": "-", "lunch": "-", "dinner": "Atlanta Highway Seafood Market, Alamosa", "accommodation": "Comfortable studio suite in midtown Manhattan, Alamosa"}, {"day": 2, "current_city": "Alamosa", "transportation": "-", "breakfast": "Riverwalk Cafe, Alamosa", "attraction": "San Luis Valley Museum | Alamosa, Alamosa;Rio Grande Farm Park, Alamosa;", "lunch": "Cafe LazyMojo, Alamosa", "dinner": "The Arena, Alamosa", "accommodation": "Comfortable studio suite in midtown Manhattan, Alamosa"}, {"day": 3, "current_city": "from Alamosa to Grand Junction", "transportation": "Self-driving, from Alamosa to Grand Junction, duration: 4 hours 29 mins, distance: 396 km", "breakfast": "-", "attraction": "Museum of the West, Museums of Western Colorado, Grand Junction;Eureka! McConnell Science Museum, Grand Junction;", "lunch": "2 Dog, Grand Junction", "dinner": "Punjab Da Pind, Grand Junction", "accommodation": "NYC Apartment near Central Park!, Grand Junction"}, {"day": 4, "current_city": "Grand Junction", "transportation": "-", "breakfast": "Austin's BBQ and Oyster Bar, Grand Junction", "attraction": "Bananas Fun Park, Grand Junction;Western Colorado Botanical Gardens, Grand Junction;", "lunch": "Shanghai Bar & Lounge - The Bristol Hotel, Grand Junction", "dinner": "Food Daddy, Grand Junction", "accommodation": "NYC Apartment near Central Park!, Grand Junction"}, {"day": 5, "current_city": "from Grand Junction to Durango", "transportation": "Self-driving, from Grand Junction to Durango, duration: 3 hours 33 mins, distance: 269 km", "breakfast": "-", "attraction": "Animas Museum, Durango;The Powerhouse, Durango;", "lunch": "Samurai Japanese Cuisine & Sushi Bar, Durango", "dinner": "Dub's High on the Hog, Durango", "accommodation": "Lux 1BR in the heart of NYC Theater district!, Durango"}, {"day": 6, "current_city": "Durango", "transportation": "-", "breakfast": "Asian Haus, Durango", "attraction": "Durango & Silverton Narrow Gauge Railroad, Durango;Oxbow Park and Preserve, Durango;", "lunch": "The Mashal, Durango", "dinner": "Kansar Gujarati Thali, Durango", "accommodation": "Lux 1BR in the heart of NYC Theater district!, Durango"}, {"day": 7, "current_city": "from Durango to Oklahoma City", "transportation": "Self-driving, from Durango to Oklahoma City, duration: 11 hours 13 mins, distance: 1,212 km", "breakfast": "-", "attraction": "-", "lunch": "-", "dinner": "-", "accommodation": "-"}]}]