[{"gpt-4-1106-preview_direct_sole-planning_results": "Travel Plan:\n\nDays: 1,\nCurrent City: from Fort Lauderdale to Milwaukee,\nTransportation: Self-driving, from Fort Lauderdale to Milwaukee, duration: 21 hours 8 mins, distance: 2,340 km, cost: 117\nBreakfast: -,\nAttraction: -,\nLunch: -,\nDinner: Cool Basil, Milwaukee, cost: 40, cuisines: \u201cChinese, Pizza, French, Fast Food, Cafe\u201d\nAccommodation: Affordable bedroom in the East Village!, Milwaukee, cost: 184, room type: Private room, house rules: No parties, minimum nights: 2, maximum occupancy: 2\n\nNumber of people = 2\nTotal cost = (117 * 2) + (40 * 2) + 184 = 498\nAccommodation minimum nights: 1/2\n\nDays: 2,\nCurrent City: Milwaukee,\nTransportation: -,\nBreakfast: Shankar Sweets, Milwaukee, cost: 66, cuisines: \u201cTea, Bakery, Pizza, Fast Food\u201d\nAttraction: Milwaukee Art Museum, Milwaukee; Milwaukee Public Museum, Milwaukee;,\nLunch: Berco's, Milwaukee, cost: 91, cuisines: \u201cDesserts, Pizza, Italian, Cafe, Seafood\u201d\nDinner: The Chinese Kitchen, Milwaukee, cost: 23, cuisines: \u201cFast Food, Bakery, Mediterranean, Italian\u201d\nAccommodation: Affordable bedroom in the East Village!, Milwaukee, cost: 184, room type: Private room, house rules: No parties, minimum nights: 2, maximum occupancy: 2\n\nNumber of people = 2\nTotal cost = (66 + 91 + 23) * 2 + 184 = 544\nAccommodation minimum nights: 2/2 (Done!)\n\nDays: 3,\nCurrent City: Milwaukee to Fort Lauderdale,\nTransportation: Flight Number: F3942425, from Milwaukee to Fort Lauderdale, Departure Time: 06:07, Arrival Time: 10:25, cost: 289\nBreakfast: -,\nAttraction: -,\nLunch: -,\nDinner: -,\nAccommodation: -\n\nNumber of people = 2\nTotal cost = 289 * 2 = 578\n\nTotal cost across all days = 498 + 544 + 578 = 1,620\n\nUnfortunately, the total cost exceeds the budget of $1,100. Adjustments need to be made to fit the budget. Since self-driving is significantly cheaper than flying, we will adjust the return transportation to self-driving to reduce costs.\n\nAdjusted Travel Plan:\n\nDays: 3,\nCurrent City: Milwaukee to Fort Lauderdale,\nTransportation: Self-driving, from Milwaukee to Fort Lauderdale, duration: 21 hours 9 mins, distance: 2,336 km, cost: 116\nBreakfast: -,\nAttraction: -,\nLunch: -,\nDinner: -,\nAccommodation: -\n\nNumber of people = 2\nTotal cost = 116 * 2 = 232\n\nAdjusted total cost across all days = 498 + 544 + 232 = 1,274\n\nThe adjusted total cost still exceeds the budget. Further adjustments are needed. We will remove the dinner on Day 1 to fit the budget.\n\nFinal Adjusted Travel Plan:\n\nDays: 1,\nCurrent City: from Fort Lauderdale to Milwaukee,\nTransportation: Self-driving, from Fort Lauderdale to Milwaukee, duration: 21 hours 8 mins, distance: 2,340 km, cost: 117\nBreakfast: -,\nAttraction: -,\nLunch: -,\nDinner: -,\nAccommodation: Affordable bedroom in the East Village!, Milwaukee, cost: 184, room type: Private room, house rules: No parties, minimum nights: 2, maximum occupancy: 2\n\nNumber of people = 2\nTotal cost = 117 * 2 + 184 = 418\nAccommodation minimum nights: 1/2\n\nFinal total cost across all days = 418 + 544 + 232 = 1,194\n\nThe final adjusted total cost is still over budget. Since the budget is very tight and we have already minimized the costs by choosing the cheapest transportation and accommodation options, it is not possible to create a travel plan that includes meals, attractions, and accommodation within the $1,100 budget while also adhering to all the constraints.", "gpt-4-1106-preview_direct_sole-planning_parsed_results": [{"day": 1, "current_city": "from Fort Lauderdale to Milwaukee", "transportation": "Self-driving, from Fort Lauderdale to Milwaukee, duration: 21 hours 8 mins, distance: 2,340 km", "breakfast": "-", "attraction": "-", "lunch": "-", "dinner": "-", "accommodation": "Affordable bedroom in the East Village!, Milwaukee"}, {"day": 2, "current_city": "Milwaukee", "transportation": "-", "breakfast": "Shankar Sweets, Milwaukee", "attraction": "Milwaukee Art Museum, Milwaukee;Milwaukee Public Museum, Milwaukee;", "lunch": "Berco's, Milwaukee", "dinner": "The Chinese Kitchen, Milwaukee", "accommodation": "Affordable bedroom in the East Village!, Milwaukee"}, {"day": 3, "current_city": "Milwaukee to Fort Lauderdale", "transportation": "Self-driving, from Milwaukee to Fort Lauderdale, duration: 21 hours 9 mins, distance: 2,336 km", "breakfast": "-", "attraction": "-", "lunch": "-", "dinner": "-", "accommodation": "-"}]}]