[{"gpt-4-1106-preview_direct_sole-planning_results": "Travel Plan:\n\nDays: 1,\nCurrent City: from Daytona Beach to Corpus Christi (Texas),\nTransportation: Self-driving, from Daytona Beach to Corpus Christi, duration: 16 hours 54 mins, distance: 1,874 km, cost: 93\nBreakfast: -,\nAttraction: -,\nLunch: -,\nDinner: Confeitaria Colombo, Corpus Christi (Texas), cost: 11, cuisines: \u201cTea, Chinese, Bakery, Cafe\u201d\nAccommodation: Penthouse Apartment in Chelsea, Corpus Christi (Texas), cost: 412, room type: Entire home/apt, house rules: No children under 10, minimum nights: 2, maximum occupancy: 3\n\nNumber of people = 1\nTotal cost = 93 + 11 + 412 = 516\nAccommodation minimum nights:  1/2\n\nDays: 2,\nCurrent City: Corpus Christi (Texas),\nTransportation: -,\nBreakfast: Sangeetha Vegetarian Restaurant, Corpus Christi (Texas), cost: 91, cuisines: \u201cDesserts, Tea, Pizza, French, BBQ\u201d\nAttraction: Texas State Aquarium, Corpus Christi (Texas); USS Lexington, Corpus Christi (Texas);\nLunch: The Binge Box Cafe, Corpus Christi (Texas), cost: 32, cuisines: \u201cDesserts, Italian, Bakery, Indian, Seafood\u201d\nDinner: Let's Noodle, Corpus Christi (Texas), cost: 32, cuisines: \u201cChinese, Seafood, Desserts, Fast Food\u201d\nAccommodation: Penthouse Apartment in Chelsea, Corpus Christi (Texas), cost: 412, room type: Entire home/apt, house rules: No children under 10, minimum nights: 2, maximum occupancy: 3\n\nNumber of people = 1\nTotal cost = 91 + 32 + 32 + 412 = 567\nAccommodation minimum nights:  2/2 (Done!)\n\nDays: 3,\nCurrent City: from Corpus Christi (Texas) to San Antonio (Texas),\nTransportation: Self-driving, from Corpus Christi to San Antonio, duration: 2 hours 3 mins, distance: 231 km, cost: 11\nBreakfast: -,\nAttraction: San Antonio River Walk, San Antonio (Texas); The Alamo, San Antonio (Texas);\nLunch: Cafe Le Rue @ The Landings, San Antonio (Texas), cost: 19, cuisines: \u201cFrench, Mexican, Cafe, Seafood\u201d\nDinner: Martin's BBQ, San Antonio (Texas), cost: 71, cuisines: \u201cTea, BBQ, Fast Food, Indian, Seafood\u201d\nAccommodation: Spacious, bright room, prime Williamsburg location, San Antonio (Texas), cost: 900, room type: Private room, house rules: No pets, minimum nights: 3, maximum occupancy: 2\n\nNumber of people = 1\nTotal cost = 11 + 19 + 71 + 900 = 1001\nAccommodation minimum nights:  1/3\n\nDays: 4,\nCurrent City: San Antonio (Texas),\nTransportation: -,\nBreakfast: Burger Queen Drive In, San Antonio (Texas), cost: 64, cuisines: \u201cCafe, Bakery, Fast Food\u201d\nAttraction: SeaWorld San Antonio, San Antonio (Texas); San Antonio Botanical Garden, San Antonio (Texas);\nLunch: Cream Stone, San Antonio (Texas), cost: 53, cuisines: \u201cCafe, BBQ, Mediterranean, Desserts\u201d\nDinner: Minerva's Food & Cocktails, San Antonio (Texas), cost: 99, cuisines: \u201cCafe, Bakery, BBQ, Seafood\u201d\nAccommodation: Spacious, bright room, prime Williamsburg location, San Antonio (Texas), cost: 900, room type: Private room, house rules: No pets, minimum nights: 3, maximum occupancy: 2\n\nNumber of people = 1\nTotal cost = 64 + 53 + 99 + 900 = 1116\nAccommodation minimum nights:  2/3\n\nDays: 5,\nCurrent City: from San Antonio (Texas) to Dallas (Texas),\nTransportation: Flight Number: F3672484, from San Antonio to Dallas, Price: 63, DepTime: 10:16, ArrTime: 11:34\nBreakfast: -,\nAttraction: The Dallas World Aquarium, Dallas (Texas); The Sixth Floor Museum at Dealey Plaza, Dallas (Texas);\nLunch: Coconuts Fish Cafe, Dallas (Texas), cost: 38, cuisines: \u201cCafe, BBQ, Mediterranean, Fast Food\u201d\nDinner: 1918 Bistro & Grill, Dallas (Texas), cost: 90, cuisines: \u201cTea, Pizza, BBQ, Seafood\u201d\nAccommodation: Luxury Williamsburg duplex, private roof terrace, Dallas (Texas), cost: 241, room type: Entire home/apt, house rules: No visitors, minimum nights: 4, maximum occupancy: 3\n\nNumber of people = 1\nTotal cost = 63 + 38 + 90 + 241 = 432\nAccommodation minimum nights:  1/4\n\nDays: 6,\nCurrent City: Dallas (Texas),\nTransportation: -,\nBreakfast: Yanki Sizzlers, Dallas (Texas), cost: 96, cuisines: \u201cCafe, French, Tea, Mediterranean\u201d\nAttraction: Reunion Tower, Dallas (Texas); Dallas Museum of Art, Dallas (Texas);\nLunch: Aravali Owls, Dallas (Texas), cost: 53, cuisines: \u201cPizza, Italian, Bakery, Fast Food, Cafe\u201d\nDinner: Kebab Xpress, Dallas (Texas), cost: 93, cuisines: \u201cTea, Bakery, Pizza, Mediterranean\u201d\nAccommodation: Luxury Williamsburg duplex, private roof terrace, Dallas (Texas), cost: 241, room type: Entire home/apt, house rules: No visitors, minimum nights: 4, maximum occupancy: 3\n\nNumber of people = 1\nTotal cost = 96 + 53 + 93 + 241 = 483\nAccommodation minimum nights:  2/4\n\nDays: 7,\nCurrent City: from Dallas (Texas) to Daytona Beach,\nTransportation: Flight Number: F4045344, from Dallas to Daytona Beach, Price: 222, DepTime: 12:44, ArrTime: 16:33\nBreakfast: -,\nAttraction: -,\nLunch: -,\nDinner: -,\nAccommodation: -\n\nNumber of people = 1\nTotal cost = 222\n\nTotal cost across all days = 516 + 567 + 1001 + 1116 + 432 + 483 + 222 = 4337\n\nUnfortunately, the total cost exceeds the budget of $3,600. To adjust the plan within the budget, we may need to consider cheaper accommodation options or remove certain attractions or meals. Please let me know how you would like to proceed.", "gpt-4-1106-preview_direct_sole-planning_parsed_results": [{"day": 1, "current_city": "from Daytona Beach to Corpus Christi", "transportation": "Self-driving, from Daytona Beach to Corpus Christi, duration: 16 hours 54 mins, distance: 1,874 km", "breakfast": "-", "attraction": "-", "lunch": "-", "dinner": "Confeitaria Colombo, Corpus Christi", "accommodation": "Penthouse Apartment in Chelsea, Corpus Christi"}, {"day": 2, "current_city": "Corpus Christi", "transportation": "-", "breakfast": "Sangeetha Vegetarian Restaurant, Corpus Christi", "attraction": "Texas State Aquarium, Corpus Christi;USS Lexington, Corpus Christi;", "lunch": "The Binge Box Cafe, Corpus Christi", "dinner": "Let's Noodle, Corpus Christi", "accommodation": "Penthouse Apartment in Chelsea, Corpus Christi"}, {"day": 3, "current_city": "from Corpus Christi to San Antonio", "transportation": "Self-driving, from Corpus Christi to San Antonio, duration: 2 hours 3 mins, distance: 231 km", "breakfast": "-", "attraction": "San Antonio River Walk, San Antonio;The Alamo, San Antonio;", "lunch": "Cafe Le Rue @ The Landings, San Antonio", "dinner": "Martin's BBQ, San Antonio", "accommodation": "Spacious, bright room, prime Williamsburg location, San Antonio"}, {"day": 4, "current_city": "San Antonio", "transportation": "-", "breakfast": "Burger Queen Drive In, San Antonio", "attraction": "SeaWorld San Antonio, San Antonio;San Antonio Botanical Garden, San Antonio;", "lunch": "Cream Stone, San Antonio", "dinner": "Minerva's Food & Cocktails, San Antonio", "accommodation": "Spacious, bright room, prime Williamsburg location, San Antonio"}, {"day": 5, "current_city": "from San Antonio to Dallas", "transportation": "Flight Number: F3672484, from San Antonio to Dallas, DepTime: 10:16, ArrTime: 11:34", "breakfast": "-", "attraction": "The Dallas World Aquarium, Dallas;The Sixth Floor Museum at Dealey Plaza, Dallas;", "lunch": "Coconuts Fish Cafe, Dallas", "dinner": "1918 Bistro & Grill, Dallas", "accommodation": "Luxury Williamsburg duplex, private roof terrace, Dallas"}, {"day": 6, "current_city": "Dallas", "transportation": "-", "breakfast": "Yanki Sizzlers, Dallas", "attraction": "Reunion Tower, Dallas;Dallas Museum of Art, Dallas;", "lunch": "Aravali Owls, Dallas", "dinner": "Kebab Xpress, Dallas", "accommodation": "Luxury Williamsburg duplex, private roof terrace, Dallas"}, {"day": 7, "current_city": "from Dallas to Daytona Beach", "transportation": "Flight Number: F4045344, from Dallas to Daytona Beach, DepTime: 12:44, ArrTime: 16:33", "breakfast": "-", "attraction": "-", "lunch": "-", "dinner": "-", "accommodation": "-"}]}]