[{"gpt-4-1106-preview_direct_sole-planning_results": "Travel Plan:\n\nDays: 1,\nCurrent City: from Memphis to Minneapolis (Minnesota),\nTransportation: Flight Number: F3836157, from Memphis to Minneapolis, Departure Time: 05:57, Arrival Time: 08:10, cost: 260\nBreakfast: -,\nAttraction: -,\nLunch: -,\nDinner: Troll Tavern, Minneapolis (Minnesota), cost: 71, cuisines: \u201cTea, BBQ, Mediterranean\u201d\nAccommodation: Light-filled Apartment in great area, close 2 all!, Minneapolis (Minnesota), cost: 343, room type: Entire home/apt, maximum occupancy: 2, house rules: No visitors, minimum nights: 1\n\nNumber of people = 4\nTotal cost = 260 * 4 + 71 * 4 + 343 * 2 = 2,184\nAccommodation minimum nights:  1/1\n\nDays: 2,\nCurrent City: Minneapolis (Minnesota),\nTransportation: -,\nBreakfast: The Cafe, Minneapolis (Minnesota), cost: 14, cuisines: \u201cIndian, Mediterranean, Desserts, Seafood\u201d\nAttraction: Minneapolis Sculpture Garden, Minneapolis (Minnesota); Minneapolis Institute of Art, Minneapolis (Minnesota);\nLunch: Court Avenue Brewing Company, Minneapolis (Minnesota), cost: 31, cuisines: \u201cPizza, French, Bakery, BBQ, Seafood\u201d\nDinner: Monkeypod Kitchen by Merriman, Minneapolis (Minnesota), cost: 50, cuisines: \u201cDesserts, Pizza, Bakery, Fast Food, Indian, Mediterranean\u201d\nAccommodation: Light-filled Apartment in great area, close 2 all!, Minneapolis (Minnesota), cost: 343, room type: Entire home/apt, maximum occupancy: 2, house rules: No visitors, minimum nights: 1\n\nNumber of people = 4\nTotal cost = (14 + 31 + 50) * 4 + 343 * 2 = 1,372\nAccommodation minimum nights:  2/1\n\nDays: 3,\nCurrent City: from Minneapolis (Minnesota) to Gustavus (Minnesota),\nTransportation: Taxi, from Minneapolis to Gustavus, duration: 1 hour 9 mins, distance: 110 km, cost: 110\nBreakfast: -,\nAttraction: Glacier Bay National Park Visitor Center, Gustavus (Minnesota);\nLunch: That Madras Place, Gustavus (Minnesota), cost: 36, cuisines: \u201cDesserts, Italian, Bakery, BBQ, Cafe\u201d\nDinner: Hofer's Bakery & Cafe, Gustavus (Minnesota), cost: 34, cuisines: \u201cMexican, Bakery, BBQ, Fast Food, Cafe, American\u201d\nAccommodation: New Furnished Modern Two-Bedroom Apartment, Gustavus (Minnesota), cost: 644, room type: Entire home/apt, maximum occupancy: 3, house rules: No pets, minimum nights: 30\n\nNumber of people = 4\nTotal cost = 110 * 4 + (36 + 34) * 4 + 644 * 2 = 1,656\nAccommodation minimum nights:  1/30 (Note: This accommodation does not meet the minimum nights requirement for the travel dates, but no other options are provided.)\n\nDays: 4,\nCurrent City: Gustavus (Minnesota),\nTransportation: -,\nBreakfast: On The Rocks - The Atrium, Gustavus (Minnesota), cost: 60, cuisines: \u201cDesserts, Tea, Pizza, Italian, Bakery, American\u201d\nAttraction: Cross Sound Express Whale Watching, Gustavus (Minnesota);\nLunch: Tobasco Kitchen, Gustavus (Minnesota), cost: 21, cuisines: \u201cDesserts, Tea, Italian, Mexican, Bakery, Seafood\u201d\nDinner: Imperfecto, Gustavus (Minnesota), cost: 10, cuisines: \u201cTea, Cafe, BBQ, Fast Food\u201d\nAccommodation: New Furnished Modern Two-Bedroom Apartment, Gustavus (Minnesota), cost: 644, room type: Entire home/apt, maximum occupancy: 3, house rules: No pets, minimum nights: 30\n\nNumber of people = 4\nTotal cost = (60 + 21 + 10) * 4 + 644 * 2 = 1,504\nAccommodation minimum nights:  2/30 (Note: This accommodation does not meet the minimum nights requirement for the travel dates, but no other options are provided.)\n\nDays: 5,\nCurrent City: from Gustavus (Minnesota) to Memphis,\nTransportation: Self-driving, from Gustavus to Memphis, duration: 12 hours 3 mins, distance: 1,294 km, cost: 64\nBreakfast: -,\nAttraction: -,\nLunch: -,\nDinner: -,\nAccommodation: -\n\nNumber of people = 4\nTotal cost = 64 * 4 = 256\n\nTotal cost across all days = 2,184 + 1,372 + 1,656 + 1,504 + 256 = 6,972\nCuisines: The prompt specifies no cuisines, so all cuisine constraints are satisfied.\nHouse rules: All accommodations chosen provide private rooms, as required.\n\nNote: The accommodations in Gustavus do not meet the minimum nights requirement as per the provided data. If this is an issue, alternative accommodations would need to be sourced.", "gpt-4-1106-preview_direct_sole-planning_parsed_results": [{"day": 1, "current_city": "from Memphis to Minneapolis", "transportation": "Flight Number: F3836157, from Memphis to Minneapolis, Departure Time: 05:57, Arrival Time: 08:10", "breakfast": "-", "attraction": "-", "lunch": "-", "dinner": "Troll Tavern, Minneapolis", "accommodation": "Light-filled Apartment in great area, close 2 all!, Minneapolis"}, {"day": 2, "current_city": "Minneapolis", "transportation": "-", "breakfast": "The Cafe, Minneapolis", "attraction": "Minneapolis Sculpture Garden, Minneapolis;Minneapolis Institute of Art, Minneapolis;", "lunch": "Court Avenue Brewing Company, Minneapolis", "dinner": "Monkeypod Kitchen by Merriman, Minneapolis", "accommodation": "Light-filled Apartment in great area, close 2 all!, Minneapolis"}, {"day": 3, "current_city": "from Minneapolis to Gustavus", "transportation": "Taxi, from Minneapolis to Gustavus, duration: 1 hour 9 mins, distance: 110 km", "breakfast": "-", "attraction": "Glacier Bay National Park Visitor Center, Gustavus", "lunch": "That Madras Place, Gustavus", "dinner": "Hofer's Bakery & Cafe, Gustavus", "accommodation": "New Furnished Modern Two-Bedroom Apartment, Gustavus"}, {"day": 4, "current_city": "Gustavus", "transportation": "-", "breakfast": "On The Rocks - The Atrium, Gustavus", "attraction": "Cross Sound Express Whale Watching, Gustavus", "lunch": "Tobasco Kitchen, Gustavus", "dinner": "Imperfecto, Gustavus", "accommodation": "New Furnished Modern Two-Bedroom Apartment, Gustavus"}, {"day": 5, "current_city": "from Gustavus to Memphis", "transportation": "Self-driving, from Gustavus to Memphis, duration: 12 hours 3 mins, distance: 1,294 km", "breakfast": "-", "attraction": "-", "lunch": "-", "dinner": "-", "accommodation": "-"}]}]