[{"gpt-4-1106-preview_direct_sole-planning_results": "Travel Plan:\n\nDays: 1,\nCurrent City: from Richmond to Miami (Florida),\nTransportation: Flight Number: F3681647, from Richmond to Miami, Departure Time: 06:28, Arrival Time: 08:53, cost: 316\nBreakfast: -,\nAttraction: -,\nLunch: -,\nDinner: Clocked, Miami (Florida), cost: 49, cuisines: \u201cTea, Italian, Mexican, BBQ, Cafe\u201d\nAccommodation: \"HELLO BROOKLYN\" PARK SIDE VIEW NEWLY RENO APT., Miami (Florida), cost: 789, room type: Entire home/apt, house rules: No parties & No visitors, minimum nights: 1, maximum occupancy: 6\n\nNumber of people = 7\nTotal cost = 316 * 7 + 49 * 7 + 789 = 3,910\nAccommodation minimum nights: 1/1\n\nDays: 2,\nCurrent City: Miami (Florida),\nTransportation: -,\nBreakfast: Papouli's Mediterranean Cafe & Market, Miami (Florida), cost: 26, cuisines: \u201cTea, Desserts\u201d\nAttraction: Jungle Island, Miami (Florida); P\u00e9rez Art Museum Miami, Miami (Florida);\nLunch: AB's Absolute Barbecues, Miami (Florida), cost: 55, cuisines: \u201cDesserts, Tea, Pizza, Italian, Fast Food, American\u201d\nDinner: Anjlika, Miami (Florida), cost: 56, cuisines: \u201cPizza, Italian, Fast Food, Cafe, Mediterranean, Seafood\u201d\nAccommodation: \"HELLO BROOKLYN\" PARK SIDE VIEW NEWLY RENO APT., Miami (Florida), cost: 789, room type: Entire home/apt, house rules: No parties & No visitors, minimum nights: 1, maximum occupancy: 6\n\nNumber of people = 7\nTotal cost = (26 + 55 + 56) * 7 + 789 = 2,072\nAccommodation minimum nights: 2/1\n\nDays: 3,\nCurrent City: from Miami (Florida) to Punta Gorda (Florida),\nTransportation: Taxi, from Miami to Punta Gorda, duration: 2 hours 41 mins, distance: 291 km, cost: 291\nBreakfast: -,\nAttraction: Laishley Park, Punta Gorda (Florida);\nLunch: Urban Cuisine, Punta Gorda (Florida), cost: 84, cuisines: \u201cDesserts, Tea, Mexican, Fast Food, Chinese, Seafood\u201d\nDinner: Nathu's Sweets, Punta Gorda (Florida), cost: 66, cuisines: \u201cTea, Chinese, Desserts, Italian\u201d\nAccommodation: Beautiful Manhattan Apt- 20 min to Times Square, Punta Gorda (Florida), cost: 79, room type: Entire home/apt, house rules: No children under 10, minimum nights: 7, maximum occupancy: 3\n\nNumber of people = 7\nTotal cost = 291 * 7 + (84 + 66) * 7 + 79 * 3 = 3,409\nAccommodation minimum nights: 1/7\n\nDays: 4,\nCurrent City: Punta Gorda (Florida),\nTransportation: -,\nBreakfast: Cookie Shoppe, Punta Gorda (Florida), cost: 44, cuisines: \u201cTea, Bakery, BBQ, Mediterranean, Seafood\u201d\nAttraction: Charlotte Harbor Preserve State Park, Punta Gorda (Florida);\nLunch: China Cafe, Punta Gorda (Florida), cost: 69, cuisines: \u201cDesserts, Bakery, Cafe, Mediterranean, Seafood\u201d\nDinner: G Thal, Punta Gorda (Florida), cost: 61, cuisines: \u201cDesserts, Bakery, Cafe, American, Mediterranean\u201d\nAccommodation: Beautiful Manhattan Apt- 20 min to Times Square, Punta Gorda (Florida), cost: 79, room type: Entire home/apt, house rules: No children under 10, minimum nights: 7, maximum occupancy: 3\n\nNumber of people = 7\nTotal cost = (44 + 69 + 61) * 7 + 79 * 3 = 1,932\nAccommodation minimum nights: 2/7\n\nDays: 5,\nCurrent City: from Punta Gorda (Florida) to Richmond,\nTransportation: Taxi, from Punta Gorda to Richmond, duration: 12 hours 50 mins, distance: 1,434 km, cost: 1434\nBreakfast: -,\nAttraction: -,\nLunch: -,\nDinner: -,\nAccommodation: -\n\nNumber of people = 7\nTotal cost = 1434 * 7 = 10,038\n\nTotal cost across all days = 3,910 + 2,072 + 3,409 + 1,932 + 10,038 = 21,361\n\nUnfortunately, the total cost of $21,361 exceeds the budget of $8,500. Additionally, the accommodation in Punta Gorda does not meet the minimum night requirement for the group size. Adjustments to the travel plan are necessary to meet the budget and accommodation constraints.", "gpt-4-1106-preview_direct_sole-planning_parsed_results": [{"day": 1, "current_city": "from Richmond to Miami", "transportation": "Flight Number: F3681647, from Richmond to Miami, Departure Time: 06:28, Arrival Time: 08:53", "breakfast": "-", "attraction": "-", "lunch": "-", "dinner": "Clocked, Miami", "accommodation": "\"HELLO BROOKLYN\" PARK SIDE VIEW NEWLY RENO APT., Miami"}, {"day": 2, "current_city": "Miami", "transportation": "-", "breakfast": "Papouli's Mediterranean Cafe & Market, Miami", "attraction": "Jungle Island, Miami;P\u00e9rez Art Museum Miami, Miami;", "lunch": "AB's Absolute Barbecues, Miami", "dinner": "Anjlika, Miami", "accommodation": "\"HELLO BROOKLYN\" PARK SIDE VIEW NEWLY RENO APT., Miami"}, {"day": 3, "current_city": "from Miami to Punta Gorda", "transportation": "Taxi, from Miami to Punta Gorda, duration: 2 hours 41 mins, distance: 291 km", "breakfast": "-", "attraction": "Laishley Park, Punta Gorda", "lunch": "Urban Cuisine, Punta Gorda", "dinner": "Nathu's Sweets, Punta Gorda", "accommodation": "Beautiful Manhattan Apt- 20 min to Times Square, Punta Gorda"}, {"day": 4, "current_city": "Punta Gorda", "transportation": "-", "breakfast": "Cookie Shoppe, Punta Gorda", "attraction": "Charlotte Harbor Preserve State Park, Punta Gorda", "lunch": "China Cafe, Punta Gorda", "dinner": "G Thal, Punta Gorda", "accommodation": "Beautiful Manhattan Apt- 20 min to Times Square, Punta Gorda"}, {"day": 5, "current_city": "from Punta Gorda to Richmond", "transportation": "Taxi, from Punta Gorda to Richmond, duration: 12 hours 50 mins, distance: 1434 km", "breakfast": "-", "attraction": "-", "lunch": "-", "dinner": "-", "accommodation": "-"}]}]