[{"gpt-4-1106-preview_direct_sole-planning_results": "Travel Plan:\nDays: 1,\nCurrent City: from Sacramento to Atlanta (Georgia),\nTransportation: Flight Number: F3510904, from Sacramento to Atlanta (Georgia), Departure Time: 06:55, Arrival Time: 14:09, cost: 520\nBreakfast: -,\nAttraction: -,\nLunch: -,\nDinner: Saffron, Atlanta (Georgia), cost: 39, cuisines: \u201cTea, Cafe, Fast Food, Seafood\u201d\nAccommodation: Bright, Modern, Clean, Spacious, Brooklyn Home, Atlanta (Georgia), cost: 1034, maximum occupancy: 4, house rules: No children under 10, minimum nights: 3\n\nNumber of people = 2\nTotal cost = (520 + 39) * 2 + 1034 = 2,152\nAccommodation minimum nights:  1/3\n\nDays: 2,\nCurrent City: Atlanta (Georgia),\nTransportation: -,\nBreakfast: Adda, Atlanta (Georgia), cost: 22, cuisines: \u201cTea, Mexican, Bakery\u201d\nAttraction: Georgia Aquarium, Atlanta (Georgia); World of Coca-Cola, Atlanta (Georgia);\nLunch: Chef Style, Atlanta (Georgia), cost: 59, cuisines: \u201cPizza, American, Desserts, Seafood\u201d\nDinner: Pizza Central, Atlanta (Georgia), cost: 75, cuisines: \u201cCafe, Bakery, BBQ, Fast Food, Chinese, Indian\u201d\nAccommodation: Bright, Modern, Clean, Spacious, Brooklyn Home, Atlanta (Georgia), cost: 1034, maximum occupancy: 4, house rules: No children under 10, minimum nights: 3\n\nNumber of people = 2\nTotal cost = (22 + 59 + 75) * 2 + 1034 = 1,344\nAccommodation minimum nights:  2/3\n\nDays: 3,\nCurrent City: from Atlanta (Georgia) to Sacramento,\nTransportation: Flight Number: F3527027, from Atlanta to Sacramento (Georgia), Departure Time: 08:56, Arrival Time: 10:42, cost: 995\nBreakfast: -,\nAttraction: -,\nLunch: -,\nDinner: -,\nAccommodation: -\n\nNumber of people = 2\nTotal cost = 995 * 2 = 1,990\n\nTotal cost across all days = 2,152 + 1,344 + 1,990 = 5,486\n\nNote: The total cost exceeds the budget of $4,700. Adjustments are needed to meet the budget constraint. Possible adjustments could include selecting a less expensive accommodation or removing some meals or attractions.\n\nCuisines: The prompt specifies no cuisines, so all cuisine constraints are satisfied.\nHouse rules: The chosen accommodation allows parties, as there is no specific rule against it.", "gpt-4-1106-preview_direct_sole-planning_parsed_results": [{"day": 1, "current_city": "from Sacramento to Atlanta (Georgia)", "transportation": "Flight Number: F3510904, from Sacramento to Atlanta (Georgia), Departure Time: 06:55, Arrival Time: 14:09", "breakfast": "-", "attraction": "-", "lunch": "-", "dinner": "Saffron, Atlanta (Georgia)", "accommodation": "Bright, Modern, Clean, Spacious, Brooklyn Home, Atlanta (Georgia)"}, {"day": 2, "current_city": "Atlanta (Georgia)", "transportation": "-", "breakfast": "Adda, Atlanta (Georgia)", "attraction": "Georgia Aquarium, Atlanta (Georgia);World of Coca-Cola, Atlanta (Georgia);", "lunch": "Chef Style, Atlanta (Georgia)", "dinner": "Pizza Central, Atlanta (Georgia)", "accommodation": "Bright, Modern, Clean, Spacious, Brooklyn Home, Atlanta (Georgia)"}, {"day": 3, "current_city": "from Atlanta (Georgia) to Sacramento", "transportation": "Flight Number: F3527027, from Atlanta to Sacramento (Georgia), Departure Time: 08:56, Arrival Time: 10:42", "breakfast": "-", "attraction": "-", "lunch": "-", "dinner": "-", "accommodation": "-"}]}]