[{"gpt-4-1106-preview_direct_sole-planning_results": "Travel Plan:\nDays: 1,\nCurrent City: from Asheville to Baltimore,\nTransportation: Taxi, from Asheville to Baltimore, duration: 7 hours 43 mins, distance: 819 km, cost: 819\nBreakfast: -,\nAttraction: -,\nLunch: -,\nDinner: Los Pablos, Baltimore, cost: 47, cuisines: \u201cIndian, BBQ, Cafe, American, Seafood\u201d\nAccommodation: Contemporary Home Away from Home, Entire house, Baltimore, cost: 290, maximum occupancy: 2, house rules: No visitors, minimum nights: 2\n\nNumber of people = 8\nTotal cost = 819 * 8 + 47 * 8 + 290 * 4 = 8,152\nAccommodation minimum nights:  1/2\n\nDays: 2,\nCurrent City: Baltimore,\nTransportation: -,\nBreakfast: Mr. Dunderbak's Biergarten and Marketplatz, Baltimore, cost: 74, cuisines: \u201cCafe, Pizza, American\u201d\nAttraction: National Aquarium, Baltimore; The Maryland Zoo in Baltimore,\nLunch: The Thai Bowl, Baltimore, cost: 66, cuisines: \u201cBBQ, Pizza, Desserts, Italian\u201d\nDinner: Salt, Baltimore, cost: 56, cuisines: \u201cTea, Bakery, Fast Food, Chinese, American\u201d\nAccommodation: Contemporary Home Away from Home, Entire house, Baltimore, cost: 290, maximum occupancy: 2, house rules: No visitors, minimum nights: 2\n\nNumber of people = 8\nTotal cost = (74 + 66 + 56) * 8 + 290 * 4 = 3,568\nAccommodation minimum nights:  2/2 (Done!)\n\nDays: 3,\nCurrent City: from Baltimore to Asheville,\nTransportation: Taxi, from Baltimore to Asheville, duration: 7 hours 42 mins, distance: 819 km, cost: 819\nBreakfast: -,\nAttraction: -,\nLunch: -,\nDinner: -,\nAccommodation: -\n\nNumber of people = 8\nTotal cost = 819 * 8 = 6,552\n\nTotal cost across all days = 8,152 + 3,568 + 6,552 = 18,272\n\nUnfortunately, the total cost of the travel plan ($18,272) exceeds the specified budget of $6,500. Additionally, the accommodation chosen does not meet the requirement for suitability for children under 10. To adhere to the budget and requirements, we need to revise the travel plan.\n\nRevised Travel Plan:\nDays: 1,\nCurrent City: from Asheville to Baltimore,\nTransportation: Taxi, from Asheville to Baltimore, duration: 7 hours 43 mins, distance: 819 km, cost: 819\nBreakfast: -,\nAttraction: -,\nLunch: -,\nDinner: Los Pablos, Baltimore, cost: 47, cuisines: \u201cIndian, BBQ, Cafe, American, Seafood\u201d\nAccommodation: Cute Family Friendly Vintage Brownstone Living!!, Shared room, Baltimore, cost: 920, maximum occupancy: 1, house rules: No parties & No children under 10, minimum nights: 2\n\nNumber of people = 8\nTotal cost = 819 * 8 + 47 * 8 + 920 = 7,984\nAccommodation minimum nights:  1/2\n\nDays: 2,\nCurrent City: Baltimore,\nTransportation: -,\nBreakfast: Mr. Dunderbak's Biergarten and Marketplatz, Baltimore, cost: 74, cuisines: \u201cCafe, Pizza, American\u201d\nAttraction: National Aquarium, Baltimore; The Maryland Zoo in Baltimore,\nLunch: The Thai Bowl, Baltimore, cost: 66, cuisines: \u201cBBQ, Pizza, Desserts, Italian\u201d\nDinner: Salt, Baltimore, cost: 56, cuisines: \u201cTea, Bakery, Fast Food, Chinese, American\u201d\nAccommodation: Cute Family Friendly Vintage Brownstone Living!!, Shared room, Baltimore, cost: 920, maximum occupancy: 1, house rules: No parties & No children under 10, minimum nights: 2\n\nNumber of people = 8\nTotal cost = (74 + 66 + 56) * 8 + 920 = 2,992\nAccommodation minimum nights:  2/2 (Done!)\n\nDays: 3,\nCurrent City: from Baltimore to Asheville,\nTransportation: Taxi, from Baltimore to Asheville, duration: 7 hours 42 mins, distance: 819 km, cost: 819\nBreakfast: -,\nAttraction: -,\nLunch: -,\nDinner: -,\nAccommodation: -\n\nNumber of people = 8\nTotal cost = 819 * 8 = 6,552\n\nTotal cost across all days = 7,984 + 2,992 + 6,552 = 17,528\n\nThe revised plan still exceeds the budget and does not meet the accommodation requirement for children under 10. We need to make further adjustments to fit within the budget and requirements.\n\nUnfortunately, given the constraints of the budget, the cost of transportation alone (taxi to and from Baltimore) exceeds the budget when multiplied by the number of people (8). Therefore, it is not possible to create a travel plan within the given budget that includes taxi transportation for 8 people to and from Baltimore. We would need to consider alternative, more affordable transportation options or adjust the number of travelers to fit within the budget.", "gpt-4-1106-preview_direct_sole-planning_parsed_results": [{"day": 1, "current_city": "from Asheville to Baltimore", "transportation": "Taxi, from Asheville to Baltimore, duration: 7 hours 43 mins, distance: 819 km", "breakfast": "-", "attraction": "-", "lunch": "-", "dinner": "Los Pablos, Baltimore", "accommodation": "Contemporary Home Away from Home, Baltimore"}, {"day": 2, "current_city": "Baltimore", "transportation": "-", "breakfast": "Mr. Dunderbak's Biergarten and Marketplatz, Baltimore", "attraction": "National Aquarium, Baltimore;The Maryland Zoo in Baltimore;", "lunch": "The Thai Bowl, Baltimore", "dinner": "Salt, Baltimore", "accommodation": "Contemporary Home Away from Home, Baltimore"}, {"day": 3, "current_city": "from Baltimore to Asheville", "transportation": "Taxi, from Baltimore to Asheville, duration: 7 hours 42 mins, distance: 819 km", "breakfast": "-", "attraction": "-", "lunch": "-", "dinner": "-", "accommodation": "-"}, {"day": 1, "current_city": "from Asheville to Baltimore", "transportation": "Taxi, from Asheville to Baltimore, duration: 7 hours 43 mins, distance: 819 km", "breakfast": "-", "attraction": "-", "lunch": "-", "dinner": "Los Pablos, Baltimore", "accommodation": "Cute Family Friendly Vintage Brownstone Living!!, Baltimore"}, {"day": 2, "current_city": "Baltimore", "transportation": "-", "breakfast": "Mr. Dunderbak's Biergarten and Marketplatz, Baltimore", "attraction": "National Aquarium, Baltimore;The Maryland Zoo in Baltimore;", "lunch": "The Thai Bowl, Baltimore", "dinner": "Salt, Baltimore", "accommodation": "Cute Family Friendly Vintage Brownstone Living!!, Baltimore"}, {"day": 3, "current_city": "from Baltimore to Asheville", "transportation": "Taxi, from Baltimore to Asheville, duration: 7 hours 42 mins, distance: 819 km", "breakfast": "-", "attraction": "-", "lunch": "-", "dinner": "-", "accommodation": "-"}]}]