[{"gpt-4-1106-preview_direct_sole-planning_results": "Travel Plan:\nDays: 1,\nCurrent City: from Seattle to Dallas (Texas),\nTransportation: Flight Number: F3669219, from Seattle to Dallas (Texas), Departure Time: 07:42, Arrival Time: 13:36, cost: 625\nBreakfast: -,\nAttraction: -,\nLunch: -,\nDinner: Coconuts Fish Cafe, Dallas (Texas), cost: 38, cuisines: \u201cCafe, BBQ, Mediterranean, Fast Food\u201d\nAccommodation: Spacious, bright room, prime Williamsburg location, Dallas (Texas), cost: 900, maximum occupancy: 2, house rules: No pets, minimum nights: 3\n\nNumber of people = 4\nTotal cost = 625 * 4 + 38 * 4 + 900 * 2 = 4,052\nAccommodation minimum nights:  1/3\n\nDays: 2,\nCurrent City: Dallas (Texas),\nTransportation: -,\nBreakfast: Cafe Gatherings, Dallas (Texas), cost: 17, cuisines: \u201cBakery, Indian, Desserts\u201d\nAttraction: The Dallas World Aquarium, Dallas (Texas); The Sixth Floor Museum at Dealey Plaza, Dallas (Texas);\nLunch: 1918 Bistro & Grill, Dallas (Texas), cost: 90, cuisines: \u201cTea, Pizza, BBQ, Seafood\u201d\nDinner: Yanki Sizzlers, Dallas (Texas), cost: 96, cuisines: \u201cCafe, French, Tea, Mediterranean\u201d\nAccommodation: Spacious, bright room, prime Williamsburg location, Dallas (Texas), cost: 900, maximum occupancy: 2, house rules: No pets, minimum nights: 3\n\nNumber of people = 4\nTotal cost = (17 + 90 + 96) * 4 + 900 * 2 = 2,548\nAccommodation minimum nights:  2/3\n\nDays: 3,\nCurrent City: from Dallas (Texas) to Houston (Texas),\nTransportation: Flight Number: F3667553, from Dallas (Texas) to Houston (Texas), Departure Time: 07:06, Arrival Time: 08:21, cost: 45\nBreakfast: -,\nAttraction: Space Center Houston, Houston (Texas);\nLunch: Jalapenos, Houston (Texas), cost: 57, cuisines: \u201cDesserts, Tea, Cafe, Chinese, Seafood\u201d\nDinner: Super Bakery, Houston (Texas), cost: 30, cuisines: \u201cSeafood, Fast Food\u201d\nAccommodation: Sunny and Airy near Manhattan, Houston (Texas), cost: 499, maximum occupancy: 4, house rules: No pets, minimum nights: 2\n\nNumber of people = 4\nTotal cost = 45 * 4 + (57 + 30) * 4 + 499 = 1,087\nAccommodation minimum nights:  1/2\n\nDays: 4,\nCurrent City: Houston (Texas),\nTransportation: -,\nBreakfast: Earthen Spices, Houston (Texas), cost: 28, cuisines: \u201cTea, Mexican, Bakery, BBQ, Fast Food\u201d\nAttraction: Houston Museum of Natural Science, Houston (Texas); Houston Zoo, Houston (Texas);\nLunch: The BrewMaster - The Mix Fine Dine, Houston (Texas), cost: 52, cuisines: \u201cFrench, Indian, Cafe, Seafood\u201d\nDinner: Pebble Street, Houston (Texas), cost: 73, cuisines: \u201cTea, American, Mediterranean, BBQ\u201d\nAccommodation: Sunny and Airy near Manhattan, Houston (Texas), cost: 499, maximum occupancy: 4, house rules: No pets, minimum nights: 2\n\nNumber of people = 4\nTotal cost = (28 + 52 + 73) * 4 + 499 = 1,301\nAccommodation minimum nights:  2/2 (Done!)\n\nDays: 5,\nCurrent City: from Houston (Texas) to San Antonio (Texas),\nTransportation: Flight Number: F3877522, from Houston (Texas) to San Antonio (Texas), Departure Time: 16:34, Arrival Time: 17:21, cost: 79\nBreakfast: -,\nAttraction: San Antonio River Walk, San Antonio (Texas);\nLunch: Cafe Le Rue @ The Landings, San Antonio (Texas), cost: 19, cuisines: \u201cFrench, Mexican, Cafe, Seafood\u201d\nDinner: Martin's BBQ, San Antonio (Texas), cost: 71, cuisines: \u201cTea, BBQ, Fast Food, Indian, Seafood\u201d\nAccommodation: Spacious, bright room, prime Williamsburg location, San Antonio (Texas), cost: 900, maximum occupancy: 2, house rules: No pets, minimum nights: 3\n\nNumber of people = 4\nTotal cost = 79 * 4 + (19 + 71) * 4 + 900 * 2 = 2,160\nAccommodation minimum nights:  1/3\n\nDays: 6,\nCurrent City: San Antonio (Texas),\nTransportation: -,\nBreakfast: Big Jack's, San Antonio (Texas), cost: 55, cuisines: \u201cTea, Pizza, BBQ\u201d\nAttraction: SeaWorld San Antonio, San Antonio (Texas); San Antonio Museum of Art (SAMA), San Antonio (Texas);\nLunch: Barbeque Nation, San Antonio (Texas), cost: 16, cuisines: \u201cTea, Cafe, Fast Food, Chinese, American\u201d\nDinner: Cream Stone, San Antonio (Texas), cost: 53, cuisines: \u201cCafe, BBQ, Mediterranean, Desserts\u201d\nAccommodation: Spacious, bright room, prime Williamsburg location, San Antonio (Texas), cost: 900, maximum occupancy: 2, house rules: No pets, minimum nights: 3\n\nNumber of people = 4\nTotal cost = (55 + 16 + 53) * 4 + 900 * 2 = 2,072\nAccommodation minimum nights:  2/3\n\nDays: 7,\nCurrent City: from San Antonio (Texas) to Seattle,\nTransportation: Flight Number: F3744881, from San Antonio (Texas) to Seattle, Departure Time: 18:35, Arrival Time: 20:58, cost: 702\nBreakfast: -,\nAttraction: -,\nLunch: -,\nDinner: -,\nAccommodation: -\n\nNumber of people = 4\nTotal cost = 702 * 4 = 2,808\n\nTotal cost across all days = 4,052 + 2,548 + 1,087 + 1,301 + 2,160 + 2,072 + 2,808 = 16,028\n\nUnfortunately, the total cost exceeds the budget of $11,000. To adjust the plan within the budget, we can consider the following changes:\n- Opt for more economical flights or consider alternative transportation methods if available.\n- Choose less expensive accommodations that still meet the requirement for entire rooms and allow parties.\n- Select more budget-friendly restaurants while ensuring they can accommodate a group of 4.\n\nPlease note that the provided travel plan is a draft and adjustments will be necessary to meet the budget constraints.", "gpt-4-1106-preview_direct_sole-planning_parsed_results": [{"day": 1, "current_city": "from Seattle to Dallas", "transportation": "Flight Number: F3669219, from Seattle to Dallas, Departure Time: 07:42, Arrival Time: 13:36", "breakfast": "-", "attraction": "-", "lunch": "-", "dinner": "Coconuts Fish Cafe, Dallas", "accommodation": "Spacious, bright room, prime Williamsburg location, Dallas"}, {"day": 2, "current_city": "Dallas", "transportation": "-", "breakfast": "Cafe Gatherings, Dallas", "attraction": "The Dallas World Aquarium, Dallas;The Sixth Floor Museum at Dealey Plaza, Dallas;", "lunch": "1918 Bistro & Grill, Dallas", "dinner": "Yanki Sizzlers, Dallas", "accommodation": "Spacious, bright room, prime Williamsburg location, Dallas"}, {"day": 3, "current_city": "from Dallas to Houston", "transportation": "Flight Number: F3667553, from Dallas to Houston, Departure Time: 07:06, Arrival Time: 08:21", "breakfast": "-", "attraction": "Space Center Houston, Houston", "lunch": "Jalapenos, Houston", "dinner": "Super Bakery, Houston", "accommodation": "Sunny and Airy near Manhattan, Houston"}, {"day": 4, "current_city": "Houston", "transportation": "-", "breakfast": "Earthen Spices, Houston", "attraction": "Houston Museum of Natural Science, Houston;Houston Zoo, Houston;", "lunch": "The BrewMaster - The Mix Fine Dine, Houston", "dinner": "Pebble Street, Houston", "accommodation": "Sunny and Airy near Manhattan, Houston"}, {"day": 5, "current_city": "from Houston to San Antonio", "transportation": "Flight Number: F3877522, from Houston to San Antonio, Departure Time: 16:34, Arrival Time: 17:21", "breakfast": "-", "attraction": "San Antonio River Walk, San Antonio", "lunch": "Cafe Le Rue @ The Landings, San Antonio", "dinner": "Martin's BBQ, San Antonio", "accommodation": "Spacious, bright room, prime Williamsburg location, San Antonio"}, {"day": 6, "current_city": "San Antonio", "transportation": "-", "breakfast": "Big Jack's, San Antonio", "attraction": "SeaWorld San Antonio, San Antonio;San Antonio Museum of Art, San Antonio;", "lunch": "Barbeque Nation, San Antonio", "dinner": "Cream Stone, San Antonio", "accommodation": "Spacious, bright room, prime Williamsburg location, San Antonio"}, {"day": 7, "current_city": "from San Antonio to Seattle", "transportation": "Flight Number: F3744881, from San Antonio to Seattle, Departure Time: 18:35, Arrival Time: 20:58", "breakfast": "-", "attraction": "-", "lunch": "-", "dinner": "-", "accommodation": "-"}]}]