[{"gpt-4-1106-preview_direct_sole-planning_results": "Travel Plan:\nDays: 1,\nCurrent City: from Punta Gorda to Marquette (Wisconsin),\nTransportation: Taxi, from Punta Gorda to Marquette, duration: 19 hours 48 mins, distance: 2,198 km, cost: 2198\nBreakfast: -,\nAttraction: -,\nLunch: -,\nDinner: The Chop House, Marquette (Wisconsin), cost: 81, cuisines: \u201cDesserts, Tea, Pizza, Mexican, Bakery, Indian\u201d\nAccommodation: Charming Cobble Hill Brownstone Apartment, Marquette (Wisconsin), cost: 220, room type: Entire home/apt, house rules: No pets, minimum nights: 2, maximum occupancy: 3\n\nNumber of people = 1\nTotal cost = 2198 + 81 + 220 = 2499\nAccommodation minimum nights:  1/2\n\nDays: 2,\nCurrent City: Marquette (Wisconsin),\nTransportation: -,\nBreakfast: Ifthar, Marquette (Wisconsin), cost: 67, cuisines: \u201cBakery, American, Cafe, Desserts\u201d\nAttraction: Presque Isle Park, Marquette (Wisconsin); Marquette Harbor Lighthouse, Marquette (Wisconsin),\nLunch: Taste of Balingup, Marquette (Wisconsin), cost: 35, cuisines: \u201cBBQ, Desserts\u201d\nDinner: Dovetail, Marquette (Wisconsin), cost: 95, cuisines: \u201cFast Food, Indian, BBQ, Italian\u201d\nAccommodation: Charming Cobble Hill Brownstone Apartment, Marquette (Wisconsin), cost: 220, room type: Entire home/apt, house rules: No pets, minimum nights: 2, maximum occupancy: 3\n\nNumber of people = 1\nTotal cost = 67 + 35 + 95 + 220 = 417\nAccommodation minimum nights:  2/2 (Done!)\n\nDays: 3,\nCurrent City: from Marquette (Wisconsin) to Madison (Wisconsin),\nTransportation: Taxi, from Marquette to Madison, duration: 1 hour 17 mins, distance: 126 km, cost: 126\nBreakfast: -,\nAttraction: Madison Children's Museum, Madison (Wisconsin); Chazen Museum of Art, Madison (Wisconsin),\nLunch: Unique Food Hut, Madison (Wisconsin), cost: 38, cuisines: \u201cDesserts, Italian, BBQ, Fast Food, Seafood\u201d\nDinner: Barbeque Nation, Madison (Wisconsin), cost: 38, cuisines: \u201cTea, Pizza, French, Bakery, Cafe\u201d\nAccommodation: Oversized bedroom with living space, Madison (Wisconsin), cost: 908, room type: Private room, house rules: No visitors, minimum nights: 20, maximum occupancy: 1\n\nNumber of people = 1\nTotal cost = 126 + 38 + 38 + 908 = 1110\nAccommodation minimum nights:  1/20\n\nDays: 4,\nCurrent City: Madison (Wisconsin),\nTransportation: -,\nBreakfast: Chini Bowl, Madison (Wisconsin), cost: 26, cuisines: \u201cCafe, Seafood\u201d\nAttraction: Olbrich Botanical Gardens, Madison (Wisconsin); Wisconsin Veterans Museum, Madison (Wisconsin),\nLunch: The Kathis, Madison (Wisconsin), cost: 67, cuisines: \u201cBBQ, Pizza, Desserts, Fast Food\u201d\nDinner: Food Cafe, Madison (Wisconsin), cost: 85, cuisines: \u201cTea, Pizza, Fast Food, American, Seafood\u201d\nAccommodation: Oversized bedroom with living space, Madison (Wisconsin), cost: 908, room type: Private room, house rules: No visitors, minimum nights: 20, maximum occupancy: 1\n\nNumber of people = 1\nTotal cost = 26 + 67 + 85 + 908 = 1086\nAccommodation minimum nights:  2/20\n\nDays: 5,\nCurrent City: from Madison (Wisconsin) to Devils Lake (Wisconsin),\nTransportation: Taxi, from Madison to Devils Lake, duration: 56 mins, distance: 70.7 km, cost: 70\nBreakfast: -,\nAttraction: Lake Region Heritage Center, Devils Lake (Wisconsin); Roosevelt Park, Devils Lake (Wisconsin),\nLunch: AB's Absolute Barbecues, Devils Lake (Wisconsin), cost: 80, cuisines: \u201cCafe, Mexican, Seafood\u201d\nDinner: Din Tai Fung, Devils Lake (Wisconsin), cost: 100, cuisines: \u201cDesserts, Pizza, Bakery, Fast Food, Indian\u201d\nAccommodation: Charming Cobble Hill Brownstone Apartment, Devils Lake (Wisconsin), cost: 220, room type: Entire home/apt, house rules: No pets, minimum nights: 2, maximum occupancy: 3\n\nNumber of people = 1\nTotal cost = 70 + 80 + 100 + 220 = 470\nAccommodation minimum nights:  1/2\n\nDays: 6,\nCurrent City: Devils Lake (Wisconsin),\nTransportation: -,\nBreakfast: Boise Fry Company, Devils Lake (Wisconsin), cost: 99, cuisines: \u201cDesserts, Mexican, Bakery, Fast Food, Cafe\u201d\nAttraction: Devils Lake State Parks, Devils Lake (Wisconsin); Roundhouse Park, Devils Lake (Wisconsin),\nLunch: Dakshin Bistro, Devils Lake (Wisconsin), cost: 42, cuisines: \u201cTea, BBQ, Indian, Desserts\u201d\nDinner: Zaffran - The Claremont, Devils Lake (Wisconsin), cost: 100, cuisines: \u201cCafe, Mexican, BBQ, Pizza\u201d\nAccommodation: Charming Cobble Hill Brownstone Apartment, Devils Lake (Wisconsin), cost: 220, room type: Entire home/apt, house rules: No pets, minimum nights: 2, maximum occupancy: 3\n\nNumber of people = 1\nTotal cost = 99 + 42 + 100 + 220 = 461\nAccommodation minimum nights:  2/2 (Done!)\n\nDays: 7,\nCurrent City: from Devils Lake (Wisconsin) to Punta Gorda,\nTransportation: Taxi, from Devils Lake to Punta Gorda, duration: 21 hours 4 mins, distance: 2,346 km, cost: 2346\nBreakfast: -,\nAttraction: -,\nLunch: -,\nDinner: -,\nAccommodation: -\n\nNumber of people = 1\nTotal cost = 2346\n\nTotal cost across all days = 2499 + 417 + 1110 + 1086 + 470 + 461 + 2346 = 8389\n\nUnfortunately, the total cost of $8,389 exceeds the specified budget of $5,700. Adjustments to the travel plan, such as changing the mode of transportation or selecting different accommodations, would be necessary to stay within budget.", "gpt-4-1106-preview_direct_sole-planning_parsed_results": [{"day": 1, "current_city": "from Punta Gorda to Marquette (Wisconsin)", "transportation": "Taxi, from Punta Gorda to Marquette, duration: 19 hours 48 mins, distance: 2,198 km", "breakfast": "-", "attraction": "-", "lunch": "-", "dinner": "The Chop House, Marquette (Wisconsin)", "accommodation": "Charming Cobble Hill Brownstone Apartment, Marquette (Wisconsin)"}, {"day": 2, "current_city": "Marquette (Wisconsin)", "transportation": "-", "breakfast": "Ifthar, Marquette (Wisconsin)", "attraction": "Presque Isle Park, Marquette (Wisconsin);Marquette Harbor Lighthouse, Marquette (Wisconsin);", "lunch": "Taste of Balingup, Marquette (Wisconsin)", "dinner": "Dovetail, Marquette (Wisconsin)", "accommodation": "Charming Cobble Hill Brownstone Apartment, Marquette (Wisconsin)"}, {"day": 3, "current_city": "from Marquette (Wisconsin) to Madison (Wisconsin)", "transportation": "Taxi, from Marquette to Madison, duration: 1 hour 17 mins, distance: 126 km", "breakfast": "-", "attraction": "Madison Children's Museum, Madison (Wisconsin);Chazen Museum of Art, Madison (Wisconsin);", "lunch": "Unique Food Hut, Madison (Wisconsin)", "dinner": "Barbeque Nation, Madison (Wisconsin)", "accommodation": "Oversized bedroom with living space, Madison (Wisconsin)"}, {"day": 4, "current_city": "Madison (Wisconsin)", "transportation": "-", "breakfast": "Chini Bowl, Madison (Wisconsin)", "attraction": "Olbrich Botanical Gardens, Madison (Wisconsin);Wisconsin Veterans Museum, Madison (Wisconsin);", "lunch": "The Kathis, Madison (Wisconsin)", "dinner": "Food Cafe, Madison (Wisconsin)", "accommodation": "Oversized bedroom with living space, Madison (Wisconsin)"}, {"day": 5, "current_city": "from Madison (Wisconsin) to Devils Lake (Wisconsin)", "transportation": "Taxi, from Madison to Devils Lake, duration: 56 mins, distance: 70.7 km", "breakfast": "-", "attraction": "Lake Region Heritage Center, Devils Lake (Wisconsin);Roosevelt Park, Devils Lake (Wisconsin);", "lunch": "AB's Absolute Barbecues, Devils Lake (Wisconsin)", "dinner": "Din Tai Fung, Devils Lake (Wisconsin)", "accommodation": "Charming Cobble Hill Brownstone Apartment, Devils Lake (Wisconsin)"}, {"day": 6, "current_city": "Devils Lake (Wisconsin)", "transportation": "-", "breakfast": "Boise Fry Company, Devils Lake (Wisconsin)", "attraction": "Devils Lake State Parks, Devils Lake (Wisconsin);Roundhouse Park, Devils Lake (Wisconsin);", "lunch": "Dakshin Bistro, Devils Lake (Wisconsin)", "dinner": "Zaffran - The Claremont, Devils Lake (Wisconsin)", "accommodation": "Charming Cobble Hill Brownstone Apartment, Devils Lake (Wisconsin)"}, {"day": 7, "current_city": "from Devils Lake (Wisconsin) to Punta Gorda", "transportation": "Taxi, from Devils Lake to Punta Gorda, duration: 21 hours 4 mins, distance: 2,346 km", "breakfast": "-", "attraction": "-", "lunch": "-", "dinner": "-", "accommodation": "-"}]}]