[{"gpt-4-1106-preview_direct_sole-planning_results": "Travel Plan:\nDays: 1,\nCurrent City: from St. Petersburg to Rockford,\nTransportation: Flight Number: F3573659, from St. Petersburg to Rockford, Departure Time: 15:40, Arrival Time: 17:04, cost: 474\nBreakfast: -,\nAttraction: -,\nLunch: -,\nDinner: Coco Bambu, Rockford, cost: 72, cuisines: \u201cTea, French, Bakery, BBQ, Cafe\u201d\nAccommodation: Private Room in a two bedroom apt., Rockford, cost: 210, maximum occupancy: 2, house rules: No visitors & No smoking, minimum nights: 1\n\nNumber of people = 1\nTotal cost = 474 + 72 + 210 = 756\nAccommodation minimum nights:  1/1\n\nDays: 2,\nCurrent City: Rockford,\nTransportation: -,\nBreakfast: Dunkin' Donuts, Rockford, cost: 24, cuisines: \u201cCafe, Bakery, BBQ, Seafood\u201d\nAttraction: Anderson Japanese Gardens, Rockford; Burpee Museum of Natural History, Rockford,\nLunch: Flying Mango, Rockford, cost: 20, cuisines: \u201cAmerican, BBQ, Seafood\u201d\nDinner: Aroma Rest O Bar, Rockford, cost: 58, cuisines: \u201cBakery, Fast Food, Chinese, American, Seafood\u201d\nAccommodation: Private Room in a two bedroom apt., Rockford, cost: 210, maximum occupancy: 2, house rules: No visitors & No smoking, minimum nights: 1\n\nNumber of people = 1\nTotal cost = 24 + 20 + 58 + 210 = 312\nAccommodation minimum nights:  2/1\n\nDays: 3,\nCurrent City: from Rockford to St. Petersburg,\nTransportation: Flight Number: F3573120, from Rockford to St. Petersburg, Departure Time: 19:00, Arrival Time: 22:43, cost: 346\nBreakfast: -,\nAttraction: -,\nLunch: -,\nDinner: -,\nAccommodation: -\n\nNumber of people = 1\nTotal cost = 346\n\nTotal cost across all days = 756 + 312 + 346 = 1,414\n\nCuisines: The prompt does not specify any cuisine preferences, so all cuisine constraints are satisfied.\nHouse rules: All accommodations chosen adhere to the house rules specified in the query.\n\n***** Travel Plan Ends *****", "gpt-4-1106-preview_direct_sole-planning_parsed_results": [{"day": 1, "current_city": "from St. Petersburg to Rockford", "transportation": "Flight Number: F3573659, from St. Petersburg to Rockford, Departure Time: 15:40, Arrival Time: 17:04", "breakfast": "-", "attraction": "-", "lunch": "-", "dinner": "Coco Bambu, Rockford", "accommodation": "Private Room in a two bedroom apt., Rockford"}, {"day": 2, "current_city": "Rockford", "transportation": "-", "breakfast": "Dunkin' Donuts, Rockford", "attraction": "Anderson Japanese Gardens, Rockford;Burpee Museum of Natural History, Rockford;", "lunch": "Flying Mango, Rockford", "dinner": "Aroma Rest O Bar, Rockford", "accommodation": "Private Room in a two bedroom apt., Rockford"}, {"day": 3, "current_city": "from Rockford to St. Petersburg", "transportation": "Flight Number: F3573120, from Rockford to St. Petersburg, Departure Time: 19:00, Arrival Time: 22:43", "breakfast": "-", "attraction": "-", "lunch": "-", "dinner": "-", "accommodation": "-"}]}]