[{"gpt-4-1106-preview_direct_sole-planning_results": "Travel Plan:\n\nDays: 1,\nCurrent City: from St. Louis to San Diego (California),\nTransportation: Flight Number: F4025732, from St. Louis to San Diego (California), Departure Time: 16:42, Arrival Time: 18:31, cost: $430\nBreakfast: -,\nAttraction: -,\nLunch: -,\nDinner: Burgrill, San Diego (California), cost: $54, cuisines: \u201cDesserts, Tea, Pizza, Fast Food, Chinese\u201d\nAccommodation: Spacious Room in Large 2 Bedroom Prewar Apartment, San Diego (California), cost: $585, maximum occupancy: 2, house rules: No parties & No visitors, minimum nights: 1\n\nNumber of people = 2\nTotal cost = ($430 + $54) * 2 + $585 = $1,553\nAccommodation minimum nights: 1/1\n\nDays: 2,\nCurrent City: San Diego (California),\nTransportation: -,\nBreakfast: Burger King, San Diego (California), cost: $20, cuisines: \u201cPizza, Italian, French, Fast Food, Seafood\u201d\nAttraction: La Jolla Shores Park, San Diego (California); Cabrillo National Monument, San Diego (California),\nLunch: Gopala, San Diego (California), cost: $98, cuisines: \u201cPizza, Mexican, BBQ, American, Seafood\u201d\nDinner: Bikaner Sweets, San Diego (California), cost: $37, cuisines: \u201cBakery, Pizza, Indian, Fast Food\u201d\nAccommodation: Spacious Room in Large 2 Bedroom Prewar Apartment, San Diego (California), cost: $585, maximum occupancy: 2, house rules: No parties & No visitors, minimum nights: 1\n\nNumber of people = 2\nTotal cost = ($20 + $98 + $37) * 2 + $585 = $895\nAccommodation minimum nights: 2/1\n\nDays: 3,\nCurrent City: from San Diego (California) to San Francisco (California),\nTransportation: Flight Number: F3746772, from San Diego (California) to San Francisco (California), Departure Time: 08:09, Arrival Time: 09:43, cost: $112\nBreakfast: -,\nAttraction: Golden Gate Bridge, San Francisco (California); Golden Gate Park, San Francisco (California),\nLunch: Bonne Bouche, San Francisco (California), cost: $21, cuisines: \u201cTea, Chinese, American, Cafe\u201d\nDinner: Kream's, San Francisco (California), cost: $67, cuisines: \u201cTea, Pizza, BBQ, Chinese, Seafood\u201d\nAccommodation: Great 1 Bedroom on Upper East, San Francisco (California), cost: $484, maximum occupancy: 2, house rules: No parties, minimum nights: 2\n\nNumber of people = 2\nTotal cost = ($112 + $21 + $67) * 2 + $484 = $884\nAccommodation minimum nights: 1/2\n\nDays: 4,\nCurrent City: San Francisco (California),\nTransportation: -,\nBreakfast: Coffee & Chai Co., San Francisco (California), cost: $10, cuisines: \u201cTea, Mexican, BBQ, Cafe, Seafood\u201d\nAttraction: California Academy of Sciences, San Francisco (California); San Francisco Museum of Modern Art, San Francisco (California),\nLunch: Sudarshan, San Francisco (California), cost: $53, cuisines: \u201cFast Food, Bakery, Mediterranean, Italian\u201d\nDinner: Green Chick Chop, San Francisco (California), cost: $39, cuisines: \u201cTea, Pizza, Italian, BBQ, Mediterranean, Seafood\u201d\nAccommodation: Great 1 Bedroom on Upper East, San Francisco (California), cost: $484, maximum occupancy: 2, house rules: No parties, minimum nights: 2\n\nNumber of people = 2\nTotal cost = ($10 + $53 + $39) * 2 + $484 = $688\nAccommodation minimum nights: 2/2\n\nDays: 5,\nCurrent City: from San Francisco (California) to Long Beach (California),\nTransportation: Taxi, from San Francisco (California) to Long Beach (California), duration: 6 hours 12 mins, distance: 651 km, cost: $651\nBreakfast: Gupta\u2019s Rasoi, San Francisco (California), cost: $13, cuisines: \u201cCafe, Bakery, BBQ, Mediterranean\u201d\nAttraction: The Queen Mary, Long Beach (California),\nLunch: -,\nDinner: Tsing Tsao South, Long Beach (California), cost: $56, cuisines: \u201cTea, Cafe, BBQ\u201d\nAccommodation: Cozy Two Bedrooms Home Away From Home Getaway., Long Beach (California), cost: $914, maximum occupancy: 3, house rules: No pets & No children under 10, minimum nights: 2\n\nNumber of people = 2\nTotal cost = $651 + ($13 + $56) * 2 + $914 = $1,704\nAccommodation minimum nights: 1/2\n\nDays: 6,\nCurrent City: Long Beach (California),\nTransportation: -,\nBreakfast: Winifreds, Long Beach (California), cost: $23, cuisines: \u201cBakery, BBQ, Fast Food\u201d\nAttraction: Aquarium of the Pacific, Long Beach (California); Rainbow Lagoon Park, Long Beach (California),\nLunch: ChandChini, Long Beach (California), cost: $19, cuisines: \u201cCafe, Pizza, Desserts, Seafood\u201d\nDinner: Giuseppe\u2019s Pizza & Italian Specialities, Long Beach (California), cost: $72, cuisines: \u201cBakery, Fast Food, Cafe, Indian, Mediterranean, Seafood\u201d\nAccommodation: Cozy Two Bedrooms Home Away From Home Getaway., Long Beach (California), cost: $914, maximum occupancy: 3, house rules: No pets & No children under 10, minimum nights: 2\n\nNumber of people = 2\nTotal cost = ($23 + $19 + $72) * 2 + $914 = $1,142\nAccommodation minimum nights: 2/2\n\nDays: 7,\nCurrent City: from Long Beach (California) to St. Louis,\nTransportation: Flight Number: F3986547, from Long Beach (California) to St. Louis, Departure Time: 07:04, Arrival Time: 12:37, cost: $370\nBreakfast: -,\nAttraction: -,\nLunch: -,\nDinner: -,\nAccommodation: -\n\nNumber of people = 2\nTotal cost = $370 * 2 = $740\n\nTotal cost across all days = $1,553 + $895 + $884 + $688 + $1,704 + $1,142 + $740 = $7,606\nCuisines: The prompt specifies American and Chinese, and both of these cuisines have been represented in the restaurants chosen.", "gpt-4-1106-preview_direct_sole-planning_parsed_results": [{"day": 1, "current_city": "from St. Louis to San Diego (California)", "transportation": "Flight Number: F4025732, from St. Louis to San Diego (California), Departure Time: 16:42, Arrival Time: 18:31", "breakfast": "-", "attraction": "-", "lunch": "-", "dinner": "Burgrill, San Diego (California)", "accommodation": "Spacious Room in Large 2 Bedroom Prewar Apartment, San Diego (California)"}, {"day": 2, "current_city": "San Diego (California)", "transportation": "-", "breakfast": "Burger King, San Diego (California)", "attraction": "La Jolla Shores Park, San Diego (California);Cabrillo National Monument, San Diego (California);", "lunch": "Gopala, San Diego (California)", "dinner": "Bikaner Sweets, San Diego (California)", "accommodation": "Spacious Room in Large 2 Bedroom Prewar Apartment, San Diego (California)"}, {"day": 3, "current_city": "from San Diego (California) to San Francisco (California)", "transportation": "Flight Number: F3746772, from San Diego (California) to San Francisco (California), Departure Time: 08:09, Arrival Time: 09:43", "breakfast": "-", "attraction": "Golden Gate Bridge, San Francisco (California);Golden Gate Park, San Francisco (California);", "lunch": "Bonne Bouche, San Francisco (California)", "dinner": "Kream's, San Francisco (California)", "accommodation": "Great 1 Bedroom on Upper East, San Francisco (California)"}, {"day": 4, "current_city": "San Francisco (California)", "transportation": "-", "breakfast": "Coffee & Chai Co., San Francisco (California)", "attraction": "California Academy of Sciences, San Francisco (California);San Francisco Museum of Modern Art, San Francisco (California);", "lunch": "Sudarshan, San Francisco (California)", "dinner": "Green Chick Chop, San Francisco (California)", "accommodation": "Great 1 Bedroom on Upper East, San Francisco (California)"}, {"day": 5, "current_city": "from San Francisco (California) to Long Beach (California)", "transportation": "Taxi, from San Francisco (California) to Long Beach (California), duration: 6 hours 12 mins, distance: 651 km", "breakfast": "Gupta\u2019s Rasoi, San Francisco (California)", "attraction": "The Queen Mary, Long Beach (California);", "lunch": "-", "dinner": "Tsing Tsao South, Long Beach (California)", "accommodation": "Cozy Two Bedrooms Home Away From Home Getaway., Long Beach (California)"}, {"day": 6, "current_city": "Long Beach (California)", "transportation": "-", "breakfast": "Winifreds, Long Beach (California)", "attraction": "Aquarium of the Pacific, Long Beach (California);Rainbow Lagoon Park, Long Beach (California);", "lunch": "ChandChini, Long Beach (California)", "dinner": "Giuseppe\u2019s Pizza & Italian Specialities, Long Beach (California)", "accommodation": "Cozy Two Bedrooms Home Away From Home Getaway., Long Beach (California)"}, {"day": 7, "current_city": "from Long Beach (California) to St. Louis", "transportation": "Flight Number: F3986547, from Long Beach (California) to St. Louis, Departure Time: 07:04, Arrival Time: 12:37", "breakfast": "-", "attraction": "-", "lunch": "-", "dinner": "-", "accommodation": "-"}]}]