[{"gpt-4-1106-preview_direct_sole-planning_results": "Travel Plan:\n\nDay 1: March 20, 2022\nCurrent City: from Greensboro to Buffalo\nTransportation: Self-driving, duration: 9 hours 40 mins, distance: 1,023 km, cost: $51\nBreakfast: -\nLunch: -\nDinner: Shokitini, Buffalo, Cost: $41, Cuisines: \"Tea, Cafe, Pizza, Mexican, Chinese, Seafood\"\nAccommodation: Cozy Studio in Heart of Ft Greene, Buffalo, Cost: $200, Entire home/apt, House Rules: No pets & No children under 10, Minimum Nights: 4\n\nDay 2: March 21, 2022\nCurrent City: Buffalo\nTransportation: -\nBreakfast: Punjab Grill, Buffalo, Cost: $25, Cuisines: \"Bakery, BBQ, Desserts, Seafood\"\nLunch: Tibby's New Orleans Kitchen, Buffalo, Cost: $48, Cuisines: \"Seafood, Indian, BBQ, Italian\"\nDinner: Ammu's South Indian Restaurant, Buffalo, Cost: $80, Cuisines: \"Desserts, Pizza, French, BBQ, Chinese\"\nAccommodation: Cozy Studio in Heart of Ft Greene, Buffalo, Cost: $200, Entire home/apt, House Rules: No pets & No children under 10, Minimum Nights: 4\n\nDay 3: March 22, 2022\nCurrent City: from Buffalo to Niagara Falls\nTransportation: Self-driving, duration: 26 mins, distance: 31.9 km, cost: $1\nBreakfast: Red Mango, Buffalo, Cost: $18, Cuisines: \"Mexican, Bakery, BBQ, Fast Food, Cafe, American\"\nAttraction: The Buffalo Zoo, Buffalo\nLunch: Shama Chicken Corner, Buffalo, Cost: $25, Cuisines: \"Tea, Chinese, Desserts\"\nDinner: Izakaya Kikufuji, Niagara Falls, Cost: $66, Cuisines: \"Desserts, Pizza, French, Fast Food, Mediterranean, Seafood\"\nAccommodation: Sunny Bedroom In The Heart of Bushwick, Niagara Falls, Cost: $893, Private room, House Rules: No pets & No parties, Minimum Nights: 3\n\nDay 4: March 23, 2022\nCurrent City: Niagara Falls\nTransportation: -\nBreakfast: Tony Roma's, Niagara Falls, Cost: $47, Cuisines: \"Desserts, Tea, French, Fast Food, Cafe, Mediterranean\"\nAttraction: Journey Behind the Falls, Niagara Falls\nLunch: Pier 70, Niagara Falls, Cost: $60, Cuisines: \"Tea, Bakery, Mediterranean, Seafood\"\nDinner: Raju Dhaba, Niagara Falls, Cost: $67, Cuisines: \"American, Desserts, Seafood\"\nAccommodation: Sunny Bedroom In The Heart of Bushwick, Niagara Falls, Cost: $893, Private room, House Rules: No pets & No parties, Minimum Nights: 3\n\nDay 5: March 24, 2022\nCurrent City: from Niagara Falls to New York\nTransportation: Self-driving, duration: 6 hours 29 mins, distance: 657 km, cost: $32\nBreakfast: -\nLunch: -\nDinner: Seasons 52 Fresh Grill, New York, Cost: $30, Cuisines: \"Seafood, Indian, Desserts, Italian\"\nAccommodation: A Contemporary Homelike Stay in the Best of BK, New York, Cost: $228, Entire home/apt, House Rules: No pets & No visitors & No children under 10, Minimum Nights: 2\n\nDay 6: March 25, 2022\nCurrent City: New York\nTransportation: -\nBreakfast: Gurgaon Hights, New York, Cost: $46, Cuisines: \"Cafe, American, Indian, Fast Food\"\nAttraction: Top of The Rock, New York\nLunch: Lord of the Drinks Forum, New York, Cost: $71, Cuisines: \"Cafe, Bakery, BBQ, Chinese, Indian\"\nDinner: QD's Restaurant, New York, Cost: $93, Cuisines: \"Tea, Desserts, Indian, BBQ\"\nAccommodation: A Contemporary Homelike Stay in the Best of BK, New York, Cost: $228, Entire home/apt, House Rules: No pets & No visitors & No children under 10, Minimum Nights: 2\n\nDay 7: March 26, 2022\nCurrent City: from New York to Greensboro\nTransportation: Self-driving, duration: 8 hours 19 mins, distance: 870 km, cost: $43\nBreakfast: Sir John Bakery Cafe, New York, Cost: $78, Cuisines: \"Pizza, Bakery, Desserts\"\nLunch: -\nDinner: -\nAccommodation: -\n\nTotal cost for transportation: $51 (Day 1) + $1 (Day 3) + $32 (Day 5) + $43 (Day 7) = $127\nTotal cost for accommodations: $200 (Day 1) + $200 (Day 2) + $893 (Day 3) + $893 (Day 4) + $228 (Day 5) + $228 (Day 6) = $2642\nTotal cost for meals and attractions: $41 (Dinner Day 1) + $25 (Breakfast Day 2) + $48 (Lunch Day 2) + $80 (Dinner Day 2) + $18 (Breakfast Day 3) + $25 (Lunch Day 3) + $66 (Dinner Day 3) + $47 (Breakfast Day 4) + $60 (Lunch Day 4) + $67 (Dinner Day 4) + $30 (Dinner Day 5) + $46 (Breakfast Day 6) + $71 (Lunch Day 6) + $93 (Dinner Day 6) + $78 (Breakfast Day 7) = $795\nTotal cost for two people: ($127 + $2642 + $795) * 2 = $7128\n\nUnfortunately, the total cost of $7128 exceeds the budget of $3800. To stay within budget, we would need to adjust the accommodations, meal choices, or the number of attractions visited. Please let me know how you would like to proceed or if there are any specific areas you would like to adjust.", "gpt-4-1106-preview_direct_sole-planning_parsed_results": [{"day": 1, "current_city": "from Greensboro to Buffalo", "transportation": "Self-driving, duration: 9 hours 40 mins, distance: 1,023 km", "breakfast": "-", "attraction": "-", "lunch": "-", "dinner": "Shokitini, Buffalo", "accommodation": "Cozy Studio in Heart of Ft Greene, Buffalo"}, {"day": 2, "current_city": "Buffalo", "transportation": "-", "breakfast": "Punjab Grill, Buffalo", "attraction": "-", "lunch": "Tibby's New Orleans Kitchen, Buffalo", "dinner": "Ammu's South Indian Restaurant, Buffalo", "accommodation": "Cozy Studio in Heart of Ft Greene, Buffalo"}, {"day": 3, "current_city": "from Buffalo to Niagara Falls", "transportation": "Self-driving, duration: 26 mins, distance: 31.9 km", "breakfast": "Red Mango, Buffalo", "attraction": "The Buffalo Zoo, Buffalo", "lunch": "Shama Chicken Corner, Buffalo", "dinner": "Izakaya Kikufuji, Niagara Falls", "accommodation": "Sunny Bedroom In The Heart of Bushwick, Niagara Falls"}, {"day": 4, "current_city": "Niagara Falls", "transportation": "-", "breakfast": "Tony Roma's, Niagara Falls", "attraction": "Journey Behind the Falls, Niagara Falls", "lunch": "Pier 70, Niagara Falls", "dinner": "Raju Dhaba, Niagara Falls", "accommodation": "Sunny Bedroom In The Heart of Bushwick, Niagara Falls"}, {"day": 5, "current_city": "from Niagara Falls to New York", "transportation": "Self-driving, duration: 6 hours 29 mins, distance: 657 km", "breakfast": "-", "attraction": "-", "lunch": "-", "dinner": "Seasons 52 Fresh Grill, New York", "accommodation": "A Contemporary Homelike Stay in the Best of BK, New York"}, {"day": 6, "current_city": "New York", "transportation": "-", "breakfast": "Gurgaon Hights, New York", "attraction": "Top of The Rock, New York", "lunch": "Lord of the Drinks Forum, New York", "dinner": "QD's Restaurant, New York", "accommodation": "A Contemporary Homelike Stay in the Best of BK, New York"}, {"day": 7, "current_city": "from New York to Greensboro", "transportation": "Self-driving, duration: 8 hours 19 mins, distance: 870 km", "breakfast": "Sir John Bakery Cafe, New York", "attraction": "-", "lunch": "-", "dinner": "-", "accommodation": "-"}]}]