[{"gpt-4-1106-preview_direct_sole-planning_results": "Travel Plan:\n\nDay 1: March 14th, 2022\nCurrent City: from Sacramento to Atlanta\nTransportation: Flight Number: F3510904, from Sacramento to Atlanta, Departure Time: 06:55, Arrival Time: 14:09, Cost: $520\nBreakfast: Not applicable (Assuming breakfast before flight or on-board)\nAttraction: Georgia Aquarium, Atlanta, Cost: $40 per person\nLunch: Adda, Atlanta, Cost: $22, Cuisines: \"Tea, Mexican, Bakery\"\nDinner: Chef Style, Atlanta, Cost: $59, Cuisines: \"Pizza, American, Desserts, Seafood\"\nAccommodation: Charming Carroll Gardens 2 BR, Atlanta, Cost: $576, Maximum Occupancy: 4, House Rules: No parties\n\nNumber of People = 2\nTotal Cost = 2 * $520 (flight) + 2 * $40 (attraction) + 2 * $22 (lunch) + 2 * $59 (dinner) + $576 (accommodation) = $1804\n\nDay 2: March 15th, 2022\nCurrent City: Atlanta\nTransportation: -\nBreakfast: Saffron, Atlanta, Cost: $39, Cuisines: \"Tea, Cafe, Fast Food, Seafood\"\nAttraction: World of Coca-Cola, Atlanta, Cost: $20 per person\nLunch: Pizza Central, Atlanta, Cost: $75, Cuisines: \"Cafe, Bakery, BBQ, Fast Food, Chinese, Indian\"\nDinner: Sizzler's Ranch, Atlanta, Cost: $36, Cuisines: \"Tea, Cafe, Indian, Italian\"\nAccommodation: Charming Carroll Gardens 2 BR, Atlanta, Cost: $576, Maximum Occupancy: 4, House Rules: No parties\n\nNumber of People = 2\nTotal Cost = 2 * $39 (breakfast) + 2 * $20 (attraction) + 2 * $75 (lunch) + 2 * $36 (dinner) + $576 (accommodation) = $926\n\nDay 3: March 16th, 2022\nCurrent City: from Atlanta to Sacramento\nTransportation: Flight Number: F3542376, from Atlanta to Sacramento, Departure Time: 17:53, Arrival Time: 20:36, Cost: $828\nBreakfast: Asian Bistro, Atlanta, Cost: $27, Cuisines: \"Tea, Bakery, Seafood\"\nAttraction: Piedmont Park, Atlanta, Cost: Free\nLunch: Daawat-e-Kashmir, Atlanta, Cost: $19, Cuisines: \"Cafe, Pizza, American, Seafood\"\nDinner: Not applicable (Assuming dinner upon arrival in Sacramento or on-board)\nAccommodation: Not applicable (Returning home)\n\nNumber of People = 2\nTotal Cost = 2 * $828 (flight) + 2 * $27 (breakfast) + 2 * $19 (lunch) = $1748\n\nTotal cost across all days = $1804 + $926 + $1748 = $4478\n\nCuisines: The prompt specifies no cuisines, so all cuisines constraints are satisfied.\n\nNote: The accommodation selected does not allow parties, which contradicts the query requirement. However, based on the provided CSV data, there are no accommodations listed that explicitly allow parties. Therefore, the closest match that meets the budget and other constraints was chosen. If accommodations that allow parties are a strict requirement, further information or options would be needed to fulfill this request.", "gpt-4-1106-preview_direct_sole-planning_parsed_results": [{"day": 1, "current_city": "from Sacramento to Atlanta", "transportation": "Flight Number: F3510904, from Sacramento to Atlanta, Departure Time: 06:55, Arrival Time: 14:09", "breakfast": "-", "attraction": "Georgia Aquarium, Atlanta;", "lunch": "Adda, Atlanta", "dinner": "Chef Style, Atlanta", "accommodation": "Charming Carroll Gardens 2 BR, Atlanta"}, {"day": 2, "current_city": "Atlanta", "transportation": "-", "breakfast": "Saffron, Atlanta", "attraction": "World of Coca-Cola, Atlanta;", "lunch": "Pizza Central, Atlanta", "dinner": "Sizzler's Ranch, Atlanta", "accommodation": "Charming Carroll Gardens 2 BR, Atlanta"}, {"day": 3, "current_city": "from Atlanta to Sacramento", "transportation": "Flight Number: F3542376, from Atlanta to Sacramento, Departure Time: 17:53, Arrival Time: 20:36", "breakfast": "Asian Bistro, Atlanta", "attraction": "Piedmont Park, Atlanta;", "lunch": "Daawat-e-Kashmir, Atlanta", "dinner": "-", "accommodation": "-"}]}]