[{"gpt-4-1106-preview_direct_sole-planning_results": "Travel Plan:\n\nDay 1: March 16, 2022\nCurrent City: Punta Gorda to Marquette\nTransportation: Self-driving, Duration: 19 hours 48 mins, Distance: 2,198 km, Cost: $109\nBreakfast: -\nLunch: -\nDinner: The Chop House, Marquette, Cost: $81, Cuisines: \"Desserts, Tea, Pizza, Mexican, Bakery, Indian\"\nAccommodation: Charming Cobble Hill Brownstone Apartment, Marquette, Cost: $220, Room Type: Entire home/apt, House Rules: No pets, Minimum Nights: 2, Maximum Occupancy: 3\n\nNumber of People = 1\nTotal Cost = 109 + 81 + 220 = $410\n\nDay 2: March 17, 2022\nCurrent City: Marquette\nTransportation: -\nBreakfast: Taste of Balingup, Marquette, Cost: $35, Cuisines: \"BBQ, Desserts\"\nAttraction: Presque Isle Park, Marquette\nLunch: Dovetail, Marquette, Cost: $95, Cuisines: \"Fast Food, Indian, BBQ, Italian\"\nDinner: Ifthar, Marquette, Cost: $67, Cuisines: \"Bakery, American, Cafe, Desserts\"\nAccommodation: Charming Cobble Hill Brownstone Apartment, Marquette, Cost: $220, Room Type: Entire home/apt, House Rules: No pets, Minimum Nights: 2, Maximum Occupancy: 3\n\nTotal Cost = 35 + 95 + 67 + 220 = $417\n\nDay 3: March 18, 2022\nCurrent City: Marquette to Madison\nTransportation: Self-driving, Duration: 1 hour 17 mins, Distance: 126 km, Cost: $6\nBreakfast: Papa Mexicano, Marquette, Cost: $17, Cuisines: \"Italian, Bakery, BBQ, Fast Food, Seafood\"\nAttraction: Marquette Regional History Center, Marquette\nLunch: -\nDinner: 99 North Restaurant, Madison, Cost: $62, Cuisines: \"Fast Food, Mexican, Indian, Pizza\"\nAccommodation: Oversized bedroom with living space, Madison, Cost: $908, Room Type: Private room, House Rules: No visitors, Minimum Nights: 20, Maximum Occupancy: 1\n\nTotal Cost = 6 + 17 + 62 + 908 = $993\n\nDay 4: March 19, 2022\nCurrent City: Madison\nTransportation: -\nBreakfast: Unique Food Hut, Madison, Cost: $38, Cuisines: \"Desserts, Italian, BBQ, Fast Food, Seafood\"\nAttraction: Madison Children's Museum, Madison\nLunch: Chini Bowl, Madison, Cost: $26, Cuisines: \"Cafe, Seafood\"\nDinner: Tibb's Frankie, Madison, Cost: $75, Cuisines: \"Fast Food, Cafe, Desserts, Italian\"\nAccommodation: Oversized bedroom with living space, Madison, Cost: $908, Room Type: Private room, House Rules: No visitors, Minimum Nights: 20, Maximum Occupancy: 1\n\nTotal Cost = 38 + 26 + 75 + 908 = $1047\n\nDay 5: March 20, 2022\nCurrent City: Madison to Devils Lake\nTransportation: Self-driving, Duration: 56 mins, Distance: 70.7 km, Cost: $3\nBreakfast: Barbeque Nation, Madison, Cost: $38, Cuisines: \"Tea, Pizza, French, Bakery, Cafe\"\nAttraction: Olbrich Botanical Gardens, Madison\nLunch: -\nDinner: Boise Fry Company, Devils Lake, Cost: $99, Cuisines: \"Desserts, Mexican, Bakery, Fast Food, Cafe\"\nAccommodation: Charming Cobble Hill Brownstone Apartment, Devils Lake, Cost: $220, Room Type: Entire home/apt, House Rules: No pets, Minimum Nights: 2, Maximum Occupancy: 3\n\nTotal Cost = 3 + 38 + 99 + 220 = $360\n\nDay 6: March 21, 2022\nCurrent City: Devils Lake\nTransportation: -\nBreakfast: AB's Absolute Barbecues, Devils Lake, Cost: $80, Cuisines: \"Cafe, Mexican, Seafood\"\nAttraction: Lake Region Heritage Center, Devils Lake\nLunch: Dakshin Bistro, Devils Lake, Cost: $42, Cuisines: \"Tea, BBQ, Indian, Desserts\"\nDinner: Zaffran - The Claremont, Devils Lake, Cost: $100, Cuisines: \"Cafe, Mexican, BBQ, Pizza\"\nAccommodation: Charming Cobble Hill Brownstone Apartment, Devils Lake, Cost: $220, Room Type: Entire home/apt, House Rules: No pets, Minimum Nights: 2, Maximum Occupancy: 3\n\nTotal Cost = 80 + 42 + 100 + 220 = $442\n\nDay 7: March 22, 2022\nCurrent City: Devils Lake to Punta Gorda\nTransportation: Self-driving, Duration: 21 hours 4 mins, Distance: 2,346 km, Cost: $117\nBreakfast: Din Tai Fung, Devils Lake, Cost: $100, Cuisines: \"Desserts, Pizza, Bakery, Fast Food, Indian\"\nLunch: -\nDinner: -\nAccommodation: -\n\nTotal Cost = 117 + 100 = $217\n\nTotal cost across all days = 410 + 417 + 993 + 1047 + 360 + 442 + 217 = $3886\n\nRemaining Budget = $5700 - $3886 = $1814\n\nCuisines: The prompt specifies no cuisines, so all cuisines constraints are satisfied.\n\nNote: The accommodation in Madison has a minimum of 20 nights, which exceeds the travel plan duration. However, due to the lack of other options provided in the reference information, it has been included to ensure a place to stay. Adjustments to the accommodation choice may be necessary based on actual availability and minimum stay requirements.", "gpt-4-1106-preview_direct_sole-planning_parsed_results": [{"day": 1, "current_city": "from Punta Gorda to Marquette", "transportation": "Self-driving, Duration: 19 hours 48 mins, Distance: 2,198 km", "breakfast": "-", "attraction": "-", "lunch": "-", "dinner": "The Chop House, Marquette", "accommodation": "Charming Cobble Hill Brownstone Apartment, Marquette"}, {"day": 2, "current_city": "Marquette", "transportation": "-", "breakfast": "Taste of Balingup, Marquette", "attraction": "Presque Isle Park, Marquette", "lunch": "Dovetail, Marquette", "dinner": "Ifthar, Marquette", "accommodation": "Charming Cobble Hill Brownstone Apartment, Marquette"}, {"day": 3, "current_city": "from Marquette to Madison", "transportation": "Self-driving, Duration: 1 hour 17 mins, Distance: 126 km", "breakfast": "Papa Mexicano, Marquette", "attraction": "Marquette Regional History Center, Marquette", "lunch": "-", "dinner": "99 North Restaurant, Madison", "accommodation": "Oversized bedroom with living space, Madison"}, {"day": 4, "current_city": "Madison", "transportation": "-", "breakfast": "Unique Food Hut, Madison", "attraction": "Madison Children's Museum, Madison", "lunch": "Chini Bowl, Madison", "dinner": "Tibb's Frankie, Madison", "accommodation": "Oversized bedroom with living space, Madison"}, {"day": 5, "current_city": "from Madison to Devils Lake", "transportation": "Self-driving, Duration: 56 mins, Distance: 70.7 km", "breakfast": "Barbeque Nation, Madison", "attraction": "Olbrich Botanical Gardens, Madison", "lunch": "-", "dinner": "Boise Fry Company, Devils Lake", "accommodation": "Charming Cobble Hill Brownstone Apartment, Devils Lake"}, {"day": 6, "current_city": "Devils Lake", "transportation": "-", "breakfast": "AB's Absolute Barbecues, Devils Lake", "attraction": "Lake Region Heritage Center, Devils Lake", "lunch": "Dakshin Bistro, Devils Lake", "dinner": "Zaffran - The Claremont, Devils Lake", "accommodation": "Charming Cobble Hill Brownstone Apartment, Devils Lake"}, {"day": 7, "current_city": "from Devils Lake to Punta Gorda", "transportation": "Self-driving, Duration: 21 hours 4 mins, Distance: 2,346 km", "breakfast": "Din Tai Fung, Devils Lake", "attraction": "-", "lunch": "-", "dinner": "-", "accommodation": "-"}]}]