[{"gpt-4-1106-preview_direct_sole-planning_results": "Travel Plan:\n\nDay 1: March 5, 2022\nCurrent City: from Greer to Philadelphia\nTransportation: Flight Number: F3730589, from Greer to Philadelphia, Departure Time: 16:50, Arrival Time: 18:32, Cost: $153\nAttraction: Liberty Bell, Philadelphia, Cost: $0 (Assuming no entrance fee)\nDinner: Hong Kong Cafe, Philadelphia, Cost: $47, Cuisines: \"Tea, Pizza, Italian, BBQ, Cafe\"\nAccommodation: Industrial Loft Living in NYC, Philadelphia, Cost: $178, Room Type: Entire home/apt, House Rules: No smoking, Minimum Nights: 4\n\nTotal Cost for Day 1: $153 (Flight) + $47 (Dinner) + $178 (Accommodation) = $378\n\nDay 2: March 6, 2022\nCurrent City: Philadelphia\nBreakfast: Red Ginger Sushi, Grill & Bar, Philadelphia, Cost: $98, Cuisines: \"Tea, Cafe, Indian, Fast Food\"\nAttraction: Philadelphia Museum of Art, Philadelphia, Cost: $0 (Assuming no entrance fee)\nLunch: Marukame Udon, Philadelphia, Cost: $100, Cuisines: \"Tea, Pizza, Italian, BBQ, Fast Food, Chinese\"\nDinner: Red Mesa Cantina, Philadelphia, Cost: $36, Cuisines: \"Tea, Cafe, American, Fast Food\"\nAccommodation: Industrial Loft Living in NYC, Philadelphia, Cost: $178, Room Type: Entire home/apt, House Rules: No smoking, Minimum Nights: 4\n\nTotal Cost for Day 2: $98 (Breakfast) + $100 (Lunch) + $36 (Dinner) + $178 (Accommodation) = $412\n\nDay 3: March 7, 2022\nCurrent City: from Philadelphia to State College\nTransportation: Flight Number: F3734033, from Philadelphia to State College, Departure Time: 09:38, Arrival Time: 10:48, Cost: $73\nAttraction: The Arboretum at Penn State, State College, Cost: $0 (Assuming no entrance fee)\nLunch: Los Agaves, State College, Cost: $39, Cuisines: \"French, BBQ, Cafe\"\nDinner: Salsa's Mexican Restaurant, State College, Cost: $52, Cuisines: \"Tea, BBQ, Fast Food\"\nAccommodation: Charming 1BR in UES Townhouse, State College, Cost: $1134, Room Type: Entire home/apt, House Rules: No smoking, Minimum Nights: 30\n\nTotal Cost for Day 3: $73 (Flight) + $39 (Lunch) + $52 (Dinner) + $1134 (Accommodation) = $1298\n\nDay 4: March 8, 2022\nCurrent City: State College\nBreakfast: Fusion Food Corner, State College, Cost: $46, Cuisines: \"Bakery, Mexican, BBQ, Italian\"\nAttraction: Penn's Cave & Wildlife Park, State College, Cost: $0 (Assuming no entrance fee)\nLunch: Hotel Ekant, State College, Cost: $16, Cuisines: \"Fast Food, Pizza, Italian\"\nDinner: Amici Cafe, State College, Cost: $96, Cuisines: \"Pizza, Bakery, BBQ, Chinese, Seafood\"\nAccommodation: Charming 1BR in UES Townhouse, State College, Cost: $1134, Room Type: Entire home/apt, House Rules: No smoking, Minimum Nights: 30\n\nTotal Cost for Day 4: $46 (Breakfast) + $16 (Lunch) + $96 (Dinner) + $1134 (Accommodation) = $1292\n\nDay 5: March 9, 2022\nCurrent City: from State College to Greer\nTransportation: Self-driving, from State College to Greer, duration: 9 hours 30 mins, distance: 982 km, cost: $49\nAttraction: Discovery Space of Central Pennsylvania, State College, Cost: $0 (Assuming no entrance fee)\nLunch: Kawa Sushi, State College, Cost: $82, Cuisines: \"French, Mexican, Desserts, Fast Food\"\nAccommodation: -\n\nTotal Cost for Day 5: $49 (Transportation) + $82 (Lunch) = $131\n\nTotal cost across all days: $378 (Day 1) + $412 (Day 2) + $1298 (Day 3) + $1292 (Day 4) + $131 (Day 5) = $3511\n\nNote: The total cost exceeds the budget by $111. To stay within the budget, consider changing the accommodation in State College to a less expensive option or adjusting meal costs. Additionally, the accommodation in State College has a minimum stay of 30 nights, which is not suitable for this travel plan. A different accommodation must be selected to meet the travel plan requirements.\n\nRevised Accommodation for Day 3 and Day 4: Beautiful, Newly Furnished, Luxury, Grand Central, State College, Cost: $210, Room Type: Entire home/apt, House Rules: No parties, Minimum Nights: 30\n\nRevised Total Cost for Day 3: $73 (Flight) + $39 (Lunch) + $52 (Dinner) + $210 (Accommodation) = $374\nRevised Total Cost for Day 4: $46 (Breakfast) + $16 (Lunch) + $96 (Dinner) + $210 (Accommodation) = $368\n\nRevised Total cost across all days: $378 (Day 1) + $412 (Day 2) + $374 (Day 3) + $368 (Day 4) + $131 (Day 5) = $1663\n\nThe revised total cost is now within the budget of $3,400.", "gpt-4-1106-preview_direct_sole-planning_parsed_results": [{"day": 1, "current_city": "from Greer to Philadelphia", "transportation": "Flight Number: F3730589, from Greer to Philadelphia, Departure Time: 16:50, Arrival Time: 18:32", "breakfast": "-", "attraction": "Liberty Bell, Philadelphia;", "lunch": "-", "dinner": "Hong Kong Cafe, Philadelphia", "accommodation": "Industrial Loft Living in NYC, Philadelphia"}, {"day": 2, "current_city": "Philadelphia", "transportation": "-", "breakfast": "Red Ginger Sushi, Grill & Bar, Philadelphia", "attraction": "Philadelphia Museum of Art, Philadelphia;", "lunch": "Marukame Udon, Philadelphia", "dinner": "Red Mesa Cantina, Philadelphia", "accommodation": "Industrial Loft Living in NYC, Philadelphia"}, {"day": 3, "current_city": "from Philadelphia to State College", "transportation": "Flight Number: F3734033, from Philadelphia to State College, Departure Time: 09:38, Arrival Time: 10:48", "breakfast": "-", "attraction": "The Arboretum at Penn State, State College;", "lunch": "Los Agaves, State College", "dinner": "Salsa's Mexican Restaurant, State College", "accommodation": "Beautiful, Newly Furnished, Luxury, Grand Central, State College"}, {"day": 4, "current_city": "State College", "transportation": "-", "breakfast": "Fusion Food Corner, State College", "attraction": "Penn's Cave & Wildlife Park, State College;", "lunch": "Hotel Ekant, State College", "dinner": "Amici Cafe, State College", "accommodation": "Beautiful, Newly Furnished, Luxury, Grand Central, State College"}, {"day": 5, "current_city": "from State College to Greer", "transportation": "Self-driving, from State College to Greer", "breakfast": "-", "attraction": "Discovery Space of Central Pennsylvania, State College;", "lunch": "Kawa Sushi, State College", "dinner": "-", "accommodation": "-"}]}]