[{"gpt-4-1106-preview_direct_sole-planning_results": "Travel Plan:\n\nDay 1: March 1, 2022\nCurrent City: from Memphis to Minneapolis\nTransportation: Flight Number: F3836157, from Memphis to Minneapolis, Departure Time: 05:57, Arrival Time: 08:10, Cost: $260\nBreakfast: Not applicable (due to early flight)\nAttraction: Minneapolis Sculpture Garden, Minneapolis, Cost: Free\nLunch: The Cafe, Minneapolis, Cost: $14, Cuisines: \"Indian, Mediterranean, Desserts, Seafood\"\nDinner: Court Avenue Brewing Company, Minneapolis, Cost: $31, Cuisines: \"Pizza, French, Bakery, BBQ, Seafood\"\nAccommodation: Light-filled Apartment in great area, close 2 all!, Minneapolis, Cost: $343, Room Type: Entire home/apt, House Rules: No visitors, Minimum Nights: 1, Maximum Occupancy: 2\n\nNumber of People = 4\nTotal Cost = 4 * $260 (flight) + 4 * $14 (lunch) + 4 * $31 (dinner) + 2 * $343 (accommodation) = $2,012\n\nDay 2: March 2, 2022\nCurrent City: Minneapolis\nTransportation: Self-driving, Cost: $66\nBreakfast: Troll Tavern, Minneapolis, Cost: $71, Cuisines: \"Tea, BBQ, Mediterranean\"\nAttraction: Minneapolis Institute of Art, Minneapolis, Cost: Free\nLunch: Texas Roadhouse, Minneapolis, Cost: $22, Cuisines: \"Cafe, Pizza, BBQ, Desserts\"\nDinner: Monkeypod Kitchen by Merriman, Minneapolis, Cost: $50, Cuisines: \"Desserts, Pizza, Bakery, Fast Food, Indian, Mediterranean\"\nAccommodation: Light-filled Apartment in great area, close 2 all!, Minneapolis, Cost: $343, Room Type: Entire home/apt, House Rules: No visitors, Minimum Nights: 1, Maximum Occupancy: 2\n\nNumber of People = 4\nTotal Cost = $66 (transportation) + 4 * $71 (breakfast) + 4 * $22 (lunch) + 4 * $50 (dinner) + 2 * $343 (accommodation) = $1,548\n\nDay 3: March 3, 2022\nCurrent City: from Minneapolis to Gustavus\nTransportation: Taxi, from Minneapolis to Gustavus, Cost: $110\nBreakfast: Bobby Tikki Wala, Minneapolis, Cost: $62, Cuisines: \"Bakery, BBQ, Desserts, Seafood\"\nAttraction: Glacier Bay National Park Visitor Center, Gustavus, Cost: Free\nLunch: That Madras Place, Gustavus, Cost: $36, Cuisines: \"Desserts, Italian, Bakery, BBQ, Cafe\"\nDinner: On The Rocks - The Atrium, Gustavus, Cost: $60, Cuisines: \"Desserts, Tea, Pizza, Italian, Bakery, American\"\nAccommodation: Large Private Room in 3 bdr apt-East Village, Gustavus, Cost: $684, Room Type: Private room, House Rules: No smoking & No parties, Minimum Nights: 1, Maximum Occupancy: 2\n\nNumber of People = 4\nTotal Cost = $110 (transportation) + 4 * $62 (breakfast) + 4 * $36 (lunch) + 4 * $60 (dinner) + 2 * $684 (accommodation) = $3,292\n\nDay 4: March 4, 2022\nCurrent City: Gustavus\nTransportation: -\nBreakfast: Hofer's Bakery & Cafe, Gustavus, Cost: $34, Cuisines: \"Mexican, Bakery, BBQ, Fast Food, Cafe, American\"\nAttraction: NatVenture Tours, Gustavus, Cost: Free\nLunch: Tobasco Kitchen, Gustavus, Cost: $21, Cuisines: \"Desserts, Tea, Italian, Mexican, Bakery, Seafood\"\nDinner: The Grand Kitchen, Gustavus, Cost: $31, Cuisines: \"BBQ, Pizza, Desserts, Seafood\"\nAccommodation: Large Private Room in 3 bdr apt-East Village, Gustavus, Cost: $684, Room Type: Private room, House Rules: No smoking & No parties, Minimum Nights: 1, Maximum Occupancy: 2\n\nNumber of People = 4\nTotal Cost = 4 * $34 (breakfast) + 4 * $21 (lunch) + 4 * $31 (dinner) + 2 * $684 (accommodation) = $3,080\n\nDay 5: March 5, 2022\nCurrent City: from Gustavus to Memphis\nTransportation: Self-driving, from Gustavus to Memphis, Cost: $64\nBreakfast: Imperfecto, Gustavus, Cost: $10, Cuisines: \"Tea, Cafe, BBQ, Fast Food\"\nLunch: Gelato Vinto, Gustavus, Cost: $14, Cuisines: \"Cafe, Bakery, Fast Food, Chinese, Seafood\"\nDinner: Not applicable (due to travel)\nAccommodation: Not applicable (returning home)\n\nNumber of People = 4\nTotal Cost = $64 (transportation) + 4 * $10 (breakfast) + 4 * $14 (lunch) = $256\n\nTotal cost across all days = $2,012 + $1,548 + $3,292 + $3,080 + $256 = $10,188\n\nRemaining Budget: $13,800 - $10,188 = $3,612\n\nCuisines: The prompt specifies no cuisines, so all cuisines constraints are satisfied.\n\nPlease note that the travel plan assumes the availability of the listed flights, accommodations, and restaurants on the specified dates. The costs are based on the provided reference information and may be subject to change. The plan also assumes that the attractions are open and available during the visit.", "gpt-4-1106-preview_direct_sole-planning_parsed_results": [{"day": 1, "current_city": "from Memphis to Minneapolis", "transportation": "Flight Number: F3836157, from Memphis to Minneapolis, Departure Time: 05:57, Arrival Time: 08:10", "breakfast": "-", "attraction": "Minneapolis Sculpture Garden, Minneapolis;", "lunch": "The Cafe, Minneapolis", "dinner": "Court Avenue Brewing Company, Minneapolis", "accommodation": "Light-filled Apartment in great area, close 2 all!, Minneapolis"}, {"day": 2, "current_city": "Minneapolis", "transportation": "-", "breakfast": "Troll Tavern, Minneapolis", "attraction": "Minneapolis Institute of Art, Minneapolis;", "lunch": "Texas Roadhouse, Minneapolis", "dinner": "Monkeypod Kitchen by Merriman, Minneapolis", "accommodation": "Light-filled Apartment in great area, close 2 all!, Minneapolis"}, {"day": 3, "current_city": "from Minneapolis to Gustavus", "transportation": "Taxi, from Minneapolis to Gustavus", "breakfast": "Bobby Tikki Wala, Minneapolis", "attraction": "Glacier Bay National Park Visitor Center, Gustavus;", "lunch": "That Madras Place, Gustavus", "dinner": "On The Rocks - The Atrium, Gustavus", "accommodation": "Large Private Room in 3 bdr apt-East Village, Gustavus"}, {"day": 4, "current_city": "Gustavus", "transportation": "-", "breakfast": "Hofer's Bakery & Cafe, Gustavus", "attraction": "NatVenture Tours, Gustavus;", "lunch": "Tobasco Kitchen, Gustavus", "dinner": "The Grand Kitchen, Gustavus", "accommodation": "Large Private Room in 3 bdr apt-East Village, Gustavus"}, {"day": 5, "current_city": "from Gustavus to Memphis", "transportation": "Self-driving, from Gustavus to Memphis", "breakfast": "Imperfecto, Gustavus", "lunch": "Gelato Vinto, Gustavus", "dinner": "-", "accommodation": "-"}]}]