[{"gpt-4-1106-preview_direct_sole-planning_results": "Travel Plan:\n\nDay 1: March 17, 2022\nCurrent City: from St. Louis to San Diego\nTransportation: Flight Number: F4025732, from St. Louis to San Diego, Departure Time: 16:42, Arrival Time: 18:31, Cost: $430 per person\nBreakfast: - (Assuming departure is after breakfast)\nLunch: - (Assuming lunch is not required due to flight timing)\nDinner: Open Yard, San Diego, Cost: $33, Cuisines: \"Chinese, Pizza, Cafe, Desserts\"\nAccommodation: Spacious Room in Large 2 Bedroom Prewar Apartment, San Diego, Cost: $585, Room Type: Private room, House Rules: No parties & No visitors, Minimum Nights: 1, Maximum Occupancy: 2\n\nNumber of People = 2\nTotal Cost = 2 * $430 (flight) + 2 * $33 (dinner) + $585 (accommodation) = $1511\n\nDay 2: March 18, 2022\nCurrent City: San Diego\nTransportation: -\nBreakfast: Jetha Lal Ka Dhabha, San Diego, Cost: $22, Cuisines: \"Tea, Cafe, Indian, Italian\"\nAttraction: Cabrillo National Monument, San Diego\nLunch: Bikaner Sweets, San Diego, Cost: $37, Cuisines: \"Bakery, Pizza, Indian, Fast Food\"\nDinner: Gopala, San Diego, Cost: $98, Cuisines: \"Pizza, Mexican, BBQ, American, Seafood\"\nAccommodation: Spacious Room in Large 2 Bedroom Prewar Apartment, San Diego, Cost: $585, Room Type: Private room, House Rules: No parties & No visitors, Minimum Nights: 1, Maximum Occupancy: 2\n\nNumber of People = 2\nTotal Cost = 2 * $22 (breakfast) + 2 * $37 (lunch) + 2 * $98 (dinner) + $585 (accommodation) = $899\n\nDay 3: March 19, 2022\nCurrent City: from San Diego to San Francisco\nTransportation: Flight Number: F3819397, from San Diego to San Francisco, Departure Time: 18:38, Arrival Time: 20:10, Cost: $93 per person\nBreakfast: Momos Hut & Chinese Food, San Diego, Cost: $94, Cuisines: \"Tea, Cafe, Fast Food\"\nAttraction: SeaWorld San Diego, San Diego\nLunch: Chaudhary Di Hatti, San Diego, Cost: $30, Cuisines: \"Desserts, Pizza, Italian, BBQ, Fast Food\"\nDinner: - (Assuming dinner in San Francisco post-arrival)\nAccommodation: Cozy, spacious Studio located on Upper East Side, San Francisco, Cost: $756, Room Type: Entire home/apt, House Rules: No visitors, Minimum Nights: 3, Maximum Occupancy: 2\n\nNumber of People = 2\nTotal Cost = 2 * $93 (flight) + 2 * $94 (breakfast) + 2 * $30 (lunch) + $756 (accommodation) = $1190\n\nDay 4: March 20, 2022\nCurrent City: San Francisco\nTransportation: -\nBreakfast: Tokyo Sushi, San Francisco, Cost: $18, Cuisines: \"Cafe, Pizza, BBQ\"\nAttraction: Golden Gate Bridge, San Francisco\nLunch: Coffee & Chai Co., San Francisco, Cost: $10, Cuisines: \"Tea, Mexican, BBQ, Cafe, Seafood\"\nDinner: Empress, San Francisco, Cost: $24, Cuisines: \"Pizza, BBQ, Mediterranean, Fast Food\"\nAccommodation: Cozy, spacious Studio located on Upper East Side, San Francisco, Cost: $756, Room Type: Entire home/apt, House Rules: No visitors, Minimum Nights: 3, Maximum Occupancy: 2\n\nNumber of People = 2\nTotal Cost = 2 * $18 (breakfast) + 2 * $10 (lunch) + 2 * $24 (dinner) + $756 (accommodation) = $860\n\nDay 5: March 21, 2022\nCurrent City: from San Francisco to Long Beach\nTransportation: Self-driving, from San Francisco to Long Beach, Duration: 6 hours 12 mins, Distance: 651 km, Cost: $32 per person\nBreakfast: Bonne Bouche, San Francisco, Cost: $21, Cuisines: \"Tea, Chinese, American, Cafe\"\nAttraction: Exploratorium, San Francisco\nLunch: AK Your Food, San Francisco, Cost: $100, Cuisines: \"Bakery, Pizza\"\nDinner: - (Assuming dinner in Long Beach post-arrival)\nAccommodation: NYC High End Upper East Side Central Park Gem Home, Long Beach, Cost: $119, Room Type: Entire home/apt, House Rules: No visitors, Minimum Nights: 1, Maximum Occupancy: 3\n\nNumber of People = 2\nTotal Cost = 2 * $32 (transportation) + 2 * $21 (breakfast) + 2 * $100 (lunch) + $119 (accommodation) = $425\n\nDay 6: March 22, 2022\nCurrent City: Long Beach\nTransportation: -\nBreakfast: Giuseppe's Pizza & Italian Specialities, Long Beach, Cost: $72, Cuisines: \"Bakery, Fast Food, Cafe, Indian, Mediterranean, Seafood\"\nAttraction: Aquarium of the Pacific, Long Beach\nLunch: Greek Village, Long Beach, Cost: $80, Cuisines: \"Desserts, Italian, Bakery, BBQ, Chinese\"\nDinner: The Chicken Dinesty, Long Beach, Cost: $92, Cuisines: \"French, Pizza, Seafood\"\nAccommodation: NYC High End Upper East Side Central Park Gem Home, Long Beach, Cost: $119, Room Type: Entire home/apt, House Rules: No visitors, Minimum Nights: 1, Maximum Occupancy: 3\n\nNumber of People = 2\nTotal Cost = 2 * $72 (breakfast) + 2 * $80 (lunch) + 2 * $92 (dinner) + $119 (accommodation) = $607\n\nDay 7: March 23, 2022\nCurrent City: from Long Beach to St. Louis\nTransportation: Flight Number: F3986547, from Long Beach to St. Louis, Departure Time: 07:04, Arrival Time: 12:37, Cost: $370 per person\nBreakfast: - (Assuming departure is before breakfast)\nLunch: - (Assuming lunch is not required due to flight timing)\nDinner: - (Assuming arrival back in St. Louis)\nAccommodation: -\n\nNumber of People = 2\nTotal Cost = 2 * $370 (flight) = $740\n\nTotal cost across all days = $1511 + $899 + $1190 + $860 + $425 + $607 + $740 = $6232\n\nCuisines: The plan includes American and Chinese cuisines as specified.\n\nRemaining Budget: $9500 - $6232 = $3268\n\nPlease note that the costs for attractions and some meals are not included due to lack of pricing information. The remaining budget can be used for these activities, additional meals, and any incidental expenses. The accommodation choices are based on the provided data and assume that the prices are for the entire room/apartment per night. The travel plan adheres to the specified budget, cuisine preferences, and includes a variety of attractions in each city.", "gpt-4-1106-preview_direct_sole-planning_parsed_results": [{"day": 1, "current_city": "from St. Louis to San Diego", "transportation": "Flight Number: F4025732, from St. Louis to San Diego, Departure Time: 16:42, Arrival Time: 18:31", "breakfast": "-", "attraction": "-", "lunch": "-", "dinner": "Open Yard, San Diego", "accommodation": "Spacious Room in Large 2 Bedroom Prewar Apartment, San Diego"}, {"day": 2, "current_city": "San Diego", "transportation": "-", "breakfast": "Jetha Lal Ka Dhabha, San Diego", "attraction": "Cabrillo National Monument, San Diego", "lunch": "Bikaner Sweets, San Diego", "dinner": "Gopala, San Diego", "accommodation": "Spacious Room in Large 2 Bedroom Prewar Apartment, San Diego"}, {"day": 3, "current_city": "from San Diego to San Francisco", "transportation": "Flight Number: F3819397, from San Diego to San Francisco, Departure Time: 18:38, Arrival Time: 20:10", "breakfast": "Momos Hut & Chinese Food, San Diego", "attraction": "SeaWorld San Diego, San Diego", "lunch": "Chaudhary Di Hatti, San Diego", "dinner": "-", "accommodation": "Cozy, spacious Studio located on Upper East Side, San Francisco"}, {"day": 4, "current_city": "San Francisco", "transportation": "-", "breakfast": "Tokyo Sushi, San Francisco", "attraction": "Golden Gate Bridge, San Francisco", "lunch": "Coffee & Chai Co., San Francisco", "dinner": "Empress, San Francisco", "accommodation": "Cozy, spacious Studio located on Upper East Side, San Francisco"}, {"day": 5, "current_city": "from San Francisco to Long Beach", "transportation": "Self-driving, from San Francisco to Long Beach, Duration: 6 hours 12 mins, Distance: 651 km", "breakfast": "Bonne Bouche, San Francisco", "attraction": "Exploratorium, San Francisco", "lunch": "AK Your Food, San Francisco", "dinner": "-", "accommodation": "NYC High End Upper East Side Central Park Gem Home, Long Beach"}, {"day": 6, "current_city": "Long Beach", "transportation": "-", "breakfast": "Giuseppe's Pizza & Italian Specialities, Long Beach", "attraction": "Aquarium of the Pacific, Long Beach", "lunch": "Greek Village, Long Beach", "dinner": "The Chicken Dinesty, Long Beach", "accommodation": "NYC High End Upper East Side Central Park Gem Home, Long Beach"}, {"day": 7, "current_city": "from Long Beach to St. Louis", "transportation": "Flight Number: F3986547, from Long Beach to St. Louis, Departure Time: 07:04, Arrival Time: 12:37", "breakfast": "-", "attraction": "-", "lunch": "-", "dinner": "-", "accommodation": "-"}]}]