[{"gpt-4-1106-preview_direct_sole-planning_results": "Travel Plan:\n\nDay 1: March 13, 2022\nCurrent City: from Asheville to New York\nTransportation: Flight Number: F3641730, from Asheville to New York, Departure Time: 13:49, Arrival Time: 15:40, Cost: $214 per person\nBreakfast: - (Assuming breakfast is not required as the flight is post-breakfast time)\nAttraction: Central Park, New York\nLunch: Shokitini, New York, Cost: $41, Cuisines: \"Tea, Cafe, Pizza, Mexican, Chinese, Seafood\"\nDinner: Tibby's New Orleans Kitchen, New York, Cost: $48, Cuisines: \"Seafood, Indian, BBQ, Italian\" (Note: Mexican and Chinese options are limited; this restaurant has a diverse menu that may include some dishes of interest)\nAccommodation: Versatile private room in Harlem/Hamilton Heights!, New York, Cost: $398, Room Type: Private room, House Rules: No pets & No visitors & No parties, Maximum Occupancy: 1\n\nNumber of People = 2\nTotal Cost = 2 * $214 + 2 * $41 + 2 * $48 + $398 = $1004\n\nDay 2: March 14, 2022\nCurrent City: New York\nTransportation: -\nBreakfast: Shokitini, New York, Cost: $41, Cuisines: \"Tea, Cafe, Pizza, Mexican, Chinese, Seafood\"\nAttraction: The Statue of Liberty, New York\nLunch: Punjab Grill, New York, Cost: $25, Cuisines: \"Bakery, BBQ, Desserts, Seafood\"\nDinner: Shama Chicken Corner, New York, Cost: $25, Cuisines: \"Tea, Chinese, Desserts\"\nAccommodation: Versatile private room in Harlem/Hamilton Heights!, New York, Cost: $398, Room Type: Private room, House Rules: No pets & No visitors & No parties, Maximum Occupancy: 1\n\nNumber of People = 2\nTotal Cost = 2 * $41 + 2 * $25 + 2 * $25 + $398 = $596\n\nDay 3: March 15, 2022\nCurrent City: from New York to Buffalo\nTransportation: Flight Number: F3641101, from New York to Buffalo, Departure Time: 11:59, Arrival Time: 13:09, Cost: $61 per person\nBreakfast: - (Assuming breakfast is not required as the flight is post-breakfast time)\nAttraction: Buffalo Naval Park, Buffalo\nLunch: Shokitini, Buffalo, Cost: $41, Cuisines: \"Tea, Cafe, Pizza, Mexican, Chinese, Seafood\"\nDinner: Tibby's New Orleans Kitchen, Buffalo, Cost: $48, Cuisines: \"Seafood, Indian, BBQ, Italian\" (Note: Mexican and Chinese options are limited; this restaurant has a diverse menu that may include some dishes of interest)\nAccommodation: Cozy Studio in Heart of Ft Greene, Buffalo, Cost: $200, Room Type: Entire home/apt, House Rules: No pets & No children under 10, Maximum Occupancy: 3\n\nNumber of People = 2\nTotal Cost = 2 * $61 + 2 * $41 + 2 * $48 + $200 = $500\n\nDay 4: March 16, 2022\nCurrent City: Buffalo\nTransportation: -\nBreakfast: Shokitini, Buffalo, Cost: $41, Cuisines: \"Tea, Cafe, Pizza, Mexican, Chinese, Seafood\"\nAttraction: The Buffalo Zoo, Buffalo\nLunch: Punjab Grill, Buffalo, Cost: $25, Cuisines: \"Bakery, BBQ, Desserts, Seafood\"\nDinner: Shama Chicken Corner, Buffalo, Cost: $25, Cuisines: \"Tea, Chinese, Desserts\"\nAccommodation: Cozy Studio in Heart of Ft Greene, Buffalo, Cost: $200, Room Type: Entire home/apt, House Rules: No pets & No children under 10, Maximum Occupancy: 3\n\nNumber of People = 2\nTotal Cost = 2 * $41 + 2 * $25 + 2 * $25 + $200 = $358\n\nDay 5: March 17, 2022\nCurrent City: from Buffalo to Asheville\nTransportation: Self-driving, from Buffalo to Asheville, duration: 10 hours 29 mins, distance: 1,110 km, Cost: $55 per person\nBreakfast: Shokitini, Buffalo, Cost: $41, Cuisines: \"Tea, Cafe, Pizza, Mexican, Chinese, Seafood\"\nAttraction: - (Assuming no attractions due to travel time)\nLunch: - (Assuming lunch on the road)\nDinner: - (Assuming dinner on the road or after arrival)\nAccommodation: -\n\nNumber of People = 2\nTotal Cost = 2 * $55 + 2 * $41 = $192\n\nTotal cost across all days = $1004 + $596 + $500 + $358 + $192 = $2650\n\nCuisines: The plan includes restaurants offering Mexican and Chinese cuisines as requested.\n\nPlease note that the accommodation chosen has a maximum occupancy of 1, so two rooms are required for two people, doubling the accommodation cost. However, the provided accommodation data does not offer a clear option for two people within the budget constraints, so the plan assumes a single room can be booked twice for two people. If this is not possible, alternative accommodation must be found.\n\nThe total cost is well within the budget of $4,700. The plan includes transportation, meals, attractions, and accommodation for each day, adhering to the constraints provided.", "gpt-4-1106-preview_direct_sole-planning_parsed_results": [{"day": 1, "current_city": "from Asheville to New York", "transportation": "Flight Number: F3641730, from Asheville to New York, Departure Time: 13:49, Arrival Time: 15:40", "breakfast": "-", "attraction": "Central Park, New York;", "lunch": "Shokitini, New York", "dinner": "Tibby's New Orleans Kitchen, New York", "accommodation": "Versatile private room in Harlem/Hamilton Heights!, New York"}, {"day": 2, "current_city": "New York", "transportation": "-", "breakfast": "Shokitini, New York", "attraction": "The Statue of Liberty, New York;", "lunch": "Punjab Grill, New York", "dinner": "Shama Chicken Corner, New York", "accommodation": "Versatile private room in Harlem/Hamilton Heights!, New York"}, {"day": 3, "current_city": "from New York to Buffalo", "transportation": "Flight Number: F3641101, from New York to Buffalo, Departure Time: 11:59, Arrival Time: 13:09", "breakfast": "-", "attraction": "Buffalo Naval Park, Buffalo;", "lunch": "Shokitini, Buffalo", "dinner": "Tibby's New Orleans Kitchen, Buffalo", "accommodation": "Cozy Studio in Heart of Ft Greene, Buffalo"}, {"day": 4, "current_city": "Buffalo", "transportation": "-", "breakfast": "Shokitini, Buffalo", "attraction": "The Buffalo Zoo, Buffalo;", "lunch": "Punjab Grill, Buffalo", "dinner": "Shama Chicken Corner, Buffalo", "accommodation": "Cozy Studio in Heart of Ft Greene, Buffalo"}, {"day": 5, "current_city": "from Buffalo to Asheville", "transportation": "Self-driving, from Buffalo to Asheville, duration: 10 hours 29 mins, distance: 1,110 km", "breakfast": "Shokitini, Buffalo", "attraction": "-", "lunch": "-", "dinner": "-", "accommodation": "-"}]}]