[{"gpt-4-1106-preview_direct_sole-planning_results": "Travel Plan:\n\nDay 1: March 18, 2022\nCurrent City: Daytona Beach to Corpus Christi\nTransportation: Self-driving, Duration: 16 hours 54 mins, Distance: 1,874 km, Cost: $93\nAccommodation: Penthouse Apartment in Chelsea, Corpus Christi, Cost: $412, Room Type: Entire home/apt, House Rules: No children under 10, Minimum Nights: 2, Maximum Occupancy: 3\n\nTotal Cost for Day 1: $93 (transportation) + $412 (accommodation) = $505\n\nDay 2: March 19, 2022\nCurrent City: Corpus Christi\nBreakfast: Confeitaria Colombo, Corpus Christi, Cost: $11, Cuisines: Tea, Chinese, Bakery, Cafe\nAttraction: Texas State Aquarium, Corpus Christi\nLunch: Sangeetha Vegetarian Restaurant, Corpus Christi, Cost: $91, Cuisines: Desserts, Tea, Pizza, French, BBQ\nDinner: The Binge Box Cafe, Corpus Christi, Cost: $32, Cuisines: Desserts, Italian, Bakery, Indian, Seafood\nAccommodation: Penthouse Apartment in Chelsea, Corpus Christi, Cost: $412\n\nTotal Cost for Day 2: $11 (breakfast) + $91 (lunch) + $32 (dinner) + $412 (accommodation) = $546\n\nDay 3: March 20, 2022\nCurrent City: Corpus Christi to San Antonio\nTransportation: Self-driving, Duration: 2 hours 3 mins, Distance: 231 km, Cost: $11\nAccommodation: Airy Brooklyn Limestone: 2 bedroom suite, San Antonio, Cost: $603, Room Type: Private room, House Rules: No visitors & No children under 10, Minimum Nights: 3, Maximum Occupancy: 2\n\nTotal Cost for Day 3: $11 (transportation) + $603 (accommodation) = $614\n\nDay 4: March 21, 2022\nCurrent City: San Antonio\nBreakfast: Cafe Le Rue @ The Landings, San Antonio, Cost: $19, Cuisines: French, Mexican, Cafe, Seafood\nAttraction: San Antonio River Walk, San Antonio\nLunch: Burger Queen Drive In, San Antonio, Cost: $64, Cuisines: Cafe, Bakery, Fast Food\nDinner: Martin's BBQ, San Antonio, Cost: $71, Cuisines: Tea, BBQ, Fast Food, Indian, Seafood\nAccommodation: Airy Brooklyn Limestone: 2 bedroom suite, San Antonio, Cost: $603\n\nTotal Cost for Day 4: $19 (breakfast) + $64 (lunch) + $71 (dinner) + $603 (accommodation) = $757\n\nDay 5: March 22, 2022\nCurrent City: San Antonio to Dallas\nTransportation: Flight Number: F3984242, Price: $69, DepTime: 07:55, ArrTime: 08:44\nAccommodation: Luxury Williamsburg duplex, private roof terrace, Dallas, Cost: $241, Room Type: Entire home/apt, House Rules: No visitors, Minimum Nights: 4, Maximum Occupancy: 3\n\nTotal Cost for Day 5: $69 (flight) + $241 (accommodation) = $310\n\nDay 6: March 23, 2022\nCurrent City: Dallas\nBreakfast: Coconuts Fish Cafe, Dallas, Cost: $38, Cuisines: Cafe, BBQ, Mediterranean, Fast Food\nAttraction: The Dallas World Aquarium, Dallas\nLunch: 1918 Bistro & Grill, Dallas, Cost: $90, Cuisines: Tea, Pizza, BBQ, Seafood\nDinner: Yanki Sizzlers, Dallas, Cost: $96, Cuisines: Cafe, French, Tea, Mediterranean\nAccommodation: Luxury Williamsburg duplex, private roof terrace, Dallas, Cost: $241\n\nTotal Cost for Day 6: $38 (breakfast) + $90 (lunch) + $96 (dinner) + $241 (accommodation) = $465\n\nDay 7: March 24, 2022\nCurrent City: Dallas to Daytona Beach\nTransportation: Flight Number: F4045344, Price: $222, DepTime: 12:44, ArrTime: 16:33\n\nTotal Cost for Day 7: $222 (flight)\n\nTotal cost across all days: $505 (Day 1) + $546 (Day 2) + $614 (Day 3) + $757 (Day 4) + $310 (Day 5) + $465 (Day 6) + $222 (Day 7) = $3419\n\nRemaining Budget: $3600 - $3419 = $181\n\nNote: All costs are in USD. The plan includes transportation, meals, attractions, and accommodations for each day. The total cost is within the specified budget of $3,600. Attractions and restaurants are chosen based on availability and proximity to the accommodation. The travel plan adheres to the constraints of starting and ending in the same city (Daytona Beach) and visiting 3 distinct cities in Texas (Corpus Christi, San Antonio, Dallas) over a span of 7 days.", "gpt-4-1106-preview_direct_sole-planning_parsed_results": [{"day": 1, "current_city": "from Daytona Beach to Corpus Christi", "transportation": "Self-driving, from Daytona Beach to Corpus Christi, Duration: 16 hours 54 mins, Distance: 1,874 km", "breakfast": "-", "attraction": "-", "lunch": "-", "dinner": "-", "accommodation": "Penthouse Apartment in Chelsea, Corpus Christi"}, {"day": 2, "current_city": "Corpus Christi", "transportation": "-", "breakfast": "Confeitaria Colombo, Corpus Christi", "attraction": "Texas State Aquarium, Corpus Christi", "lunch": "Sangeetha Vegetarian Restaurant, Corpus Christi", "dinner": "The Binge Box Cafe, Corpus Christi", "accommodation": "Penthouse Apartment in Chelsea, Corpus Christi"}, {"day": 3, "current_city": "from Corpus Christi to San Antonio", "transportation": "Self-driving, from Corpus Christi to San Antonio, Duration: 2 hours 3 mins, Distance: 231 km", "breakfast": "-", "attraction": "-", "lunch": "-", "dinner": "-", "accommodation": "Airy Brooklyn Limestone: 2 bedroom suite, San Antonio"}, {"day": 4, "current_city": "San Antonio", "transportation": "-", "breakfast": "Cafe Le Rue @ The Landings, San Antonio", "attraction": "San Antonio River Walk, San Antonio", "lunch": "Burger Queen Drive In, San Antonio", "dinner": "Martin's BBQ, San Antonio", "accommodation": "Airy Brooklyn Limestone: 2 bedroom suite, San Antonio"}, {"day": 5, "current_city": "from San Antonio to Dallas", "transportation": "Flight Number: F3984242, from San Antonio to Dallas, Departure Time: 07:55, Arrival Time: 08:44", "breakfast": "-", "attraction": "-", "lunch": "-", "dinner": "-", "accommodation": "Luxury Williamsburg duplex, private roof terrace, Dallas"}, {"day": 6, "current_city": "Dallas", "transportation": "-", "breakfast": "Coconuts Fish Cafe, Dallas", "attraction": "The Dallas World Aquarium, Dallas", "lunch": "1918 Bistro & Grill, Dallas", "dinner": "Yanki Sizzlers, Dallas", "accommodation": "Luxury Williamsburg duplex, private roof terrace, Dallas"}, {"day": 7, "current_city": "from Dallas to Daytona Beach", "transportation": "Flight Number: F4045344, from Dallas to Daytona Beach, Departure Time: 12:44, Arrival Time: 16:33", "breakfast": "-", "attraction": "-", "lunch": "-", "dinner": "-", "accommodation": "-"}]}]