[{"gpt-4-1106-preview_direct_sole-planning_results": "Travel Plan:\n\nDay 1: March 25, 2022\nCurrent City: Santa Ana to Abilene\nTransportation: Self-driving, from Santa Ana to Abilene, Duration: 18 hours 6 mins, Distance: 2,002 km, Cost: $100\nAccommodation: Joyce and Donovan's, Room for One, Abilene, Cost: $83, Room Type: Private room, House Rules: No parties, Minimum Nights: 25, Maximum Occupancy: 2\n\nNumber of People = 4\nTotal Cost = 4 * 100 + 2 * 83 = $566\n\nDay 2: March 26, 2022\nCurrent City: Abilene\nBreakfast: Thai Garden, Abilene, Cost: $13, Cuisines: Cafe, American, Desserts\nAttraction: The Grace Museum, Abilene\nLunch: Crispy Crust, Abilene, Cost: $54, Cuisines: Desserts, Bakery, Cafe, American, Seafood\nDinner: Finger Licious, Abilene, Cost: $35, Cuisines: Fast Food, Cafe, BBQ, Seafood\nAccommodation: Joyce and Donovan's, Room for One, Abilene, Cost: $83, Room Type: Private room, House Rules: No parties, Minimum Nights: 25, Maximum Occupancy: 2\n\nNumber of People = 4\nTotal Cost = 4 * 13 + 4 * 54 + 4 * 35 + 2 * 83 = $662\n\nDay 3: March 27, 2022\nCurrent City: Abilene to Amarillo\nTransportation: Self-driving, from Abilene to Amarillo, Duration: 4 hours 10 mins, Distance: 446 km, Cost: $22\nAccommodation: Harlem Humble Abode - 1 bedroom - Cute and Quaint, Amarillo, Cost: $409, Room Type: Entire home/apt, House Rules: No pets, Minimum Nights: 5, Maximum Occupancy: 3\n\nNumber of People = 4\nTotal Cost = 4 * 22 + 2 * 409 = $890\n\nDay 4: March 28, 2022\nCurrent City: Amarillo\nBreakfast: The Cinnamon Kitchen, Amarillo, Cost: $69, Cuisines: Desserts, Tea, Pizza, Chinese, Seafood\nAttraction: Cadillac Ranch, Amarillo\nLunch: Komachi, Amarillo, Cost: $71, Cuisines: Desserts, Tea, Fast Food, Chinese, Mediterranean\nDinner: Kanha North & South Indian Veg., Amarillo, Cost: $34, Cuisines: Tea, Cafe, BBQ, Fast Food\nAccommodation: Harlem Humble Abode - 1 bedroom - Cute and Quaint, Amarillo, Cost: $409, Room Type: Entire home/apt, House Rules: No pets, Minimum Nights: 5, Maximum Occupancy: 3\n\nNumber of People = 4\nTotal Cost = 4 * 69 + 4 * 71 + 4 * 34 + 2 * 409 = $1,354\n\nDay 5: March 29, 2022\nCurrent City: Amarillo to Lubbock\nTransportation: Self-driving, from Amarillo to Lubbock, Duration: 1 hour 47 mins, Distance: 197 km, Cost: $9\nAccommodation: Private bedroom in UWS Apartment, Lubbock, Cost: $709, Room Type: Private room, House Rules: No visitors & No pets, Minimum Nights: 2, Maximum Occupancy: 2\n\nNumber of People = 4\nTotal Cost = 4 * 9 + 2 * 709 = $1,445\n\nDay 6: March 30, 2022\nCurrent City: Lubbock\nBreakfast: Cantinho da Gula, Lubbock, Cost: $78, Cuisines: Cafe, BBQ, Desserts, Italian\nAttraction: Buddy Holly Center, Lubbock\nLunch: Paris 6 Classique, Lubbock, Cost: $91, Cuisines: Desserts, Cafe, Pizza, Mexican, BBQ, Chinese\nDinner: 3 Squares Diner, Lubbock, Cost: $73, Cuisines: Pizza, Indian, Fast Food\nAccommodation: Private bedroom in UWS Apartment, Lubbock, Cost: $709, Room Type: Private room, House Rules: No visitors & No pets, Minimum Nights: 2, Maximum Occupancy: 2\n\nNumber of People = 4\nTotal Cost = 4 * 78 + 4 * 91 + 4 * 73 + 2 * 709 = $1,930\n\nDay 7: March 31, 2022\nCurrent City: Lubbock to Santa Ana\nTransportation: Self-driving, from Lubbock to Santa Ana, Duration: 16 hours 28 mins, Distance: 1,780 km, Cost: $89\n\nNumber of People = 4\nTotal Cost = 4 * 89 = $356\n\nTotal cost across all days = $566 + $662 + $890 + $1,354 + $1,445 + $1,930 + $356 = $7,203\n\nUnfortunately, the total cost exceeds the specified budget of $5,800. Adjustments will need to be made to the plan to reduce costs, such as selecting more affordable accommodations or dining options. Please note that the provided accommodation options may not all accommodate children under the age of 10, as the query requires. Further adjustments may be necessary to ensure compliance with this requirement.", "gpt-4-1106-preview_direct_sole-planning_parsed_results": [{"day": 1, "current_city": "from Santa Ana to Abilene", "transportation": "Self-driving, from Santa Ana to Abilene, Duration: 18 hours 6 mins, Distance: 2,002 km", "breakfast": "-", "attraction": "-", "lunch": "-", "dinner": "-", "accommodation": "Joyce and Donovan's, Room for One, Abilene"}, {"day": 2, "current_city": "Abilene", "transportation": "-", "breakfast": "Thai Garden, Abilene", "attraction": "The Grace Museum, Abilene", "lunch": "Crispy Crust, Abilene", "dinner": "Finger Licious, Abilene", "accommodation": "Joyce and Donovan's, Room for One, Abilene"}, {"day": 3, "current_city": "from Abilene to Amarillo", "transportation": "Self-driving, from Abilene to Amarillo, Duration: 4 hours 10 mins, Distance: 446 km", "breakfast": "-", "attraction": "-", "lunch": "-", "dinner": "-", "accommodation": "Harlem Humble Abode - 1 bedroom - Cute and Quaint, Amarillo"}, {"day": 4, "current_city": "Amarillo", "transportation": "-", "breakfast": "The Cinnamon Kitchen, Amarillo", "attraction": "Cadillac Ranch, Amarillo", "lunch": "Komachi, Amarillo", "dinner": "Kanha North & South Indian Veg., Amarillo", "accommodation": "Harlem Humble Abode - 1 bedroom - Cute and Quaint, Amarillo"}, {"day": 5, "current_city": "from Amarillo to Lubbock", "transportation": "Self-driving, from Amarillo to Lubbock, Duration: 1 hour 47 mins, Distance: 197 km", "breakfast": "-", "attraction": "-", "lunch": "-", "dinner": "-", "accommodation": "Private bedroom in UWS Apartment, Lubbock"}, {"day": 6, "current_city": "Lubbock", "transportation": "-", "breakfast": "Cantinho da Gula, Lubbock", "attraction": "Buddy Holly Center, Lubbock", "lunch": "Paris 6 Classique, Lubbock", "dinner": "3 Squares Diner, Lubbock", "accommodation": "Private bedroom in UWS Apartment, Lubbock"}, {"day": 7, "current_city": "from Lubbock to Santa Ana", "transportation": "Self-driving, from Lubbock to Santa Ana, Duration: 16 hours 28 mins, Distance: 1,780 km", "breakfast": "-", "attraction": "-", "lunch": "-", "dinner": "-", "accommodation": "-"}]}]