[{"gpt-4-1106-preview_direct_sole-planning_results": "Travel Plan:\n\nDay 1: March 20, 2022\nCurrent City: from Houston to Fayetteville\nTransportation: Flight Number: F3923439, from Houston to Fayetteville, Departure Time: 09:29, Arrival Time: 11:04, Cost: $157 per person\nBreakfast: - (Assuming breakfast is had before departure or during the flight)\nAttraction: The Fayetteville Area Transportation and Local History Museum, Fayetteville (Open during business hours)\nLunch: Biryani By Kilo, Fayetteville, Cost: $53, Cuisines: \"Desserts, Pizza, American, Mediterranean, Seafood\"\nDinner: Eat Street, Fayetteville, Cost: $63, Cuisines: \"Tea, French, BBQ, Seafood\"\nAccommodation: *CoZy Private Williamsburg Home*, Fayetteville, Cost: $546, Entire home/apt, House Rules: No children under 10 & No smoking & No visitors, Minimum Nights: 2, Maximum Occupancy: 5\n\nNumber of People = 2\nTotal Cost = 2 * $157 + 2 * $53 + 2 * $63 + $546 = $1082\n\nDay 2: March 21, 2022\nCurrent City: Fayetteville\nTransportation: -\nBreakfast: Kay's Food Land, Fayetteville, Cost: $87, Cuisines: \"Cafe, Pizza, BBQ\"\nAttraction: Cape Fear Botanical Garden, Fayetteville (Open during business hours)\nLunch: Oriental Fusion, Fayetteville, Cost: $56, Cuisines: \"Bakery, BBQ, Seafood\"\nDinner: The Great Indian Pub, Fayetteville, Cost: $95, Cuisines: \"Fast Food, Tea, Seafood\"\nAccommodation: *CoZy Private Williamsburg Home*, Fayetteville, Cost: $546, Entire home/apt, House Rules: No children under 10 & No smoking & No visitors, Minimum Nights: 2, Maximum Occupancy: 5\n\nNumber of People = 2\nTotal Cost = 2 * $87 + 2 * $56 + 2 * $95 + $546 = $1116 (Accommodation cost already included in Day 1)\n\nDay 3: March 22, 2022\nCurrent City: from Fayetteville to Houston\nTransportation: Flight Number: F3922249, from Fayetteville to Houston, Departure Time: 19:18, Arrival Time: 20:52, Cost: $193 per person\nBreakfast: Fresh n Refresh, Fayetteville, Cost: $33, Cuisines: \"Fast Food, Cafe, BBQ, Italian\"\nAttraction: Airborne & Special Operations Museum Foundation, Fayetteville (Open during business hours)\nLunch: Fa Yian, Fayetteville, Cost: $63, Cuisines: \"Desserts, Tea, Cafe, Chinese, Indian\"\nDinner: - (Assuming dinner is had after arrival in Houston or during the flight)\nAccommodation: -\n\nNumber of People = 2\nTotal Cost = 2 * $193 + 2 * $33 + 2 * $63 = $582\n\nTotal cost across all days = $1082 + $1116 + $582 = $2780\n\nHowever, the total cost exceeds the specified budget of $1,500. To adjust the plan within the budget, we need to make the following changes:\n\n- Change the accommodation to a more affordable option that allows children under 10.\n- Opt for less expensive meal options while still adhering to the specified cuisines.\n\nRevised Travel Plan:\n\nDay 1: March 20, 2022\nAccommodation: Private BRoom, Bathroom & backyard, Fayetteville, Cost: $56, Private room, House Rules: No parties & No children under 10 & No pets, Minimum Nights: 4, Maximum Occupancy: 2\n\nDay 2: March 21, 2022\nAccommodation: Private BRoom, Bathroom & backyard, Fayetteville, Cost: $56, Private room, House Rules: No parties & No children under 10 & No pets, Minimum Nights: 4, Maximum Occupancy: 2\n\nRevised Total Cost for Accommodation: 2 * $56 * 2 nights = $224\n\nRevised Total Cost for Meals and Attractions: Assuming a reduction of 50% in meal costs and selecting free attractions.\n\nRevised Total Cost for Transportation: No change, as non-self-driving transportation was requested.\n\nRevised Total Cost Across All Days: $1082 (Day 1) + $224 (Accommodation for Day 1 and Day 2) + $582 (Day 3) = $1888\n\nThe revised total cost is still above the budget. Further adjustments are needed, such as selecting a cheaper flight or reducing meal costs further. However, without additional options provided in the reference information, it is not possible to create a plan that meets all the requirements within the specified budget of $1,500.", "gpt-4-1106-preview_direct_sole-planning_parsed_results": [{"day": 1, "current_city": "from Houston to Fayetteville", "transportation": "Flight Number: F3923439, from Houston to Fayetteville, Departure Time: 09:29, Arrival Time: 11:04", "breakfast": "-", "attraction": "The Fayetteville Area Transportation and Local History Museum, Fayetteville", "lunch": "Biryani By Kilo, Fayetteville", "dinner": "Eat Street, Fayetteville", "accommodation": "*CoZy Private Williamsburg Home*, Fayetteville"}, {"day": 2, "current_city": "Fayetteville", "transportation": "-", "breakfast": "Kay's Food Land, Fayetteville", "attraction": "Cape Fear Botanical Garden, Fayetteville", "lunch": "Oriental Fusion, Fayetteville", "dinner": "The Great Indian Pub, Fayetteville", "accommodation": "*CoZy Private Williamsburg Home*, Fayetteville"}, {"day": 3, "current_city": "from Fayetteville to Houston", "transportation": "Flight Number: F3922249, from Fayetteville to Houston, Departure Time: 19:18, Arrival Time: 20:52", "breakfast": "Fresh n Refresh, Fayetteville", "attraction": "Airborne & Special Operations Museum Foundation, Fayetteville", "lunch": "Fa Yian, Fayetteville", "dinner": "-", "accommodation": "-"}]}]