[{"gpt-4-1106-preview_direct_sole-planning_results": "Travel Plan:\n\nDay 1: March 1, 2022\nCurrent City: from Oklahoma City to Alamosa\nTransportation: Self-driving, from Oklahoma City to Alamosa, Duration: 8 hours 53 mins, Distance: 922 km, Cost: $46\nBreakfast: -\nLunch: -\nDinner: Atlanta Highway Seafood Market, Alamosa, Cost: $68, Cuisines: \"Fast Food, Desserts, Seafood\"\nAccommodation: Comfortable studio suite in midtown Manhattan, Alamosa, Cost: $67, Maximum Occupancy: 2, House Rules: No parties & No smoking & No visitors, Minimum Nights: 30\n\nTotal Cost for Day 1: $46 (Transportation) + $68 (Dinner) + $67 (Accommodation) = $181\n\nDay 2: March 2, 2022\nCurrent City: Alamosa\nTransportation: -\nBreakfast: Coffee to Cocktail Bar - Hyatt Place, Alamosa, Cost: $35, Cuisines: \"Tea, Indian, Desserts, Italian\"\nAttraction: San Luis Valley Museum, Alamosa\nLunch: Riverwalk Cafe, Alamosa, Cost: $97, Cuisines: \"Tea, Pizza, Fast Food\"\nDinner: Cafe LazyMojo, Alamosa, Cost: $26, Cuisines: \"Tea, Pizza, American, Fast Food\"\nAccommodation: Comfortable studio suite in midtown Manhattan, Alamosa, Cost: $67, Maximum Occupancy: 2, House Rules: No parties & No smoking & No visitors, Minimum Nights: 30\n\nTotal Cost for Day 2: $35 (Breakfast) + $97 (Lunch) + $26 (Dinner) + $67 (Accommodation) = $225\n\nDay 3: March 3, 2022\nCurrent City: from Alamosa to Grand Junction\nTransportation: Self-driving, from Alamosa to Grand Junction, Duration: 4 hours 29 mins, Distance: 396 km, Cost: $19\nBreakfast: -\nLunch: The Arena, Grand Junction, Cost: $85, Cuisines: \"Tea, French, Desserts\"\nDinner: 2 Dog, Grand Junction, Cost: $29, Cuisines: \"Desserts, BBQ, Fast Food, Cafe, American\"\nAccommodation: NYC Apartment near Central Park!, Grand Junction, Cost: $1118, Maximum Occupancy: 5, House Rules: No children under 10, Minimum Nights: 3\n\nTotal Cost for Day 3: $19 (Transportation) + $85 (Lunch) + $29 (Dinner) + $1118 (Accommodation) = $1251\n\nDay 4: March 4, 2022\nCurrent City: Grand Junction\nTransportation: -\nBreakfast: Austin's BBQ and Oyster Bar, Grand Junction, Cost: $15, Cuisines: \"Tea, Bakery, Fast Food, Indian, Seafood\"\nAttraction: Museum of the West, Museums of Western Colorado, Grand Junction\nLunch: Shanghai Bar & Lounge - The Bristol Hotel, Grand Junction, Cost: $31, Cuisines: \"Cafe, Pizza\"\nDinner: Punjab Da Pind, Grand Junction, Cost: $52, Cuisines: \"Desserts, Pizza, Bakery, Chinese, Mediterranean, Seafood\"\nAccommodation: NYC Apartment near Central Park!, Grand Junction, Cost: $1118, Maximum Occupancy: 5, House Rules: No children under 10, Minimum Nights: 3\n\nTotal Cost for Day 4: $15 (Breakfast) + $31 (Lunch) + $52 (Dinner) + $1118 (Accommodation) = $1216\n\nDay 5: March 5, 2022\nCurrent City: from Grand Junction to Durango\nTransportation: Self-driving, from Grand Junction to Durango, Duration: 3 hours 33 mins, Distance: 269 km, Cost: $13\nBreakfast: -\nLunch: Samurai Japanese Cuisine & Sushi Bar, Durango, Cost: $67, Cuisines: \"Bakery, Desserts, Fast Food\"\nDinner: Dub's High on the Hog, Durango, Cost: $98, Cuisines: \"Tea, Italian, French, Cafe, Seafood\"\nAccommodation: Lux 1BR in the heart of NYC Theater district!, Durango, Cost: $81, Maximum Occupancy: 3, House Rules: No children under 10, Minimum Nights: 30\n\nTotal Cost for Day 5: $13 (Transportation) + $67 (Lunch) + $98 (Dinner) + $81 (Accommodation) = $259\n\nDay 6: March 6, 2022\nCurrent City: Durango\nTransportation: -\nBreakfast: Chickenette, Durango, Cost: $31, Cuisines: \"Tea, Pizza, Desserts, Fast Food\"\nAttraction: Animas Museum, Durango\nLunch: King Bikaneri, Durango, Cost: $87, Cuisines: \"Seafood, Indian, BBQ, Fast Food\"\nDinner: The Mashal, Durango, Cost: $85, Cuisines: \"Italian, BBQ, Fast Food, Cafe, American, Seafood\"\nAccommodation: Lux 1BR in the heart of NYC Theater district!, Durango, Cost: $81, Maximum Occupancy: 3, House Rules: No children under 10, Minimum Nights: 30\n\nTotal Cost for Day 6: $31 (Breakfast) + $87 (Lunch) + $85 (Dinner) + $81 (Accommodation) = $284\n\nDay 7: March 7, 2022\nCurrent City: from Durango to Oklahoma City\nTransportation: Self-driving, from Durango to Oklahoma City, Duration: 11 hours 13 mins, Distance: 1,212 km, Cost: $60\nBreakfast: -\nLunch: -\nDinner: -\nAccommodation: -\n\nTotal Cost for Day 7: $60 (Transportation) = $60\n\nTotal cost across all days: $181 (Day 1) + $225 (Day 2) + $1251 (Day 3) + $1216 (Day 4) + $259 (Day 5) + $284 (Day 6) + $60 (Day 7) = $3466\n\nNote: The total cost exceeds the budget of $3,000. To stay within budget, consider adjusting accommodation choices or dining options. The accommodation on Day 3 and Day 4 is particularly expensive and could be replaced with more affordable options. Additionally, the plan does not include breakfast on some days, and some attractions may have entry fees not accounted for in this plan.", "gpt-4-1106-preview_direct_sole-planning_parsed_results": [{"day": 1, "current_city": "from Oklahoma City to Alamosa", "transportation": "Self-driving, from Oklahoma City to Alamosa, Duration: 8 hours 53 mins, Distance: 922 km", "breakfast": "-", "attraction": "-", "lunch": "-", "dinner": "Atlanta Highway Seafood Market, Alamosa", "accommodation": "Comfortable studio suite in midtown Manhattan, Alamosa"}, {"day": 2, "current_city": "Alamosa", "transportation": "-", "breakfast": "Coffee to Cocktail Bar - Hyatt Place, Alamosa", "attraction": "San Luis Valley Museum, Alamosa", "lunch": "Riverwalk Cafe, Alamosa", "dinner": "Cafe LazyMojo, Alamosa", "accommodation": "Comfortable studio suite in midtown Manhattan, Alamosa"}, {"day": 3, "current_city": "from Alamosa to Grand Junction", "transportation": "Self-driving, from Alamosa to Grand Junction, Duration: 4 hours 29 mins, Distance: 396 km", "breakfast": "-", "attraction": "-", "lunch": "The Arena, Grand Junction", "dinner": "2 Dog, Grand Junction", "accommodation": "NYC Apartment near Central Park!, Grand Junction"}, {"day": 4, "current_city": "Grand Junction", "transportation": "-", "breakfast": "Austin's BBQ and Oyster Bar, Grand Junction", "attraction": "Museum of the West, Museums of Western Colorado, Grand Junction", "lunch": "Shanghai Bar & Lounge - The Bristol Hotel, Grand Junction", "dinner": "Punjab Da Pind, Grand Junction", "accommodation": "NYC Apartment near Central Park!, Grand Junction"}, {"day": 5, "current_city": "from Grand Junction to Durango", "transportation": "Self-driving, from Grand Junction to Durango, Duration: 3 hours 33 mins, Distance: 269 km", "breakfast": "-", "attraction": "-", "lunch": "Samurai Japanese Cuisine & Sushi Bar, Durango", "dinner": "Dub's High on the Hog, Durango", "accommodation": "Lux 1BR in the heart of NYC Theater district!, Durango"}, {"day": 6, "current_city": "Durango", "transportation": "-", "breakfast": "Chickenette, Durango", "attraction": "Animas Museum, Durango", "lunch": "King Bikaneri, Durango", "dinner": "The Mashal, Durango", "accommodation": "Lux 1BR in the heart of NYC Theater district!, Durango"}, {"day": 7, "current_city": "from Durango to Oklahoma City", "transportation": "Self-driving, from Durango to Oklahoma City, Duration: 11 hours 13 mins, Distance: 1,212 km", "breakfast": "-", "attraction": "-", "lunch": "-", "dinner": "-", "accommodation": "-"}]}]