[{"gpt-4-1106-preview_direct_sole-planning_results": "Travel Plan:\n\nDay 1: March 15, 2022\nCurrent City: from Washington to Orlando\nTransportation: Flight Number: F3722587, from Washington to Orlando, Departure Time: 08:27, Arrival Time: 10:58, Cost: $190 per person\nBreakfast: - (Assuming breakfast in Washington or on the flight)\nAttraction: The Wheel at ICON Park, Orlando\nLunch: Fuji Japanese Steakhouse, Orlando, Cost: $75, Cuisines: \"Tea, Bakery, Desserts\"\nDinner: Turquoise Villa, Orlando, Cost: $55, Cuisines: \"French, Bakery, BBQ, Fast Food\"\nAccommodation: Sixth Ave Chelsea, Studio Serviced Apartment, Orlando, Cost: $70, Room Type: Entire home/apt, House Rules: No visitors & No pets, Minimum Nights: 1, Maximum Occupancy: 3\n\nNumber of People = 2\nTotal Cost = 2 * $190 + 2 * $75 + 2 * $55 + $70 = $730\nAccommodation Minimum Nights: 1/1\n\nDay 2: March 16, 2022\nCurrent City: Orlando\nTransportation: -\nBreakfast: Wai Yu Mun Ching, Orlando, Cost: $51, Cuisines: \"Tea, Pizza, Desserts\"\nAttraction: Universal Orlando Resort, Orlando\nLunch: Indochi Cafe & Restaurant, Orlando, Cost: $72, Cuisines: \"Pizza, French, Bakery, Fast Food, Indian, Seafood\"\nDinner: Always Eat Green, Orlando, Cost: $98, Cuisines: \"Tea, Italian, Fast Food, Cafe, Seafood\"\nAccommodation: Sixth Ave Chelsea, Studio Serviced Apartment, Orlando, Cost: $70, Room Type: Entire home/apt, House Rules: No visitors & No pets, Minimum Nights: 1, Maximum Occupancy: 3\n\nNumber of People = 2\nTotal Cost = 2 * $51 + 2 * $72 + 2 * $98 + $70 = $512\nAccommodation Minimum Nights: 2/1\n\nDay 3: March 17, 2022\nCurrent City: from Orlando to Washington\nTransportation: Flight Number: F3725294, from Orlando to Washington, Departure Time: 15:11, Arrival Time: 17:17, Cost: $155 per person\nBreakfast: Ambrosia - The Golden Palms Hotel, Orlando, Cost: $52, Cuisines: \"Tea, Mexican, Desserts\"\nAttraction: Harry P Leu Gardens, Orlando\nLunch: The Tandoori Times, Orlando, Cost: $84, Cuisines: \"Tea, Cafe, BBQ, Italian\"\nDinner: - (Assuming dinner in Washington or on the flight)\nAccommodation: -\n\nNumber of People = 2\nTotal Cost = 2 * $155 + 2 * $52 + 2 * $84 = $582\nAccommodation Minimum Nights: -\n\nTotal cost across all days = $730 + $512 + $582 = $1824\nCuisines: The prompt specifies no cuisines, so all cuisines constraints are satisfied.\n\nNote: The provided information does not include specific opening hours for attractions or specific meal times at restaurants, so it is assumed that the attractions and restaurants are available during the travelers' visit times. Breakfast on Day 1 and dinner on Day 3 are not included in the plan due to the assumption that they will be had outside of Orlando or on the flight. The accommodation on Day 2 is the same as Day 1, meeting the minimum nights requirement. The total cost is within the specified budget of $2,000.", "gpt-4-1106-preview_direct_sole-planning_parsed_results": [{"day": 1, "current_city": "from Washington to Orlando", "transportation": "Flight Number: F3722587, from Washington to Orlando, Departure Time: 08:27, Arrival Time: 10:58", "breakfast": "-", "attraction": "The Wheel at ICON Park, Orlando;", "lunch": "Fuji Japanese Steakhouse, Orlando", "dinner": "Turquoise Villa, Orlando", "accommodation": "Sixth Ave Chelsea, Studio Serviced Apartment, Orlando"}, {"day": 2, "current_city": "Orlando", "transportation": "-", "breakfast": "Wai Yu Mun Ching, Orlando", "attraction": "Universal Orlando Resort, Orlando;", "lunch": "Indochi Cafe & Restaurant, Orlando", "dinner": "Always Eat Green, Orlando", "accommodation": "Sixth Ave Chelsea, Studio Serviced Apartment, Orlando"}, {"day": 3, "current_city": "from Orlando to Washington", "transportation": "Flight Number: F3725294, from Orlando to Washington, Departure Time: 15:11, Arrival Time: 17:17", "breakfast": "Ambrosia - The Golden Palms Hotel, Orlando", "attraction": "Harry P Leu Gardens, Orlando;", "lunch": "The Tandoori Times, Orlando", "dinner": "-", "accommodation": "-"}]}]