[{"gpt-4-1106-preview_direct_sole-planning_results": "Travel Plan:\n\nDay 1: March 21, 2022\nCurrent City: from Bangor to Washington\nTransportation: Flight Number: F3787709, from Bangor to Washington, Departure Time: 05:38, Arrival Time: 07:22, Cost: 223\nBreakfast: - (Assuming breakfast is had before the flight or on board)\nAttraction: The Seattle Great Wheel, Washington\nLunch: Los Aztecas, Washington, Cost: 46, Cuisines: \"Cafe, Bakery, BBQ, Fast Food\"\nDinner: Manna Java World Cafe, Washington, Cost: 59, Cuisines: \"Cafe, Seafood\"\nAccommodation: Stunning 2Bed/2BA + 300sqft deck by the river!, Washington, Cost: 209, Maximum Occupancy: 3, House Rules: No visitors, Minimum Nights: 1\n\nNumber of People = 3\nTotal Cost = 3 * 223 + 3 * 46 + 3 * 59 + 209 = 1195\n\nDay 2: March 22, 2022\nCurrent City: Washington\nTransportation: -\nBreakfast: Thaaliwala, Washington, Cost: 88, Cuisines: \"Tea, Pizza, Italian, BBQ, Cafe\"\nAttraction: Space Needle, Washington\nLunch: Good Foods, Washington, Cost: 65, Cuisines: \"BBQ, Desserts, Seafood\"\nDinner: Shiv Dhaba, Washington, Cost: 61, Cuisines: \"Bakery, American, Cafe, Seafood\"\nAccommodation: Stunning 2Bed/2BA + 300sqft deck by the river!, Washington, Cost: 209, Maximum Occupancy: 3, House Rules: No visitors, Minimum Nights: 1\n\nNumber of People = 3\nTotal Cost = 3 * 88 + 3 * 65 + 3 * 61 + 209 = 1015\n\nDay 3: March 23, 2022\nCurrent City: from Washington to Bangor\nTransportation: Flight Number: F3797033, from Washington to Bangor, Departure Time: 21:54, Arrival Time: 23:30, Cost: 131\nBreakfast: Republic of Chicken, Washington, Cost: 91, Cuisines: \"Tea, Bakery, American, Desserts\"\nAttraction: Olympic National Park, Washington\nLunch: Amaze Dining, Washington, Cost: 92, Cuisines: \"Cafe, Pizza, American, Fast Food\"\nDinner: - (Assuming dinner will be had after arrival in Bangor or on the way)\nAccommodation: -\n\nNumber of People = 3\nTotal Cost = 3 * 131 + 3 * 91 + 3 * 92 = 924\n\nTotal cost across all days = 1195 + 1015 + 924 = 3134\n\nNote: The total cost slightly exceeds the budget by $34. To stay within the budget, consider adjusting meal choices or seeking a promotional discount on one of the flights or meals.\n\nCuisines: The prompt specifies no cuisines, so all cuisines constraints are satisfied.\n\nAccommodations: The chosen accommodation is pet-friendly and offers entire rooms, adhering to the specified constraints.\n\nTransportation: Flights are used for transportation between cities, as self-driving is not preferred for this trip.", "gpt-4-1106-preview_direct_sole-planning_parsed_results": [{"day": 1, "current_city": "from Bangor to Washington", "transportation": "Flight Number: F3787709, from Bangor to Washington, Departure Time: 05:38, Arrival Time: 07:22", "breakfast": "-", "attraction": "The Seattle Great Wheel, Washington;", "lunch": "Los Aztecas, Washington", "dinner": "Manna Java World Cafe, Washington", "accommodation": "Stunning 2Bed/2BA + 300sqft deck by the river!, Washington"}, {"day": 2, "current_city": "Washington", "transportation": "-", "breakfast": "Thaaliwala, Washington", "attraction": "Space Needle, Washington;", "lunch": "Good Foods, Washington", "dinner": "Shiv Dhaba, Washington", "accommodation": "Stunning 2Bed/2BA + 300sqft deck by the river!, Washington"}, {"day": 3, "current_city": "from Washington to Bangor", "transportation": "Flight Number: F3797033, from Washington to Bangor, Departure Time: 21:54, Arrival Time: 23:30", "breakfast": "Republic of Chicken, Washington", "attraction": "Olympic National Park, Washington;", "lunch": "Amaze Dining, Washington", "dinner": "-", "accommodation": "-"}]}]