[{"gpt-4-1106-preview_direct_sole-planning_results": "Travel Plan:\n\nDay 1: March 17, 2022\nCurrent City: from Minneapolis to Toledo\nTransportation: Self-driving, from Minneapolis to Toledo, Duration: 9 hours 43 mins, Distance: 1,057 km, Cost: $52\nBreakfast: -\nLunch: -\nDinner: Devotay, Toledo, Cost: $78, Cuisines: \"Chinese, BBQ, Seafood\"\nAccommodation: Sunny Modern Lux Private House with Parking, Toledo, Cost: $614, Maximum Occupancy: 6, House Rules: No smoking & No children under 10 & No parties, Pet-Friendly: Yes\n\nNumber of People = 2\nTotal Cost = 2 * 52 + 2 * 78 + 614 = $874\n\nDay 2: March 18, 2022\nCurrent City: Toledo\nTransportation: -\nBreakfast: Bombay Brasserie, Toledo, Cost: $32, Cuisines: \"Tea, Pizza, Mediterranean\"\nAttraction: Toledo Zoo, Toledo\nLunch: The Punjabi Essence Restaurant, Toledo, Cost: $72, Cuisines: \"Desserts, Tea, Mexican, Chinese, Seafood\"\nDinner: The Chocolate Room, Toledo, Cost: $95, Cuisines: \"Chinese, Mexican, Pizza, BBQ\"\nAccommodation: Sunny Modern Lux Private House with Parking, Toledo, Cost: $614, Maximum Occupancy: 6, House Rules: No smoking & No children under 10 & No parties, Pet-Friendly: Yes\n\nNumber of People = 2\nTotal Cost = 2 * 32 + 2 * 72 + 2 * 95 + 614 = $1012\n\nDay 3: March 19, 2022\nCurrent City: from Toledo to Cleveland\nTransportation: Self-driving, from Toledo to Cleveland, Duration: 1 hour 50 mins, Distance: 183 km, Cost: $9\nBreakfast: Spice Wok, Toledo, Cost: $24, Cuisines: \"Tea, Pizza, Italian, French, BBQ\"\nAttraction: National Museum of the Great Lakes, Toledo\nLunch: Barbeque Nation, Toledo, Cost: $78, Cuisines: \"Desserts, Tea, Bakery, American, Mediterranean\"\nDinner: Bikanerwala, Cleveland, Cost: $10, Cuisines: \"Tea, Bakery, BBQ, Fast Food\"\nAccommodation: Richmond Hill 3 Bedroom apartment in Private home!, Cleveland, Cost: $565, Maximum Occupancy: 4, House Rules: No visitors, Pet-Friendly: Yes\n\nNumber of People = 2\nTotal Cost = 2 * 9 + 2 * 24 + 2 * 78 + 2 * 10 + 565 = $807\n\nDay 4: March 20, 2022\nCurrent City: Cleveland\nTransportation: -\nBreakfast: Makhan Fish and Chicken Corner, Cleveland, Cost: $25, Cuisines: \"Pizza, French, Fast Food, Chinese, Seafood\"\nAttraction: Cleveland Metroparks Zoo, Cleveland\nLunch: Pind Balluchi, Cleveland, Cost: $96, Cuisines: \"Chinese, Pizza, French, BBQ, Cafe\"\nDinner: Me Kong Bowl, Cleveland, Cost: $19, Cuisines: \"Cafe, BBQ, Seafood\"\nAccommodation: Richmond Hill 3 Bedroom apartment in Private home!, Cleveland, Cost: $565, Maximum Occupancy: 4, House Rules: No visitors, Pet-Friendly: Yes\n\nNumber of People = 2\nTotal Cost = 2 * 25 + 2 * 96 + 2 * 19 + 565 = $845\n\nDay 5: March 21, 2022\nCurrent City: from Cleveland to Dayton\nTransportation: Self-driving, from Cleveland to Dayton, Duration: 3 hours 11 mins, Distance: 340 km, Cost: $17\nBreakfast: Green Leaf, Cleveland, Cost: $73, Cuisines: \"Desserts, Tea, Cafe, BBQ, Chinese\"\nAttraction: Rock & Roll Hall of Fame, Cleveland\nLunch: Big Chicken, Cleveland, Cost: $27, Cuisines: \"Cafe, Pizza, Bakery, Italian\"\nDinner: Star Noodle, Dayton, Cost: $17, Cuisines: \"Desserts, Bakery, BBQ, Fast Food, Chinese, American\"\nAccommodation: Studio apartment; close to tourist attractions, Dayton, Cost: $769, Maximum Occupancy: 6, House Rules: No visitors & No smoking, Pet-Friendly: Yes\n\nNumber of People = 2\nTotal Cost = 2 * 17 + 2 * 73 + 2 * 27 + 2 * 17 + 769 = $1020\n\nDay 6: March 22, 2022\nCurrent City: Dayton\nTransportation: -\nBreakfast: Onesta, Dayton, Cost: $47, Cuisines: \"Italian, BBQ, Fast Food, Cafe, American, Seafood\"\nAttraction: Carillon Historical Park, Dayton\nLunch: Pizza Express, Dayton, Cost: $92, Cuisines: \"Cafe, Pizza, American, Seafood\"\nDinner: Cookingo, Dayton, Cost: $78, Cuisines: \"Fast Food, French, BBQ, Seafood\"\nAccommodation: Studio apartment; close to tourist attractions, Dayton, Cost: $769, Maximum Occupancy: 6, House Rules: No visitors & No smoking, Pet-Friendly: Yes\n\nNumber of People = 2\nTotal Cost = 2 * 47 + 2 * 92 + 2 * 78 + 769 = $1203\n\nDay 7: March 23, 2022\nCurrent City: from Dayton to Minneapolis\nTransportation: Self-driving, from Dayton to Minneapolis, Duration: 10 hours 31 mins, Distance: 1,138 km, Cost: $56\nBreakfast: Subway, Dayton, Cost: $11, Cuisines: \"BBQ, Desserts, Seafood\"\nLunch: -\nDinner: -\nAccommodation: -\n\nNumber of People = 2\nTotal Cost = 2 * 56 + 2 * 11 = $134\n\nTotal cost across all days = $874 + $1012 + $807 + $845 + $1020 + $1203 + $134 = $5895\n\nNote: The total cost exceeds the budget of $5,100. To adjust, consider changing accommodations to more affordable options, reducing meal costs, or altering the itinerary to visit fewer attractions. Additionally, the cost of gasoline for self-driving has not been included and should be factored into the budget.", "gpt-4-1106-preview_direct_sole-planning_parsed_results": [{"day": 1, "current_city": "from Minneapolis to Toledo", "transportation": "Self-driving, from Minneapolis to Toledo, Duration: 9 hours 43 mins, Distance: 1,057 km", "breakfast": "-", "attraction": "-", "lunch": "-", "dinner": "Devotay, Toledo", "accommodation": "Sunny Modern Lux Private House with Parking, Toledo"}, {"day": 2, "current_city": "Toledo", "transportation": "-", "breakfast": "Bombay Brasserie, Toledo", "attraction": "Toledo Zoo, Toledo", "lunch": "The Punjabi Essence Restaurant, Toledo", "dinner": "The Chocolate Room, Toledo", "accommodation": "Sunny Modern Lux Private House with Parking, Toledo"}, {"day": 3, "current_city": "from Toledo to Cleveland", "transportation": "Self-driving, from Toledo to Cleveland, Duration: 1 hour 50 mins, Distance: 183 km", "breakfast": "Spice Wok, Toledo", "attraction": "National Museum of the Great Lakes, Toledo", "lunch": "Barbeque Nation, Toledo", "dinner": "Bikanerwala, Cleveland", "accommodation": "Richmond Hill 3 Bedroom apartment in Private home!, Cleveland"}, {"day": 4, "current_city": "Cleveland", "transportation": "-", "breakfast": "Makhan Fish and Chicken Corner, Cleveland", "attraction": "Cleveland Metroparks Zoo, Cleveland", "lunch": "Pind Balluchi, Cleveland", "dinner": "Me Kong Bowl, Cleveland", "accommodation": "Richmond Hill 3 Bedroom apartment in Private home!, Cleveland"}, {"day": 5, "current_city": "from Cleveland to Dayton", "transportation": "Self-driving, from Cleveland to Dayton, Duration: 3 hours 11 mins, Distance: 340 km", "breakfast": "Green Leaf, Cleveland", "attraction": "Rock & Roll Hall of Fame, Cleveland", "lunch": "Big Chicken, Cleveland", "dinner": "Star Noodle, Dayton", "accommodation": "Studio apartment; close to tourist attractions, Dayton"}, {"day": 6, "current_city": "Dayton", "transportation": "-", "breakfast": "Onesta, Dayton", "attraction": "Carillon Historical Park, Dayton", "lunch": "Pizza Express, Dayton", "dinner": "Cookingo, Dayton", "accommodation": "Studio apartment; close to tourist attractions, Dayton"}, {"day": 7, "current_city": "from Dayton to Minneapolis", "transportation": "Self-driving, from Dayton to Minneapolis, Duration: 10 hours 31 mins, Distance: 1,138 km", "breakfast": "Subway, Dayton", "attraction": "-", "lunch": "-", "dinner": "-", "accommodation": "-"}]}]