[{"gpt-4-1106-preview_direct_sole-planning_results": "Travel Plan:\n\nDay 1: March 3, 2022\nCurrent City: from Atlanta to Bemidji\nTransportation: Taxi, from Atlanta to Bemidji, duration: 19 hours 53 mins, distance: 2,166 km, cost: $2,166\nBreakfast: - (Assuming breakfast in Atlanta before departure)\nAttraction: Paul Bunyan & Babe the Blue Ox Statues, Bemidji\nLunch: Pig and Whistle, Bemidji, Cost: $39, Cuisines: \"Fast Food, Mexican, Bakery, Seafood\"\nDinner: The Chocolate Haven, Bemidji, Cost: $23, Cuisines: \"Desserts, Tea, Italian, BBQ, Fast Food, Chinese\"\nAccommodation: Warm Artistic Wburg Loft Off 4 Train Lines, Bemidji, Cost: $831, Entire home/apt, House Rules: No pets, Minimum Nights: 5, Maximum Occupancy: 2\n\nNumber of People = 3\nTotal Cost = $2,166 + 3 * $39 + 3 * $23 + 3 * $831 / 2 = $3,785\nAccommodation Minimum Nights: 1/5\n\nDay 2: March 4, 2022\nCurrent City: Bemidji\nTransportation: -\nBreakfast: Flying Cakes, Bemidji, Cost: $43, Cuisines: \"Tea, Seafood\"\nAttraction: Headwaters Science Center, Bemidji\nLunch: Outback Bar and Grill - Leisure Inn, Bemidji, Cost: $59, Cuisines: \"Indian, Desserts, Fast Food\"\nDinner: Gastronomica Kitchen & Bar, Bemidji, Cost: $84, Cuisines: \"Chinese, BBQ, Cafe, Desserts\"\nAccommodation: Warm Artistic Wburg Loft Off 4 Train Lines, Bemidji, Cost: $831, Entire home/apt, House Rules: No pets, Minimum Nights: 5, Maximum Occupancy: 2\n\nNumber of People = 3\nTotal Cost = 3 * $43 + 3 * $59 + 3 * $84 + 3 * $831 / 2 = $2,031\nAccommodation Minimum Nights: 2/5\n\nDay 3: March 5, 2022\nCurrent City: from Bemidji to Minneapolis\nTransportation: Flight Number: F3849472, from Bemidji to Minneapolis, Departure Time: 08:21, Arrival Time: 09:23, Cost: $86\nBreakfast: - (Assuming breakfast in Bemidji before departure)\nAttraction: Minneapolis Sculpture Garden, Minneapolis\nLunch: The Cafe, Minneapolis, Cost: $14, Cuisines: \"Indian, Mediterranean, Desserts, Seafood\"\nDinner: Court Avenue Brewing Company, Minneapolis, Cost: $31, Cuisines: \"Pizza, French, Bakery, BBQ, Seafood\"\nAccommodation: Light-filled Apartment in great area, close 2 all!, Minneapolis, Cost: $343, Entire home/apt, House Rules: No visitors, Minimum Nights: 1, Maximum Occupancy: 2\n\nNumber of People = 3\nTotal Cost = 3 * $86 + 3 * $14 + 3 * $31 + 3 * $343 / 2 = $1,158\nAccommodation Minimum Nights: 1/1\n\nDay 4: March 6, 2022\nCurrent City: Minneapolis\nTransportation: -\nBreakfast: Texas Roadhouse, Minneapolis, Cost: $22, Cuisines: \"Cafe, Pizza, BBQ, Desserts\"\nAttraction: Minneapolis Institute of Art, Minneapolis\nLunch: Monkeypod Kitchen by Merriman, Minneapolis, Cost: $50, Cuisines: \"Desserts, Pizza, Bakery, Fast Food, Indian, Mediterranean\"\nDinner: Balbeer's Kitchen & Bar, Minneapolis, Cost: $81, Cuisines: \"Tea, Chinese, Bakery\"\nAccommodation: Light-filled Apartment in great area, close 2 all!, Minneapolis, Cost: $343, Entire home/apt, House Rules: No visitors, Minimum Nights: 1, Maximum Occupancy: 2\n\nNumber of People = 3\nTotal Cost = 3 * $22 + 3 * $50 + 3 * $81 + 3 * $343 / 2 = $1,098\nAccommodation Minimum Nights: 2/1\n\nDay 5: March 7, 2022\nCurrent City: from Minneapolis to Atlanta\nTransportation: Flight Number: F3781929, from Minneapolis to Atlanta, Departure Time: 05:32, Arrival Time: 08:59, Cost: $191\nBreakfast: - (Assuming breakfast in Minneapolis before departure)\nAttraction: - (Assuming no time for attractions due to early flight)\nLunch: - (Assuming lunch in Atlanta after arrival)\nDinner: - (Assuming dinner in Atlanta after arrival)\nAccommodation: -\n\nNumber of People = 3\nTotal Cost = 3 * $191 = $573\n\nTotal cost across all days = $3,785 + $2,031 + $1,158 + $1,098 + $573 = $8,645\n\nUnfortunately, the total cost exceeds the specified budget of $7,900. To adjust the plan within the budget, we may need to consider alternative transportation or accommodation options. For example, we could opt for a taxi instead of a flight from Bemidji to Minneapolis, which would reduce the cost by $204 in total. Additionally, we could choose a less expensive accommodation option in Minneapolis to stay within budget.", "gpt-4-1106-preview_direct_sole-planning_parsed_results": [{"day": 1, "current_city": "from Atlanta to Bemidji", "transportation": "Taxi, from Atlanta to Bemidji, duration: 19 hours 53 mins, distance: 2,166 km", "breakfast": "-", "attraction": "Paul Bunyan & Babe the Blue Ox Statues, Bemidji;", "lunch": "Pig and Whistle, Bemidji", "dinner": "The Chocolate Haven, Bemidji", "accommodation": "Warm Artistic Wburg Loft Off 4 Train Lines, Bemidji"}, {"day": 2, "current_city": "Bemidji", "transportation": "-", "breakfast": "Flying Cakes, Bemidji", "attraction": "Headwaters Science Center, Bemidji;", "lunch": "Outback Bar and Grill - Leisure Inn, Bemidji", "dinner": "Gastronomica Kitchen & Bar, Bemidji", "accommodation": "Warm Artistic Wburg Loft Off 4 Train Lines, Bemidji"}, {"day": 3, "current_city": "from Bemidji to Minneapolis", "transportation": "Flight Number: F3849472, from Bemidji to Minneapolis, Departure Time: 08:21, Arrival Time: 09:23", "breakfast": "-", "attraction": "Minneapolis Sculpture Garden, Minneapolis;", "lunch": "The Cafe, Minneapolis", "dinner": "Court Avenue Brewing Company, Minneapolis", "accommodation": "Light-filled Apartment in great area, close 2 all!, Minneapolis"}, {"day": 4, "current_city": "Minneapolis", "transportation": "-", "breakfast": "Texas Roadhouse, Minneapolis", "attraction": "Minneapolis Institute of Art, Minneapolis;", "lunch": "Monkeypod Kitchen by Merriman, Minneapolis", "dinner": "Balbeer's Kitchen & Bar, Minneapolis", "accommodation": "Light-filled Apartment in great area, close 2 all!, Minneapolis"}, {"day": 5, "current_city": "from Minneapolis to Atlanta", "transportation": "Flight Number: F3781929, from Minneapolis to Atlanta, Departure Time: 05:32, Arrival Time: 08:59", "breakfast": "-", "attraction": "-", "lunch": "-", "dinner": "-", "accommodation": "-"}]}]