[{"gpt-4-1106-preview_direct_sole-planning_results": "Travel Plan:\n\nDay 1: March 7th, 2022\nCurrent City: from Atlanta to Chattanooga\nTransportation: Flight Number: F3540824, from Atlanta to Chattanooga, Departure Time: 10:20, Arrival Time: 11:05, Cost: 30\nBreakfast: - (Assuming breakfast is had before departure or during the flight)\nAttraction: Tennessee Aquarium, Chattanooga\nLunch: L'amandier, Chattanooga, Cost: 28, Cuisines: \"Cafe, BBQ, Mediterranean, Seafood\"\nDinner: P.F. Chang's, Chattanooga, Cost: 33, Cuisines: \"Cafe, Bakery, BBQ, Seafood\"\nAccommodation: Sunny One Bedroom, Chattanooga, Cost: 722, Maximum Occupancy: 5, House Rules: No pets & No children under 10, Minimum Nights: 1\n\nNumber of People = 5\nTotal Cost = 5 * 30 (Flight) + 5 * 28 (Lunch) + 5 * 33 (Dinner) + 722 (Accommodation) = 150 + 140 + 165 + 722 = 1177\n\nDay 2: March 8th, 2022\nCurrent City: Chattanooga\nTransportation: -\nBreakfast: The Royal, Chattanooga, Cost: 39, Cuisines: \"French, Pizza, Bakery, Fast Food\"\nAttraction: Rock City Gardens, Chattanooga\nLunch: Cook Du Kdu, Chattanooga, Cost: 69, Cuisines: \"Pizza, Fast Food, Cafe, Indian, Mediterranean, Seafood\"\nDinner: Ichiban, Chattanooga, Cost: 87, Cuisines: \"Mexican, Bakery, Desserts\"\nAccommodation: Sunny One Bedroom, Chattanooga, Cost: 722, Maximum Occupancy: 5, House Rules: No pets & No children under 10, Minimum Nights: 1\n\nNumber of People = 5\nTotal Cost = 5 * 39 (Breakfast) + 5 * 69 (Lunch) + 5 * 87 (Dinner) + 722 (Accommodation) = 195 + 345 + 435 + 722 = 1697\n\nDay 3: March 9th, 2022\nCurrent City: from Chattanooga to Atlanta\nTransportation: Flight Number: F3642297, from Chattanooga to Atlanta, Departure Time: 14:29, Arrival Time: 15:36, Cost: 33\nBreakfast: Bisque Bakery, Chattanooga, Cost: 90, Cuisines: \"French, Desserts, Seafood\"\nAttraction: Hunter Museum of American Art, Chattanooga\nLunch: Anupam Sweets & Restaurant, Chattanooga, Cost: 62, Cuisines: \"Tea, Cafe, Desserts, Seafood\"\nDinner: - (Assuming dinner will be had upon arrival in Atlanta or after the trip)\nAccommodation: -\n\nNumber of People = 5\nTotal Cost = 5 * 33 (Flight) + 5 * 90 (Breakfast) + 5 * 62 (Lunch) = 165 + 450 + 310 = 925\n\nTotal cost across all days = 1177 + 1697 + 925 = 3799\n\nCuisines: The plan includes French, Mediterranean, Indian, and Chinese cuisines as requested.\n\nPlease note that the total cost slightly exceeds the budget of $3,600 by $199. To adjust for this, you may consider changing the flight to a cheaper option, choosing less expensive restaurants, or finding a more budget-friendly accommodation. However, given the constraints and the desire for entire room accommodations, this is the most optimal plan that includes the requested cuisines and adheres to the other constraints.", "gpt-4-1106-preview_direct_sole-planning_parsed_results": [{"day": 1, "current_city": "from Atlanta to Chattanooga", "transportation": "Flight Number: F3540824, from Atlanta to Chattanooga, Departure Time: 10:20, Arrival Time: 11:05", "breakfast": "-", "attraction": "Tennessee Aquarium, Chattanooga;", "lunch": "L'amandier, Chattanooga", "dinner": "P.F. Chang's, Chattanooga", "accommodation": "Sunny One Bedroom, Chattanooga"}, {"day": 2, "current_city": "Chattanooga", "transportation": "-", "breakfast": "The Royal, Chattanooga", "attraction": "Rock City Gardens, Chattanooga;", "lunch": "Cook Du Kdu, Chattanooga", "dinner": "Ichiban, Chattanooga", "accommodation": "Sunny One Bedroom, Chattanooga"}, {"day": 3, "current_city": "from Chattanooga to Atlanta", "transportation": "Flight Number: F3642297, from Chattanooga to Atlanta, Departure Time: 14:29, Arrival Time: 15:36", "breakfast": "Bisque Bakery, Chattanooga", "attraction": "Hunter Museum of American Art, Chattanooga;", "lunch": "Anupam Sweets & Restaurant, Chattanooga", "dinner": "-", "accommodation": "-"}]}]