[{"gpt-4-1106-preview_direct_sole-planning_results": "Travel Plan:\nNumber of people = 5\nTotal budget = $3,600\n\nDays: 1, March 7th\nCurrent City: from Atlanta to Chattanooga\nTransportation: Flight Number: F3540824, from Atlanta to Chattanooga, Departure Time: 10:20, Arrival Time: 11:05, cost: $30 per person\nBreakfast: - (Assuming breakfast in Atlanta before departure)\nAttraction: Tennessee Aquarium, Chattanooga; cost: $29.95 per adult\nLunch: L'amandier, Chattanooga, cost: $28, cuisines: \u201cCafe, BBQ, Mediterranean, Seafood\u201d\nDinner: P.F. Chang's, Chattanooga, cost: $33, cuisines: \u201cCafe, Bakery, BBQ, Seafood\u201d\nAccommodation: Sunny One Bedroom, Chattanooga, cost: $722, room type: Entire home/apt, house rules: No pets & No children under 10, minimum nights: 1\n\nTotal cost for Day 1 = (Flight $30 + Aquarium $29.95 + Lunch $28 + Dinner $33) * 5 + Accommodation $722 = $1,087.25\n\nDays: 2, March 8th\nCurrent City: Chattanooga\nTransportation: -\nBreakfast: The Royal, Chattanooga, cost: $39, cuisines: \u201cFrench, Pizza, Bakery, Fast Food\u201d\nAttraction: Rock City Gardens, Chattanooga; cost: $21.95 per adult\nLunch: Chaayos, Chattanooga, cost: $54, cuisines: \u201cDesserts, Cafe, BBQ, Chinese, Seafood\u201d\nDinner: Curry n Phulka, Chattanooga, cost: $40, cuisines: \u201cTea, Chinese, Fast Food\u201d\nAccommodation: Sunny One Bedroom, Chattanooga, cost: $722, room type: Entire home/apt, house rules: No pets & No children under 10, minimum nights: 1\n\nTotal cost for Day 2 = (Breakfast $39 + Rock City $21.95 + Lunch $54 + Dinner $40) * 5 + Accommodation $722 = $1,367.25\n\nDays: 3, March 9th\nCurrent City: from Chattanooga to Atlanta\nTransportation: Flight Number: F3644458, from Chattanooga to Atlanta, Departure Time: 17:43, Arrival Time: 18:31, cost: $21 per person\nBreakfast: Bisque Bakery, Chattanooga, cost: $90, cuisines: \u201cFrench, Desserts, Seafood\u201d\nAttraction: Hunter Museum of American Art, Chattanooga; cost: $20 per adult\nLunch: Anupam Sweet, Chattanooga, cost: $82, cuisines: \u201cDesserts, American, BBQ\u201d\nDinner: - (Assuming dinner in Atlanta after arrival)\nAccommodation: - (Assuming return to own residence in Atlanta)\n\nTotal cost for Day 3 = (Flight $21 + Breakfast $90 + Museum $20 + Lunch $82) * 5 = $1,065\n\nTotal cost across all days = $1,087.25 + $1,367.25 + $1,065 = $3,519.50\n\nCuisines: French, Mediterranean, Indian, and Chinese cuisines have been included in the meals chosen.\n\nNote: The attractions and meals were selected based on the provided CSV data and the specified preferences in the query. The accommodations chosen are entire home/apt as requested, and the transportation does not include self-driving as per the constraints. The total cost is within the specified budget of $3,600.", "gpt-4-1106-preview_direct_sole-planning_parsed_results": [{"day": 1, "current_city": "from Atlanta to Chattanooga", "transportation": "Flight Number: F3540824, from Atlanta to Chattanooga, Departure Time: 10:20, Arrival Time: 11:05", "breakfast": "-", "attraction": "Tennessee Aquarium, Chattanooga;", "lunch": "L'amandier, Chattanooga", "dinner": "P.F. Chang's, Chattanooga", "accommodation": "Sunny One Bedroom, Chattanooga"}, {"day": 2, "current_city": "Chattanooga", "transportation": "-", "breakfast": "The Royal, Chattanooga", "attraction": "Rock City Gardens, Chattanooga;", "lunch": "Chaayos, Chattanooga", "dinner": "Curry n Phulka, Chattanooga", "accommodation": "Sunny One Bedroom, Chattanooga"}, {"day": 3, "current_city": "from Chattanooga to Atlanta", "transportation": "Flight Number: F3644458, from Chattanooga to Atlanta, Departure Time: 17:43, Arrival Time: 18:31", "breakfast": "Bisque Bakery, Chattanooga", "attraction": "Hunter Museum of American Art, Chattanooga;", "lunch": "Anupam Sweet, Chattanooga", "dinner": "-", "accommodation": "-"}]}]