[{"gpt-4-1106-preview_direct_sole-planning_results": "Travel Plan:\nDays: 1,\nCurrent City: from St. Petersburg to Rockford,\nTransportation: Flight Number: F3573659, from St. Petersburg to Rockford, Departure Time: 15:40, Arrival Time: 17:04, cost: 474\nBreakfast: -,\nAttraction: -,\nLunch: -,\nDinner: Coco Bambu, Rockford, cost: 72, cuisines: \u201cTea, French, Bakery, BBQ, Cafe\u201d\nAccommodation: Private Room in a two bedroom apt., Rockford, cost: 210, room type: Private room, house rules: No visitors & No smoking, minimum nights: 1, maximum occupancy: 2\n\nNumber of people = 1\nTotal cost = 474 + 72 + 210 = 756\nAccommodation minimum nights:  1/1\n\nDays: 2,\nCurrent City: Rockford,\nTransportation: -,\nBreakfast: Cafe Coffee Day, Rockford, cost: 28, cuisines: \u201cChinese, Desserts, Pizza, Cafe, Mediterranean\u201d\nAttraction: Anderson Japanese Gardens, Rockford, cost: 0 (assuming free entry)\nLunch: Flying Mango, Rockford, cost: 20, cuisines: \u201cAmerican, BBQ, Seafood\u201d\nDinner: Aroma Rest O Bar, Rockford, cost: 58, cuisines: \u201cBakery, Fast Food, Chinese, American, Seafood\u201d\nAccommodation: Private Room in a two bedroom apt., Rockford, cost: 210, room type: Private room, house rules: No visitors & No smoking, minimum nights: 1, maximum occupancy: 2\n\nNumber of people = 1\nTotal cost = 28 + 20 + 58 + 210 = 316\nAccommodation minimum nights:  2/1\n\nDays: 3,\nCurrent City: from Rockford to St. Petersburg,\nTransportation: Flight Number: F3573120, from Rockford to St. Petersburg, Departure Time: 19:00, Arrival Time: 22:43, cost: 346\nBreakfast: Dunkin' Donuts, Rockford, cost: 24, cuisines: \u201cCafe, Bakery, BBQ, Seafood\u201d\nAttraction: Burpee Museum of Natural History, Rockford, cost: 0 (assuming free entry)\nLunch: Gajalee Sea Food, Rockford, cost: 49, cuisines: \u201cBakery, BBQ\u201d\nDinner: -,\nAccommodation: -,\n\nNumber of people = 1\nTotal cost = 24 + 49 + 346 = 419\n\nTotal cost across all days = 756 + 316 + 419 = 1,491\n\nCuisines: The restaurants chosen offer a variety of cuisines including the specified American and BBQ, with additional options such as Tea, French, Bakery, Cafe, Chinese, Desserts, Pizza, Mediterranean, and Seafood.\n\nNote: The attractions listed do not have an entry cost associated with them in the provided data, so they are assumed to be free. If there is an entry fee, it should be added to the total cost. The accommodation chosen does not exceed the minimum night stay requirement. The total cost is within the specified budget of $1,700.", "gpt-4-1106-preview_direct_sole-planning_parsed_results": [{"day": 1, "current_city": "from St. Petersburg to Rockford", "transportation": "Flight Number: F3573659, from St. Petersburg to Rockford, Departure Time: 15:40, Arrival Time: 17:04", "breakfast": "-", "attraction": "-", "lunch": "-", "dinner": "Coco Bambu, Rockford", "accommodation": "Private Room in a two bedroom apt., Rockford"}, {"day": 2, "current_city": "Rockford", "transportation": "-", "breakfast": "Cafe Coffee Day, Rockford", "attraction": "Anderson Japanese Gardens, Rockford;", "lunch": "Flying Mango, Rockford", "dinner": "Aroma Rest O Bar, Rockford", "accommodation": "Private Room in a two bedroom apt., Rockford"}, {"day": 3, "current_city": "from Rockford to St. Petersburg", "transportation": "Flight Number: F3573120, from Rockford to St. Petersburg, Departure Time: 19:00, Arrival Time: 22:43", "breakfast": "Dunkin' Donuts, Rockford", "attraction": "Burpee Museum of Natural History, Rockford;", "lunch": "Gajalee Sea Food, Rockford", "dinner": "-", "accommodation": "-"}]}]