[{"gpt-4-1106-preview_direct_sole-planning_results": "Travel Plan:\n\nDays: 1,\nCurrent City: from Grand Forks to Minneapolis,\nTransportation: Self-driving, from Grand Forks to Minneapolis, duration: 4 hours 37 mins, distance: 507 km, cost: 25\nBreakfast: -,\nAttraction: -,\nLunch: -,\nDinner: The Cafe, Minneapolis, cost: 14, cuisines: \u201cIndian, Mediterranean, Desserts, Seafood\u201d\nAccommodation: Light-filled Apartment in great area, close 2 all!, Minneapolis, cost: 343, room type: Entire home/apt, house rules: No visitors, minimum nights: 1, maximum occupancy: 2\n\nNumber of people = 2\nTotal cost = (25 + 14) * 2 + 343 = 421\nAccommodation minimum nights:  1/1\n\nDays: 2,\nCurrent City: Minneapolis,\nTransportation: -,\nBreakfast: Court Avenue Brewing Company, Minneapolis, cost: 31, cuisines: \u201cPizza, French, Bakery, BBQ, Seafood\u201d\nAttraction: Minneapolis Sculpture Garden, Minneapolis; Mill City Museum, Minneapolis;,\nLunch: Malo, Minneapolis, cost: 80, cuisines: \u201cTea, Chinese, Indian, Cafe\u201d\nDinner: Monkeypod Kitchen by Merriman, Minneapolis, cost: 50, cuisines: \u201cDesserts, Pizza, Bakery, Fast Food, Indian, Mediterranean\u201d\nAccommodation: Light-filled Apartment in great area, close 2 all!, Minneapolis, cost: 343, room type: Entire home/apt, house rules: No visitors, minimum nights: 1, maximum occupancy: 2\n\nNumber of people = 2\nTotal cost = (31 + 80 + 50) * 2 + 343 = 707\nAccommodation minimum nights:  2/1\n\nDays: 3,\nCurrent City: from Minneapolis to Grand Forks,\nTransportation: Taxi, from Minneapolis to Grand Forks, duration: 4 hours 37 mins, distance: 507 km, cost: 507\nBreakfast: -,\nAttraction: -,\nLunch: -,\nDinner: -,\nAccommodation: -\n\nNumber of people = 2\nTotal cost = 507 * 2 = 1014\n\nTotal cost across all days = 421 + 707 + 1014 = 2142\n\nUnfortunately, the total cost exceeds the specified budget of $1,300. To adjust the plan within the budget, we can consider changing the accommodation or dining options. Here's an updated plan with a more affordable accommodation:\n\nRevised Travel Plan:\n\nDays: 1,\nCurrent City: from Grand Forks to Minneapolis,\nTransportation: Self-driving, from Grand Forks to Minneapolis, duration: 4 hours 37 mins, distance: 507 km, cost: 25\nBreakfast: -,\nAttraction: -,\nLunch: -,\nDinner: The Cafe, Minneapolis, cost: 14, cuisines: \u201cIndian, Mediterranean, Desserts, Seafood\u201d\nAccommodation: ROOM TWO, Minneapolis, cost: 112, room type: Private room, house rules: No children under 10, minimum nights: 3, maximum occupancy: 2\n\nNumber of people = 2\nTotal cost = (25 + 14) * 2 + 112 = 190\nAccommodation minimum nights:  1/3\n\nDays: 2,\nCurrent City: Minneapolis,\nTransportation: -,\nBreakfast: Court Avenue Brewing Company, Minneapolis, cost: 31, cuisines: \u201cPizza, French, Bakery, BBQ, Seafood\u201d\nAttraction: Minneapolis Sculpture Garden, Minneapolis; Mill City Museum, Minneapolis;,\nLunch: Malo, Minneapolis, cost: 80, cuisines: \u201cTea, Chinese, Indian, Cafe\u201d\nDinner: Monkeypod Kitchen by Merriman, Minneapolis, cost: 50, cuisines: \u201cDesserts, Pizza, Bakery, Fast Food, Indian, Mediterranean\u201d\nAccommodation: ROOM TWO, Minneapolis, cost: 112, room type: Private room, house rules: No children under 10, minimum nights: 3, maximum occupancy: 2\n\nNumber of people = 2\nTotal cost = (31 + 80 + 50) * 2 + 112 = 476\nAccommodation minimum nights:  2/3\n\nDays: 3,\nCurrent City: from Minneapolis to Grand Forks,\nTransportation: Taxi, from Minneapolis to Grand Forks, duration: 4 hours 37 mins, distance: 507 km, cost: 507\nBreakfast: -,\nAttraction: -,\nLunch: -,\nDinner: -,\nAccommodation: -\n\nNumber of people = 2\nTotal cost = 507 * 2 = 1014\n\nTotal revised cost across all days = 190 + 476 + 1014 = 1680\n\nThe revised plan still exceeds the budget. To further reduce costs, we can opt for self-driving on the return trip and choose more affordable dining options:\n\nFinal Revised Travel Plan:\n\nDays: 1,\nCurrent City: from Grand Forks to Minneapolis,\nTransportation: Self-driving, from Grand Forks to Minneapolis, duration: 4 hours 37 mins, distance: 507 km, cost: 25\nBreakfast: -,\nAttraction: -,\nLunch: -,\nDinner: The Cafe, Minneapolis, cost: 14, cuisines: \u201cIndian, Mediterranean, Desserts, Seafood\u201d\nAccommodation: ROOM TWO, Minneapolis, cost: 112, room type: Private room, house rules: No children under 10, minimum nights: 3, maximum occupancy: 2\n\nNumber of people = 2\nTotal cost = (25 + 14) * 2 + 112 = 190\nAccommodation minimum nights:  1/3\n\nDays: 2,\nCurrent City: Minneapolis,\nTransportation: -,\nBreakfast: Court Avenue Brewing Company, Minneapolis, cost: 31, cuisines: \u201cPizza, French, Bakery, BBQ, Seafood\u201d\nAttraction: Minneapolis Sculpture Garden, Minneapolis; Mill City Museum, Minneapolis;,\nLunch: Malo, Minneapolis, cost: 80, cuisines: \u201cTea, Chinese, Indian, Cafe\u201d\nDinner: Monkeypod Kitchen by Merriman, Minneapolis, cost: 50, cuisines: \u201cDesserts, Pizza, Bakery, Fast Food, Indian, Mediterranean\u201d\nAccommodation: ROOM TWO, Minneapolis, cost: 112, room type: Private room, house rules: No children under 10, minimum nights: 3, maximum occupancy: 2\n\nNumber of people = 2\nTotal cost = (31 + 80 + 50) * 2 + 112 = 476\nAccommodation minimum nights:  2/3\n\nDays: 3,\nCurrent City: from Minneapolis to Grand Forks,\nTransportation: Self-driving, from Minneapolis to Grand Forks, duration: 4 hours 37 mins, distance: 507 km, cost: 25\nBreakfast: -,\nAttraction: -,\nLunch: -,\nDinner: -,\nAccommodation: -\n\nNumber of people = 2\nTotal cost = 25 * 2 = 50\n\nTotal final revised cost across all days = 190 + 476 + 50 = 716\n\nThe final revised travel plan is within the budget of $1,300.", "gpt-4-1106-preview_direct_sole-planning_parsed_results": [{"day": 1, "current_city": "from Grand Forks to Minneapolis", "transportation": "Self-driving, from Grand Forks to Minneapolis, duration: 4 hours 37 mins, distance: 507 km", "breakfast": "-", "attraction": "-", "lunch": "-", "dinner": "The Cafe, Minneapolis", "accommodation": "Light-filled Apartment in great area, close 2 all!, Minneapolis"}, {"day": 2, "current_city": "Minneapolis", "transportation": "-", "breakfast": "Court Avenue Brewing Company, Minneapolis", "attraction": "Minneapolis Sculpture Garden, Minneapolis;Mill City Museum, Minneapolis;", "lunch": "Malo, Minneapolis", "dinner": "Monkeypod Kitchen by Merriman, Minneapolis", "accommodation": "Light-filled Apartment in great area, close 2 all!, Minneapolis"}, {"day": 3, "current_city": "from Minneapolis to Grand Forks", "transportation": "Taxi, from Minneapolis to Grand Forks, duration: 4 hours 37 mins, distance: 507 km", "breakfast": "-", "attraction": "-", "lunch": "-", "dinner": "-", "accommodation": "-"}, {"day": 1, "current_city": "from Grand Forks to Minneapolis", "transportation": "Self-driving, from Grand Forks to Minneapolis, duration: 4 hours 37 mins, distance: 507 km", "breakfast": "-", "attraction": "-", "lunch": "-", "dinner": "The Cafe, Minneapolis", "accommodation": "ROOM TWO, Minneapolis"}, {"day": 2, "current_city": "Minneapolis", "transportation": "-", "breakfast": "Court Avenue Brewing Company, Minneapolis", "attraction": "Minneapolis Sculpture Garden, Minneapolis;Mill City Museum, Minneapolis;", "lunch": "Malo, Minneapolis", "dinner": "Monkeypod Kitchen by Merriman, Minneapolis", "accommodation": "ROOM TWO, Minneapolis"}, {"day": 3, "current_city": "from Minneapolis to Grand Forks", "transportation": "Taxi, from Minneapolis to Grand Forks, duration: 4 hours 37 mins, distance: 507 km", "breakfast": "-", "attraction": "-", "lunch": "-", "dinner": "-", "accommodation": "-"}, {"day": 1, "current_city": "from Grand Forks to Minneapolis", "transportation": "Self-driving, from Grand Forks to Minneapolis, duration: 4 hours 37 mins, distance: 507 km", "breakfast": "-", "attraction": "-", "lunch": "-", "dinner": "The Cafe, Minneapolis", "accommodation": "ROOM TWO, Minneapolis"}, {"day": 2, "current_city": "Minneapolis", "transportation": "-", "breakfast": "Court Avenue Brewing Company, Minneapolis", "attraction": "Minneapolis Sculpture Garden, Minneapolis;Mill City Museum, Minneapolis;", "lunch": "Malo, Minneapolis", "dinner": "Monkeypod Kitchen by Merriman, Minneapolis", "accommodation": "ROOM TWO, Minneapolis"}, {"day": 3, "current_city": "from Minneapolis to Grand Forks", "transportation": "Self-driving, from Minneapolis to Grand Forks, duration: 4 hours 37 mins, distance: 507 km", "breakfast": "-", "attraction": "-", "lunch": "-", "dinner": "-", "accommodation": "-"}]}]