[{"gpt-4-1106-preview_direct_sole-planning_results": "Travel Plan:\nDays: 1,\nCurrent City: from Indianapolis to Grand Junction (Colorado),\nTransportation: Self-driving, from Indianapolis to Grand Junction, duration: 19 hours 23 mins, distance: 2,132 km, cost: 106 * 5 = 530\nBreakfast: -,\nAttraction: -,\nLunch: -,\nDinner: Austin's BBQ and Oyster Bar, Grand Junction (Colorado), cost: 15 * 5 = 75, cuisines: \u201cTea, Bakery, Fast Food, Indian, Seafood\u201d\nAccommodation: NYC Apartment near Central Park!, Grand Junction (Colorado), cost: 1118, room type: Entire home/apt, house rules: No children under 10, minimum nights: 3, maximum occupancy: 5, pet-friendly: Yes\n\nNumber of people = 5\nTotal cost = 530 + 75 + 1118 = 1,723\nAccommodation minimum nights:  1/3\n\nDays: 2,\nCurrent City: Grand Junction (Colorado),\nTransportation: -,\nBreakfast: 2 Dog, Grand Junction (Colorado), cost: 29 * 5 = 145, cuisines: \u201cDesserts, BBQ, Fast Food, Cafe, American\u201d\nAttraction: Museum of the West, Museums of Western Colorado, Grand Junction (Colorado); Canyon View Park, Grand Junction (Colorado);\nLunch: Punjab Da Pind, Grand Junction (Colorado), cost: 52 * 5 = 260, cuisines: \u201cDesserts, Pizza, Bakery, Chinese, Mediterranean, Seafood\u201d\nDinner: Ambarsari Kababs & Curries, Grand Junction (Colorado), cost: 55 * 5 = 275, cuisines: \u201cPizza, BBQ, Fast Food, Cafe, American\u201d\nAccommodation: NYC Apartment near Central Park!, Grand Junction (Colorado), cost: 1118, room type: Entire home/apt, house rules: No children under 10, minimum nights: 3, maximum occupancy: 5, pet-friendly: Yes\n\nNumber of people = 5\nTotal cost = 145 + 260 + 275 + 1118 = 1,798\nAccommodation minimum nights:  2/3\n\nDays: 3,\nCurrent City: from Grand Junction to Alamosa (Colorado),\nTransportation: Self-driving, from Grand Junction to Alamosa, duration: 4 hours 37 mins, distance: 397 km, cost: 19 * 5 = 95\nBreakfast: -,\nAttraction: San Luis Valley Museum | Alamosa, Alamosa (Colorado); Rio Grande Farm Park, Alamosa (Colorado);\nLunch: Riverwalk Cafe, Alamosa (Colorado), cost: 97 * 5 = 485, cuisines: \u201cTea, Pizza, Fast Food\u201d\nDinner: Street Foods by Punjab Grill, Alamosa (Colorado), cost: 55 * 5 = 275, cuisines: \u201cPizza, BBQ, Fast Food, Chinese, Mediterranean\u201d\nAccommodation: Comfortable studio suite in midtown Manhattan, Alamosa (Colorado), cost: 67 * 5 = 335, room type: Entire home/apt, house rules: No parties & No smoking & No visitors, minimum nights: 30, maximum occupancy: 2, pet-friendly: Yes\n\nNumber of people = 5\nTotal cost = 95 + 485 + 275 + 335 = 1,190\nAccommodation minimum nights:  1/30\n\nDays: 4,\nCurrent City: Alamosa (Colorado),\nTransportation: -,\nBreakfast: Cafe LazyMojo, Alamosa (Colorado), cost: 26 * 5 = 130, cuisines: \u201cTea, Pizza, American, Fast Food\u201d\nAttraction: Alamosa National Wildlife Refuge and Visitor Center, Alamosa (Colorado); Cole Park, Alamosa (Colorado);\nLunch: The Diet Kitchen, Alamosa (Colorado), cost: 50 * 5 = 250, cuisines: \u201cPizza, Bakery, BBQ, American, Mediterranean\u201d\nDinner: Emperor's Lounge - The Taj Mahal Hotel, Alamosa (Colorado), cost: 65 * 5 = 325, cuisines: \u201cTea, Italian, BBQ, Cafe, Seafood\u201d\nAccommodation: Comfortable studio suite in midtown Manhattan, Alamosa (Colorado), cost: 67 * 5 = 335, room type: Entire home/apt, house rules: No parties & No smoking & No visitors, minimum nights: 30, maximum occupancy: 2, pet-friendly: Yes\n\nNumber of people = 5\nTotal cost = 130 + 250 + 325 + 335 = 1,040\nAccommodation minimum nights:  2/30\n\nDays: 5,\nCurrent City: from Alamosa to Denver (Colorado),\nTransportation: Flight Number: F3837896, from Alamosa to Denver, Departure Time: 18:06, Arrival Time: 18:57, cost: 57 * 5 = 285\nBreakfast: -,\nAttraction: Denver Zoo, Denver (Colorado); Denver Botanic Gardens, Denver (Colorado);\nLunch: The Urban Socialite, Denver (Colorado), cost: 34 * 5 = 170, cuisines: \u201cCafe, Indian, Desserts, Italian\u201d\nDinner: The Fatty Bao - Asian Gastro Bar, Denver (Colorado), cost: 93 * 5 = 465, cuisines: \u201cBakery, BBQ, Cafe, Indian, Seafood\u201d\nAccommodation: Harlem cozy nights, Denver (Colorado), cost: 457, room type: Entire home/apt, house rules: No visitors, minimum nights: 4, maximum occupancy: 3, pet-friendly: Yes\n\nNumber of people = 5\nTotal cost = 285 + 170 + 465 + 457 = 1,377\nAccommodation minimum nights:  1/4\n\nDays: 6,\nCurrent City: Denver (Colorado),\nTransportation: -,\nBreakfast: Rain Tree Grill, Denver (Colorado), cost: 94 * 5 = 470, cuisines: \u201cTea, Mexican, BBQ, Italian\u201d\nAttraction: Colorado State Capitol, Denver (Colorado); Denver Art Museum, Denver (Colorado);\nLunch: Cafe Diva, Denver (Colorado), cost: 44 * 5 = 220, cuisines: \u201cChinese, Cafe, Desserts, Fast Food\u201d\nDinner: Kebab Gali, Denver (Colorado), cost: 63 * 5 = 315, cuisines: \u201cTea, Bakery, BBQ, Italian\u201d\nAccommodation: Harlem cozy nights, Denver (Colorado), cost: 457, room type: Entire home/apt, house rules: No visitors, minimum nights: 4, maximum occupancy: 3, pet-friendly: Yes\n\nNumber of people = 5\nTotal cost = 470 + 220 + 315 + 457 = 1,462\nAccommodation minimum nights:  2/4\n\nDays: 7,\nCurrent City: from Denver to Indianapolis,\nTransportation: Flight Number: F3910546, from Denver to Indianapolis, Departure Time: 17:33, Arrival Time: 21:46, cost: 462 * 5 = 2,310\nBreakfast: -,\nAttraction: -,\nLunch: -,\nDinner: -,\nAccommodation: -\n\nNumber of people = 5\nTotal cost = 2,310\n\nTotal cost across all days = 1,723 + 1,798 + 1,190 + 1,040 + 1,377 + 1,462 + 2,310 = 10,900\nCuisines: The prompt specifies Mexican, Italian, Mediterranean, and Indian, and all of these cuisines have been represented in the restaurants chosen.", "gpt-4-1106-preview_direct_sole-planning_parsed_results": [{"day": 1, "current_city": "from Indianapolis to Grand Junction", "transportation": "Self-driving, from Indianapolis to Grand Junction, duration: 19 hours 23 mins, distance: 2,132 km", "breakfast": "-", "attraction": "-", "lunch": "-", "dinner": "Austin's BBQ and Oyster Bar, Grand Junction", "accommodation": "NYC Apartment near Central Park!, Grand Junction"}, {"day": 2, "current_city": "Grand Junction", "transportation": "-", "breakfast": "2 Dog, Grand Junction", "attraction": "Museum of the West, Museums of Western Colorado, Grand Junction;Canyon View Park, Grand Junction;", "lunch": "Punjab Da Pind, Grand Junction", "dinner": "Ambarsari Kababs & Curries, Grand Junction", "accommodation": "NYC Apartment near Central Park!, Grand Junction"}, {"day": 3, "current_city": "from Grand Junction to Alamosa", "transportation": "Self-driving, from Grand Junction to Alamosa, duration: 4 hours 37 mins, distance: 397 km", "breakfast": "-", "attraction": "San Luis Valley Museum | Alamosa, Alamosa;Rio Grande Farm Park, Alamosa;", "lunch": "Riverwalk Cafe, Alamosa", "dinner": "Street Foods by Punjab Grill, Alamosa", "accommodation": "Comfortable studio suite in midtown Manhattan, Alamosa"}, {"day": 4, "current_city": "Alamosa", "transportation": "-", "breakfast": "Cafe LazyMojo, Alamosa", "attraction": "Alamosa National Wildlife Refuge and Visitor Center, Alamosa;Cole Park, Alamosa;", "lunch": "The Diet Kitchen, Alamosa", "dinner": "Emperor's Lounge - The Taj Mahal Hotel, Alamosa", "accommodation": "Comfortable studio suite in midtown Manhattan, Alamosa"}, {"day": 5, "current_city": "from Alamosa to Denver", "transportation": "Flight Number: F3837896, from Alamosa to Denver, Departure Time: 18:06, Arrival Time: 18:57", "breakfast": "-", "attraction": "Denver Zoo, Denver;Denver Botanic Gardens, Denver;", "lunch": "The Urban Socialite, Denver", "dinner": "The Fatty Bao - Asian Gastro Bar, Denver", "accommodation": "Harlem cozy nights, Denver"}, {"day": 6, "current_city": "Denver", "transportation": "-", "breakfast": "Rain Tree Grill, Denver", "attraction": "Colorado State Capitol, Denver;Denver Art Museum, Denver;", "lunch": "Cafe Diva, Denver", "dinner": "Kebab Gali, Denver", "accommodation": "Harlem cozy nights, Denver"}, {"day": 7, "current_city": "from Denver to Indianapolis", "transportation": "Flight Number: F3910546, from Denver to Indianapolis, Departure Time: 17:33, Arrival Time: 21:46", "breakfast": "-", "attraction": "-", "lunch": "-", "dinner": "-", "accommodation": "-"}]}]