[{"gpt-4-1106-preview_direct_sole-planning_results": "Travel Plan:\nDays: 1,\nCurrent City: from Minneapolis to Toledo (Ohio),\nTransportation: Self-driving, from Minneapolis to Toledo, duration: 9 hours 43 mins, distance: 1,057 km, cost: 52\nBreakfast: -,\nAttraction: -,\nLunch: -,\nDinner: Devotay, Toledo (Ohio), cost: 78, cuisines: \u201cChinese, BBQ, Seafood\u201d\nAccommodation: Sunny Modern Lux Private House with Parking, Toledo (Ohio), cost: 614, room type: Entire home/apt, house rules: No smoking & No children under 10 & No parties, minimum nights: 1, maximum occupancy: 6, pet-friendly: Yes\n\nNumber of people = 2\nTotal cost = 52 * 2 + 78 * 2 + 614 = 884\nAccommodation minimum nights:  1/1\n\nDays: 2,\nCurrent City: Toledo (Ohio),\nTransportation: -,\nBreakfast: Barista, Toledo (Ohio), cost: 11, cuisines: \u201cDesserts, Bakery, Fast Food, Indian, Seafood\u201d\nAttraction: Toledo Zoo, Toledo (Ohio); Toledo Museum of Art, Toledo (Ohio);,\nLunch: Bombay Brasserie, Toledo (Ohio), cost: 32, cuisines: \u201cTea, Pizza, Mediterranean\u201d\nDinner: The Woking Mama, Toledo (Ohio), cost: 62, cuisines: \u201cPizza, French, BBQ, Fast Food, Indian, Seafood\u201d\nAccommodation: Sunny Modern Lux Private House with Parking, Toledo (Ohio), cost: 614, room type: Entire home/apt, house rules: No smoking & No children under 10 & No parties, minimum nights: 1, maximum occupancy: 6, pet-friendly: Yes\n\nNumber of people = 2\nTotal cost = (11 + 32 + 62) * 2 + 614 = 824\nAccommodation minimum nights:  2/1\n\nDays: 3,\nCurrent City: from Toledo (Ohio) to Cleveland (Ohio),\nTransportation: Self-driving, from Toledo to Cleveland, duration: 1 hour 50 mins, distance: 183 km, cost: 9\nBreakfast: -,\nAttraction: Cleveland Metroparks Zoo, Cleveland (Ohio); The Cleveland Museum of Art, Cleveland (Ohio);,\nLunch: Makhan Fish and Chicken Corner, Cleveland (Ohio), cost: 25, cuisines: \u201cPizza, French, Fast Food, Chinese, Seafood\u201d\nDinner: Five Boroughs, Cleveland (Ohio), cost: 97, cuisines: \u201cFrench, Bakery, BBQ, Seafood\u201d\nAccommodation: Richmond Hill 3 Bedroom apartment in Private home!, Cleveland (Ohio), cost: 565, room type: Entire home/apt, house rules: No visitors, minimum nights: 1, maximum occupancy: 4, pet-friendly: Yes\n\nNumber of people = 2\nTotal cost = 9 * 2 + (25 + 97) * 2 + 565 = 828\nAccommodation minimum nights:  1/1\n\nDays: 4,\nCurrent City: Cleveland (Ohio),\nTransportation: -,\nBreakfast: Bikanerwala, Cleveland (Ohio), cost: 10, cuisines: \u201cTea, Bakery, BBQ, Fast Food\u201d\nAttraction: Rock & Roll Hall of Fame, Cleveland (Ohio); Great Lakes Science Center, Cleveland (Ohio);,\nLunch: Me Kong Bowl, Cleveland (Ohio), cost: 19, cuisines: \u201cCafe, BBQ, Seafood\u201d\nDinner: Green Leaf, Cleveland (Ohio), cost: 73, cuisines: \u201cDesserts, Tea, Cafe, BBQ, Chinese\u201d\nAccommodation: Richmond Hill 3 Bedroom apartment in Private home!, Cleveland (Ohio), cost: 565, room type: Entire home/apt, house rules: No visitors, minimum nights: 1, maximum occupancy: 4, pet-friendly: Yes\n\nNumber of people = 2\nTotal cost = (10 + 19 + 73) * 2 + 565 = 769\nAccommodation minimum nights:  2/1\n\nDays: 5,\nCurrent City: from Cleveland (Ohio) to Dayton (Ohio),\nTransportation: Self-driving, from Cleveland to Dayton, duration: 3 hours 11 mins, distance: 340 km, cost: 17\nBreakfast: -,\nAttraction: Carillon Historical Park, Dayton (Ohio); Boonshoft Museum of Discovery, Dayton (Ohio);,\nLunch: Onesta, Dayton (Ohio), cost: 47, cuisines: \u201cItalian, BBQ, Fast Food, Cafe, American, Seafood\u201d\nDinner: Star Noodle, Dayton (Ohio), cost: 17, cuisines: \u201cDesserts, Bakery, BBQ, Fast Food, Chinese, American\u201d\nAccommodation: Luxurious, Sunny Apartment Overlooking Park, Dayton (Ohio), cost: 226, room type: Entire home/apt, house rules: No pets & No parties & No children under 10, minimum nights: 2, maximum occupancy: 2, pet-friendly: Yes\n\nNumber of people = 2\nTotal cost = 17 * 2 + (47 + 17) * 2 + 226 = 371\nAccommodation minimum nights:  1/2\n\nDays: 6,\nCurrent City: Dayton (Ohio),\nTransportation: -,\nBreakfast: Subway, Dayton (Ohio), cost: 11, cuisines: \u201cBBQ, Desserts, Seafood\u201d\nAttraction: National Museum of the US Air Force, Dayton (Ohio); The Dayton Art Institute, Dayton (Ohio);,\nLunch: Pizza Express, Dayton (Ohio), cost: 92, cuisines: \u201cCafe, Pizza, American, Seafood\u201d\nDinner: 22nd Parallel, Dayton (Ohio), cost: 48, cuisines: \u201cTea, Bakery, BBQ\u201d\nAccommodation: Luxurious, Sunny Apartment Overlooking Park, Dayton (Ohio), cost: 226, room type: Entire home/apt, house rules: No pets & No parties & No children under 10, minimum nights: 2, maximum occupancy: 2, pet-friendly: Yes\n\nNumber of people = 2\nTotal cost = (11 + 92 + 48) * 2 + 226 = 628\nAccommodation minimum nights:  2/2\n\nDays: 7,\nCurrent City: from Dayton (Ohio) to Minneapolis,\nTransportation: Self-driving, from Dayton to Minneapolis, duration: 10 hours 31 mins, distance: 1,138 km, cost: 56\nBreakfast: -,\nAttraction: -,\nLunch: -,\nDinner: -,\nAccommodation: -\n\nNumber of people = 2\nTotal cost = 56 * 2 = 112\n\nTotal cost across all days = 884 + 824 + 828 + 769 + 371 + 628 + 112 = 4,516\nCuisines: The prompt specifies American, Mediterranean, Chinese, and Italian, and all of these cuisines have been represented in the restaurants chosen.", "gpt-4-1106-preview_direct_sole-planning_parsed_results": [{"day": 1, "current_city": "from Minneapolis to Toledo (Ohio)", "transportation": "Self-driving, from Minneapolis to Toledo, duration: 9 hours 43 mins, distance: 1,057 km", "breakfast": "-", "attraction": "-", "lunch": "-", "dinner": "Devotay, Toledo (Ohio)", "accommodation": "Sunny Modern Lux Private House with Parking, Toledo (Ohio)"}, {"day": 2, "current_city": "Toledo (Ohio)", "transportation": "-", "breakfast": "Barista, Toledo (Ohio)", "attraction": "Toledo Zoo, Toledo (Ohio);Toledo Museum of Art, Toledo (Ohio);", "lunch": "Bombay Brasserie, Toledo (Ohio)", "dinner": "The Woking Mama, Toledo (Ohio)", "accommodation": "Sunny Modern Lux Private House with Parking, Toledo (Ohio)"}, {"day": 3, "current_city": "from Toledo (Ohio) to Cleveland (Ohio)", "transportation": "Self-driving, from Toledo to Cleveland, duration: 1 hour 50 mins, distance: 183 km", "breakfast": "-", "attraction": "Cleveland Metroparks Zoo, Cleveland (Ohio);The Cleveland Museum of Art, Cleveland (Ohio);", "lunch": "Makhan Fish and Chicken Corner, Cleveland (Ohio)", "dinner": "Five Boroughs, Cleveland (Ohio)", "accommodation": "Richmond Hill 3 Bedroom apartment in Private home!, Cleveland (Ohio)"}, {"day": 4, "current_city": "Cleveland (Ohio)", "transportation": "-", "breakfast": "Bikanerwala, Cleveland (Ohio)", "attraction": "Rock & Roll Hall of Fame, Cleveland (Ohio);Great Lakes Science Center, Cleveland (Ohio);", "lunch": "Me Kong Bowl, Cleveland (Ohio)", "dinner": "Green Leaf, Cleveland (Ohio)", "accommodation": "Richmond Hill 3 Bedroom apartment in Private home!, Cleveland (Ohio)"}, {"day": 5, "current_city": "from Cleveland (Ohio) to Dayton (Ohio)", "transportation": "Self-driving, from Cleveland to Dayton, duration: 3 hours 11 mins, distance: 340 km", "breakfast": "-", "attraction": "Carillon Historical Park, Dayton (Ohio);Boonshoft Museum of Discovery, Dayton (Ohio);", "lunch": "Onesta, Dayton (Ohio)", "dinner": "Star Noodle, Dayton (Ohio)", "accommodation": "Luxurious, Sunny Apartment Overlooking Park, Dayton (Ohio)"}, {"day": 6, "current_city": "Dayton (Ohio)", "transportation": "-", "breakfast": "Subway, Dayton (Ohio)", "attraction": "National Museum of the US Air Force, Dayton (Ohio);The Dayton Art Institute, Dayton (Ohio);", "lunch": "Pizza Express, Dayton (Ohio)", "dinner": "22nd Parallel, Dayton (Ohio)", "accommodation": "Luxurious, Sunny Apartment Overlooking Park, Dayton (Ohio)"}, {"day": 7, "current_city": "from Dayton (Ohio) to Minneapolis", "transportation": "Self-driving, from Dayton to Minneapolis, duration: 10 hours 31 mins, distance: 1,138 km", "breakfast": "-", "attraction": "-", "lunch": "-", "dinner": "-", "accommodation": "-"}]}]