[{"gpt-4-1106-preview_direct_sole-planning_results": "Travel Plan:\n\nDays: 1,\nCurrent City: from Oklahoma City to Alamosa (Colorado),\nTransportation: Self-driving, from Oklahoma City to Alamosa, duration: 8 hours 53 mins, distance: 922 km, cost: 46\nBreakfast: -,\nAttraction: -,\nLunch: -,\nDinner: Atlanta Highway Seafood Market, Alamosa (Colorado), cost: 68, cuisines: \u201cFast Food, Desserts, Seafood\u201d\nAccommodation: Comfortable studio suite in midtown Manhattan, Alamosa (Colorado), cost: 67, maximum occupancy: 2, house rules: No parties & No smoking & No visitors, minimum nights: 30\n\nNumber of people = 1\nTotal cost = 46 + 68 + 67 = 181\nAccommodation minimum nights:  1/30\n\nDays: 2,\nCurrent City: Alamosa (Colorado),\nTransportation: -,\nBreakfast: Riverwalk Cafe, Alamosa (Colorado), cost: 97, cuisines: \u201cTea, Pizza, Fast Food\u201d\nAttraction: San Luis Valley Museum | Alamosa, Alamosa (Colorado); Rio Grande Farm Park, Alamosa (Colorado);,\nLunch: Coffee to Cocktail Bar - Hyatt Place, Alamosa (Colorado), cost: 35, cuisines: \u201cTea, Indian, Desserts, Italian\u201d\nDinner: Burger Singh, Alamosa (Colorado), cost: 95, cuisines: \u201cDesserts, Tea, BBQ, Chinese, Seafood\u201d\nAccommodation: Comfortable studio suite in midtown Manhattan, Alamosa (Colorado), cost: 67, maximum occupancy: 2, house rules: No parties & No smoking & No visitors, minimum nights: 30\n\nNumber of people = 1\nTotal cost = 97 + 35 + 95 + 67 = 294\nAccommodation minimum nights:  2/30\n\nDays: 3,\nCurrent City: from Alamosa (Colorado) to Grand Junction (Colorado),\nTransportation: Self-driving, from Alamosa to Grand Junction, duration: 4 hours 29 mins, distance: 396 km, cost: 19\nBreakfast: -,\nAttraction: Museum of the West, Museums of Western Colorado, Grand Junction (Colorado); Eureka! McConnell Science Museum, Grand Junction (Colorado);,\nLunch: Shanghai Bar & Lounge - The Bristol Hotel, Grand Junction (Colorado), cost: 31, cuisines: \u201cCafe, Pizza\u201d\nDinner: Punjab Da Pind, Grand Junction (Colorado), cost: 52, cuisines: \u201cDesserts, Pizza, Bakery, Chinese, Mediterranean, Seafood\u201d\nAccommodation: NYC Apartment near Central Park!, Grand Junction (Colorado), cost: 1118, maximum occupancy: 5, house rules: No children under 10, minimum nights: 3\n\nNumber of people = 1\nTotal cost = 19 + 31 + 52 + 1118 = 1220\nAccommodation minimum nights:  1/3\n\nDays: 4,\nCurrent City: Grand Junction (Colorado),\nTransportation: -,\nBreakfast: 2 Dog, Grand Junction (Colorado), cost: 29, cuisines: \u201cDesserts, BBQ, Fast Food, Cafe, American\u201d\nAttraction: Western Colorado Botanical Gardens, Grand Junction (Colorado); Canyon View Park, Grand Junction (Colorado);,\nLunch: Austin's BBQ and Oyster Bar, Grand Junction (Colorado), cost: 15, cuisines: \u201cTea, Bakery, Fast Food, Indian, Seafood\u201d\nDinner: 2 Dog, Grand Junction (Colorado), cost: 29, cuisines: \u201cDesserts, BBQ, Fast Food, Cafe, American\u201d\nAccommodation: NYC Apartment near Central Park!, Grand Junction (Colorado), cost: 1118, maximum occupancy: 5, house rules: No children under 10, minimum nights: 3\n\nNumber of people = 1\nTotal cost = 29 + 15 + 29 + 1118 = 1191\nAccommodation minimum nights:  2/3\n\nDays: 5,\nCurrent City: from Grand Junction (Colorado) to Durango (Colorado),\nTransportation: Self-driving, from Grand Junction to Durango, duration: 3 hours 33 mins, distance: 269 km, cost: 13\nBreakfast: -,\nAttraction: Animas Museum, Durango (Colorado); The Powerhouse, Durango (Colorado);,\nLunch: Samurai Japanese Cuisine & Sushi Bar, Durango (Colorado), cost: 67, cuisines: \u201cBakery, Desserts, Fast Food\u201d\nDinner: Dub's High on the Hog, Durango (Colorado), cost: 98, cuisines: \u201cTea, Italian, French, Cafe, Seafood\u201d\nAccommodation: Lux 1BR in the heart of NYC Theater district!, Durango (Colorado), cost: 81, maximum occupancy: 3, house rules: No children under 10, minimum nights: 30\n\nNumber of people = 1\nTotal cost = 13 + 67 + 98 + 81 = 259\nAccommodation minimum nights:  1/30\n\nDays: 6,\nCurrent City: Durango (Colorado),\nTransportation: -,\nBreakfast: Asian Haus, Durango (Colorado), cost: 26, cuisines: \u201cFast Food, Seafood, Pizza, Italian\u201d\nAttraction: Durango Adventures and Zipline Tours, Durango (Colorado); Oxbow Park and Preserve, Durango (Colorado);,\nLunch: Chickenette, Durango (Colorado), cost: 31, cuisines: \u201cTea, Pizza, Desserts, Fast Food\u201d\nDinner: Samurai Japanese Cuisine & Sushi Bar, Durango (Colorado), cost: 67, cuisines: \u201cBakery, Desserts, Fast Food\u201d\nAccommodation: Lux 1BR in the heart of NYC Theater district!, Durango (Colorado), cost: 81, maximum occupancy: 3, house rules: No children under 10, minimum nights: 30\n\nNumber of people = 1\nTotal cost = 26 + 31 + 67 + 81 = 205\nAccommodation minimum nights:  2/30\n\nDays: 7,\nCurrent City: from Durango (Colorado) to Oklahoma City,\nTransportation: Self-driving, from Durango to Oklahoma City, duration: 11 hours 13 mins, distance: 1,212 km, cost: 60\nBreakfast: -,\nAttraction: -,\nLunch: -,\nDinner: -,\nAccommodation: -\n\nNumber of people = 1\nTotal cost = 60\n\nTotal cost across all days = 181 + 294 + 1220 + 1191 + 259 + 205 + 60 = 3410\n\nUnfortunately, the total cost exceeds the budget of $3,000. Adjustments will need to be made to the plan to reduce costs. This could include choosing more budget-friendly accommodations, dining options, or altering transportation methods.", "gpt-4-1106-preview_direct_sole-planning_parsed_results": [{"day": 1, "current_city": "from Oklahoma City to Alamosa (Colorado)", "transportation": "Self-driving, from Oklahoma City to Alamosa, duration: 8 hours 53 mins, distance: 922 km", "breakfast": "-", "attraction": "-", "lunch": "-", "dinner": "Atlanta Highway Seafood Market, Alamosa (Colorado)", "accommodation": "Comfortable studio suite in midtown Manhattan, Alamosa (Colorado)"}, {"day": 2, "current_city": "Alamosa (Colorado)", "transportation": "-", "breakfast": "Riverwalk Cafe, Alamosa (Colorado)", "attraction": "San Luis Valley Museum | Alamosa, Alamosa (Colorado);Rio Grande Farm Park, Alamosa (Colorado);", "lunch": "Coffee to Cocktail Bar - Hyatt Place, Alamosa (Colorado)", "dinner": "Burger Singh, Alamosa (Colorado)", "accommodation": "Comfortable studio suite in midtown Manhattan, Alamosa (Colorado)"}, {"day": 3, "current_city": "from Alamosa (Colorado) to Grand Junction (Colorado)", "transportation": "Self-driving, from Alamosa to Grand Junction, duration: 4 hours 29 mins, distance: 396 km", "breakfast": "-", "attraction": "Museum of the West, Museums of Western Colorado, Grand Junction (Colorado);Eureka! McConnell Science Museum, Grand Junction (Colorado);", "lunch": "Shanghai Bar & Lounge - The Bristol Hotel, Grand Junction (Colorado)", "dinner": "Punjab Da Pind, Grand Junction (Colorado)", "accommodation": "NYC Apartment near Central Park!, Grand Junction (Colorado)"}, {"day": 4, "current_city": "Grand Junction (Colorado)", "transportation": "-", "breakfast": "2 Dog, Grand Junction (Colorado)", "attraction": "Western Colorado Botanical Gardens, Grand Junction (Colorado);Canyon View Park, Grand Junction (Colorado);", "lunch": "Austin's BBQ and Oyster Bar, Grand Junction (Colorado)", "dinner": "2 Dog, Grand Junction (Colorado)", "accommodation": "NYC Apartment near Central Park!, Grand Junction (Colorado)"}, {"day": 5, "current_city": "from Grand Junction (Colorado) to Durango (Colorado)", "transportation": "Self-driving, from Grand Junction to Durango, duration: 3 hours 33 mins, distance: 269 km", "breakfast": "-", "attraction": "Animas Museum, Durango (Colorado);The Powerhouse, Durango (Colorado);", "lunch": "Samurai Japanese Cuisine & Sushi Bar, Durango (Colorado)", "dinner": "Dub's High on the Hog, Durango (Colorado)", "accommodation": "Lux 1BR in the heart of NYC Theater district!, Durango (Colorado)"}, {"day": 6, "current_city": "Durango (Colorado)", "transportation": "-", "breakfast": "Asian Haus, Durango (Colorado)", "attraction": "Durango Adventures and Zipline Tours, Durango (Colorado);Oxbow Park and Preserve, Durango (Colorado);", "lunch": "Chickenette, Durango (Colorado)", "dinner": "Samurai Japanese Cuisine & Sushi Bar, Durango (Colorado)", "accommodation": "Lux 1BR in the heart of NYC Theater district!, Durango (Colorado)"}, {"day": 7, "current_city": "from Durango (Colorado) to Oklahoma City", "transportation": "Self-driving, from Durango to Oklahoma City, duration: 11 hours 13 mins, distance: 1,212 km", "breakfast": "-", "attraction": "-", "lunch": "-", "dinner": "-", "accommodation": "-"}]}]