[{"gpt-4-1106-preview_direct_sole-planning_results": "Travel Plan:\nDays: 1,\nCurrent City: from Kansas City to Pensacola,\nTransportation: Self-driving, from Kansas City to Pensacola, duration: 14 hours 4 mins, distance: 1,433 km, cost: 71\nBreakfast: -,\nAttraction: -,\nLunch: -,\nDinner: Frog Hollow Tavern, Pensacola, cost: 20, cuisines: \u201cAmerican, BBQ, Fast Food, Cafe, Indian\u201d\nAccommodation: Cozy 1-Bedroom Apartment 2 Blocks from the Subway, Pensacola, cost: 339, room type: Entire home/apt, house rules: No parties, minimum nights: 1, maximum occupancy: 3\n\nNumber of people = 1\nTotal cost = 71 + 20 + 339 = 430\nAccommodation minimum nights:  1/1\n\nDays: 2,\nCurrent City: Pensacola,\nTransportation: -,\nBreakfast: Berry Patch Restaurant, Pensacola, cost: 13, cuisines: \u201cBakery, BBQ, Desserts, Seafood\u201d\nAttraction: Historic Pensacola Village, Pensacola; Pensacola Museum of Art, Pensacola; Palafox Street Downtown Pensacola, Pensacola;,\nLunch: Bailey's Bar-B-Que, Pensacola, cost: 13, cuisines: \u201cTea, Bakery, Mediterranean\u201d\nDinner: Watershed Cafe, Pensacola, cost: 12, cuisines: \u201cChinese, BBQ, Desserts\u201d\nAccommodation: Cozy 1-Bedroom Apartment 2 Blocks from the Subway, Pensacola, cost: 339, room type: Entire home/apt, house rules: No parties, minimum nights: 1, maximum occupancy: 3\n\nNumber of people = 1\nTotal cost = 13 + 13 + 12 + 339 = 377\nAccommodation minimum nights:  2/1\n\nDays: 3,\nCurrent City: from Pensacola to Kansas City,\nTransportation: Self-driving, from Pensacola to Kansas City, duration: 14 hours 0 mins, distance: 1,447 km, cost: 72\nBreakfast: -,\nAttraction: -,\nLunch: -,\nDinner: -,\nAccommodation: -\n\nNumber of people = 1\nTotal cost = 72\n\nTotal cost across all days = 430 + 377 + 72 = 879\n\nCuisines: The prompt specifies American, BBQ, Fast Food, Cafe, Indian, Bakery, Desserts, Seafood, Tea, Mediterranean, and Chinese, and these cuisines have been represented in the restaurants chosen.\n\nNote: The travel plan adheres to the budget of $900, includes a variety of cuisines, and ensures that the traveler returns to the starting city, Kansas City, forming a closed loop. The accommodations are private as per the available data and do not exceed the budget. Attractions are included for the full day in Pensacola, and no attractions are repeated. The transportation method is consistent (self-driving) and matches the specified cities.", "gpt-4-1106-preview_direct_sole-planning_parsed_results": [{"day": 1, "current_city": "from Kansas City to Pensacola", "transportation": "Self-driving, from Kansas City to Pensacola, duration: 14 hours 4 mins, distance: 1,433 km", "breakfast": "-", "attraction": "-", "lunch": "-", "dinner": "Frog Hollow Tavern, Pensacola", "accommodation": "Cozy 1-Bedroom Apartment 2 Blocks from the Subway, Pensacola"}, {"day": 2, "current_city": "Pensacola", "transportation": "-", "breakfast": "Berry Patch Restaurant, Pensacola", "attraction": "Historic Pensacola Village, Pensacola;Pensacola Museum of Art, Pensacola;Palafox Street Downtown Pensacola, Pensacola;", "lunch": "Bailey's Bar-B-Que, Pensacola", "dinner": "Watershed Cafe, Pensacola", "accommodation": "Cozy 1-Bedroom Apartment 2 Blocks from the Subway, Pensacola"}, {"day": 3, "current_city": "from Pensacola to Kansas City", "transportation": "Self-driving, from Pensacola to Kansas City, duration: 14 hours 0 mins, distance: 1,447 km", "breakfast": "-", "attraction": "-", "lunch": "-", "dinner": "-", "accommodation": "-"}]}]