[{"gpt-4-1106-preview_direct_sole-planning_results": "Travel Plan:\n\nDays: 1,\nCurrent City: from Richmond to Miami (Florida),\nTransportation: Flight Number: F3681647, from Richmond to Miami (Florida), Departure Time: 06:28, Arrival Time: 08:53, cost: 316\nBreakfast: -,\nAttraction: Bayfront Park, Miami (Florida), cost: 0 (assuming no entry fee),\nLunch: Shorts Burger and Shine, Miami (Florida), cost: 81, cuisines: \u201cChinese, Cafe, Seafood\u201d\nDinner: L'Opera, Miami (Florida), cost: 28, cuisines: \u201cDesserts, Seafood\u201d\nAccommodation: \"HELLO BROOKLYN\" PARK SIDE VIEW NEWLY RENO APT., Miami (Florida), cost: 789, maximum occupancy: 6, house rules: No parties & No visitors, minimum nights: 1\n\nNumber of people = 7\nTotal cost = (316 * 7) + (81 + 28) * 7 + 789 = 4,013\nAccommodation minimum nights:  1/1\n\nDays: 2,\nCurrent City: Miami (Florida),\nTransportation: -,\nBreakfast: Clocked, Miami (Florida), cost: 49, cuisines: \u201cTea, Italian, Mexican, BBQ, Cafe\u201d\nAttraction: P\u00e9rez Art Museum Miami, Miami (Florida), cost: 0 (assuming no entry fee),\nLunch: AB's Absolute Barbecues, Miami (Florida), cost: 55, cuisines: \u201cDesserts, Tea, Pizza, Italian, Fast Food, American\u201d\nDinner: Anjlika, Miami (Florida), cost: 56, cuisines: \u201cPizza, Italian, Fast Food, Cafe, Mediterranean, Seafood\u201d\nAccommodation: \"HELLO BROOKLYN\" PARK SIDE VIEW NEWLY RENO APT., Miami (Florida), cost: 789, maximum occupancy: 6, house rules: No parties & No visitors, minimum nights: 1\n\nNumber of people = 7\nTotal cost = (49 + 55 + 56) * 7 + 789 = 2,065\nAccommodation minimum nights:  2/1\n\nDays: 3,\nCurrent City: from Miami (Florida) to Punta Gorda (Florida),\nTransportation: self-driving, from Miami to Punta Gorda, duration: 2 hours 41 mins, distance: 291 km, cost: 14\nBreakfast: Papouli's Mediterranean Cafe & Market, Miami (Florida), cost: 26, cuisines: \u201cTea, Desserts\u201d\nAttraction: Laishley Park, Punta Gorda (Florida), cost: 0 (assuming no entry fee),\nLunch: Urban Cuisine, Punta Gorda (Florida), cost: 84, cuisines: \u201cDesserts, Tea, Mexican, Fast Food, Chinese, Seafood\u201d\nDinner: Nathu's Sweets, Punta Gorda (Florida), cost: 66, cuisines: \u201cTea, Chinese, Desserts, Italian\u201d\nAccommodation: Beautiful Manhattan Apt- 20 min to Times Square, Punta Gorda (Florida), cost: 79, maximum occupancy: 3, house rules: No children under 10, minimum nights: 7\n\nNumber of people = 7\nTotal cost = (14 * 7) + (26 + 84 + 66) * 7 + (79 * 3) = 1,883\nAccommodation minimum nights:  1/7\n\nDays: 4,\nCurrent City: Punta Gorda (Florida),\nTransportation: -,\nBreakfast: Cookie Shoppe, Punta Gorda (Florida), cost: 44, cuisines: \u201cTea, Bakery, BBQ, Mediterranean, Seafood\u201d\nAttraction: Peace River Wildlife Center, Punta Gorda (Florida), cost: 0 (assuming no entry fee),\nLunch: China Cafe, Punta Gorda (Florida), cost: 69, cuisines: \u201cDesserts, Bakery, Cafe, Mediterranean, Seafood\u201d\nDinner: G Thal, Punta Gorda (Florida), cost: 61, cuisines: \u201cDesserts, Bakery, Cafe, American, Mediterranean\u201d\nAccommodation: Beautiful Manhattan Apt- 20 min to Times Square, Punta Gorda (Florida), cost: 79, maximum occupancy: 3, house rules: No children under 10, minimum nights: 7\n\nNumber of people = 7\nTotal cost = (44 + 69 + 61) * 7 + (79 * 3) = 1,722\nAccommodation minimum nights:  2/7\n\nDays: 5,\nCurrent City: from Punta Gorda (Florida) to Richmond,\nTransportation: self-driving, from Punta Gorda to Richmond, duration: 12 hours 50 mins, distance: 1,434 km, cost: 71\nBreakfast: -,\nAttraction: -,\nLunch: -,\nDinner: -,\nAccommodation: -\n\nNumber of people = 7\nTotal cost = 71 * 7 = 497\n\nTotal cost across all days = 4,013 + 2,065 + 1,883 + 1,722 + 497 = 10,180\n\nUnfortunately, the total cost exceeds the budget of $8,500. To adjust the plan within the budget, we can consider the following changes:\n\n- Opt for cheaper accommodation options.\n- Reduce dining costs by selecting restaurants with lower average costs.\n- Consider alternative transportation methods if cheaper.\n\nPlease note that the provided accommodation options in Punta Gorda do not allow visitors, which contradicts the requirement. Additionally, the accommodation in Punta Gorda has a minimum stay of 7 nights, which is not suitable for a 5-day itinerary. Therefore, we would need to find alternative accommodation that meets the requirements. However, due to the lack of provided options that meet the criteria, we cannot complete the itinerary within the given constraints.", "gpt-4-1106-preview_direct_sole-planning_parsed_results": [{"day": 1, "current_city": "from Richmond to Miami (Florida)", "transportation": "Flight Number: F3681647, from Richmond to Miami (Florida), Departure Time: 06:28, Arrival Time: 08:53", "breakfast": "-", "attraction": "Bayfront Park, Miami (Florida);", "lunch": "Shorts Burger and Shine, Miami (Florida)", "dinner": "L'Opera, Miami (Florida)", "accommodation": "\"HELLO BROOKLYN\" PARK SIDE VIEW NEWLY RENO APT., Miami (Florida)"}, {"day": 2, "current_city": "Miami (Florida)", "transportation": "-", "breakfast": "Clocked, Miami (Florida)", "attraction": "P\u00e9rez Art Museum Miami, Miami (Florida);", "lunch": "AB's Absolute Barbecues, Miami (Florida)", "dinner": "Anjlika, Miami (Florida)", "accommodation": "\"HELLO BROOKLYN\" PARK SIDE VIEW NEWLY RENO APT., Miami (Florida)"}, {"day": 3, "current_city": "from Miami (Florida) to Punta Gorda (Florida)", "transportation": "self-driving, from Miami to Punta Gorda, duration: 2 hours 41 mins, distance: 291 km", "breakfast": "Papouli's Mediterranean Cafe & Market, Miami (Florida)", "attraction": "Laishley Park, Punta Gorda (Florida);", "lunch": "Urban Cuisine, Punta Gorda (Florida)", "dinner": "Nathu's Sweets, Punta Gorda (Florida)", "accommodation": "Beautiful Manhattan Apt- 20 min to Times Square, Punta Gorda (Florida)"}, {"day": 4, "current_city": "Punta Gorda (Florida)", "transportation": "-", "breakfast": "Cookie Shoppe, Punta Gorda (Florida)", "attraction": "Peace River Wildlife Center, Punta Gorda (Florida);", "lunch": "China Cafe, Punta Gorda (Florida)", "dinner": "G Thal, Punta Gorda (Florida)", "accommodation": "Beautiful Manhattan Apt- 20 min to Times Square, Punta Gorda (Florida)"}, {"day": 5, "current_city": "from Punta Gorda (Florida) to Richmond", "transportation": "self-driving, from Punta Gorda to Richmond, duration: 12 hours 50 mins, distance: 1,434 km", "breakfast": "-", "attraction": "-", "lunch": "-", "dinner": "-", "accommodation": "-"}]}]