[{"gpt-4-1106-preview_direct_sole-planning_results": "Travel Plan:\nDays: 1,\nCurrent City: from Oakland to Portland (Oregon),\nTransportation: Flight Number: F3860996, from Oakland to Portland (Oregon), Departure Time: 13:26, Arrival Time: 14:50, cost: 152\nBreakfast: -,\nAttraction: -,\nLunch: -,\nDinner: Nacho Mamas Burritos, Portland (Oregon), cost: 54, cuisines: \u201cChinese, Pizza, Seafood, Italian\u201d\nAccommodation: The ocean view room size 12x14, Portland (Oregon), cost: 709, room type: Private room, house rules: No parties, minimum nights: 5, maximum occupancy: 1\n\nNumber of people = 2\nTotal cost = (152 + 54) * 2 + 709 = 1,121\nAccommodation minimum nights:  1/5\n\nDays: 2,\nCurrent City: Portland (Oregon),\nTransportation: -,\nBreakfast: Osaka, Portland (Oregon), cost: 42, cuisines: \u201cDesserts, Tea, Pizza, BBQ, Chinese\u201d\nAttraction: Washington Park, Portland (Oregon); Lan Su Chinese Garden, Portland (Oregon);,\nLunch: Cactus Flower Cafe Navarre, Portland (Oregon), cost: 48, cuisines: \u201cCafe, Italian, BBQ, Fast Food, Chinese\u201d\nDinner: Barbeque Nation, Portland (Oregon), cost: 79, cuisines: \u201cMediterranean, Desserts, Fast Food\u201d\nAccommodation: The ocean view room size 12x14, Portland (Oregon), cost: 709, room type: Private room, house rules: No parties, minimum nights: 5, maximum occupancy: 1\n\nNumber of people = 2\nTotal cost = (42 + 48 + 79) * 2 + 709 = 1,047\nAccommodation minimum nights:  2/5\n\nDays: 3,\nCurrent City: from Portland (Oregon) to Medford (Oregon),\nTransportation: Flight Number: F3861509, from Portland (Oregon) to Medford (Oregon), Departure Time: 16:10, Arrival Time: 17:12, cost: 78\nBreakfast: -,\nAttraction: -,\nLunch: -,\nDinner: Exotica, Medford (Oregon), cost: 25, cuisines: \u201cPizza, BBQ, Seafood\u201d\nAccommodation: The Fountain House, Medford (Oregon), cost: 178, room type: Entire home/apt, house rules: No parties & No children under 10, minimum nights: 2, maximum occupancy: 3\n\nNumber of people = 2\nTotal cost = (78 + 25) * 2 + 178 = 384\nAccommodation minimum nights:  1/2\n\nDays: 4,\nCurrent City: Medford (Oregon),\nTransportation: -,\nBreakfast: Desi Tadka, Medford (Oregon), cost: 55, cuisines: \u201cTea, Mexican, Bakery\u201d\nAttraction: Medford Railroad Park, Medford (Oregon); Crater Rock Museum, Medford (Oregon);,\nLunch: Tandooriwala, Medford (Oregon), cost: 58, cuisines: \u201cDesserts, Pizza, Mexican, Cafe, American\u201d\nDinner: Monarch Restaurant - Holiday Inn Jaipur City Centre, Medford (Oregon), cost: 83, cuisines: \u201cBBQ, Fast Food\u201d\nAccommodation: The Fountain House, Medford (Oregon), cost: 178, room type: Entire home/apt, house rules: No parties & No children under 10, minimum nights: 2, maximum occupancy: 3\n\nNumber of people = 2\nTotal cost = (55 + 58 + 83) * 2 + 178 = 570\nAccommodation minimum nights:  2/2\n\nDays: 5,\nCurrent City: from Medford (Oregon) to Eugene (Oregon),\nTransportation: Self-driving, from Medford (Oregon) to Eugene (Oregon), duration: 2 hours 40 mins, distance: 268 km, cost: 13\nBreakfast: -,\nAttraction: -,\nLunch: -,\nDinner: Ammu's South Indian Restaurant, Eugene (Oregon), cost: 91, cuisines: \u201cCafe, Indian, Desserts\u201d\nAccommodation: Large NYC Apartment!, Eugene (Oregon), cost: 185, room type: Private room, house rules: No parties, minimum nights: 3, maximum occupancy: 2\n\nNumber of people = 2\nTotal cost = (13 + 91) * 2 + 185 = 393\nAccommodation minimum nights:  1/3\n\nDays: 6,\nCurrent City: Eugene (Oregon),\nTransportation: -,\nBreakfast: Upper Crust, Eugene (Oregon), cost: 79, cuisines: \u201cTea, Pizza, Italian, Cafe, Seafood\u201d\nAttraction: Eugene Science Center, Eugene (Oregon); Hendricks Park, Eugene (Oregon);,\nLunch: Panchwati Rasoi, Eugene (Oregon), cost: 51, cuisines: \u201cDesserts, Fast Food, Cafe, American, Mediterranean\u201d\nDinner: Moti Mahal, Eugene (Oregon), cost: 72, cuisines: \u201cFrench, Seafood, Desserts, Italian\u201d\nAccommodation: Large NYC Apartment!, Eugene (Oregon), cost: 185, room type: Private room, house rules: No parties, minimum nights: 3, maximum occupancy: 2\n\nNumber of people = 2\nTotal cost = (79 + 51 + 72) * 2 + 185 = 589\nAccommodation minimum nights:  2/3\n\nDays: 7,\nCurrent City: from Eugene (Oregon) to Oakland,\nTransportation: Flight Number: F4027025, from Eugene (Oregon) to Oakland, Departure Time: 17:20, Arrival Time: 18:42, cost: 110\nBreakfast: -,\nAttraction: -,\nLunch: -,\nDinner: -,\nAccommodation: -\n\nNumber of people = 2\nTotal cost = 110 * 2 = 220\n\nTotal cost across all days = 1,121 + 1,047 + 384 + 570 + 393 + 589 + 220 = 4,324\nCuisines: The prompt specifies Italian and Mediterranean, and both of these cuisines have been represented in the restaurants chosen.", "gpt-4-1106-preview_direct_sole-planning_parsed_results": [{"day": 1, "current_city": "from Oakland to Portland (Oregon)", "transportation": "Flight Number: F3860996, from Oakland to Portland (Oregon), Departure Time: 13:26, Arrival Time: 14:50", "breakfast": "-", "attraction": "-", "lunch": "-", "dinner": "Nacho Mamas Burritos, Portland (Oregon)", "accommodation": "The ocean view room, Portland (Oregon)"}, {"day": 2, "current_city": "Portland (Oregon)", "transportation": "-", "breakfast": "Osaka, Portland (Oregon)", "attraction": "Washington Park, Portland (Oregon);Lan Su Chinese Garden, Portland (Oregon);", "lunch": "Cactus Flower Cafe Navarre, Portland (Oregon)", "dinner": "Barbeque Nation, Portland (Oregon)", "accommodation": "The ocean view room, Portland (Oregon)"}, {"day": 3, "current_city": "from Portland (Oregon) to Medford (Oregon)", "transportation": "Flight Number: F3861509, from Portland (Oregon) to Medford (Oregon), Departure Time: 16:10, Arrival Time: 17:12", "breakfast": "-", "attraction": "-", "lunch": "-", "dinner": "Exotica, Medford (Oregon)", "accommodation": "The Fountain House, Medford (Oregon)"}, {"day": 4, "current_city": "Medford (Oregon)", "transportation": "-", "breakfast": "Desi Tadka, Medford (Oregon)", "attraction": "Medford Railroad Park, Medford (Oregon);Crater Rock Museum, Medford (Oregon);", "lunch": "Tandooriwala, Medford (Oregon)", "dinner": "Monarch Restaurant - Holiday Inn Jaipur City Centre, Medford (Oregon)", "accommodation": "The Fountain House, Medford (Oregon)"}, {"day": 5, "current_city": "from Medford (Oregon) to Eugene (Oregon)", "transportation": "Self-driving, from Medford (Oregon) to Eugene (Oregon), duration: 2 hours 40 mins, distance: 268 km", "breakfast": "-", "attraction": "-", "lunch": "-", "dinner": "Ammu's South Indian Restaurant, Eugene (Oregon)", "accommodation": "Large NYC Apartment!, Eugene (Oregon)"}, {"day": 6, "current_city": "Eugene (Oregon)", "transportation": "-", "breakfast": "Upper Crust, Eugene (Oregon)", "attraction": "Eugene Science Center, Eugene (Oregon);Hendricks Park, Eugene (Oregon);", "lunch": "Panchwati Rasoi, Eugene (Oregon)", "dinner": "Moti Mahal, Eugene (Oregon)", "accommodation": "Large NYC Apartment!, Eugene (Oregon)"}, {"day": 7, "current_city": "from Eugene (Oregon) to Oakland", "transportation": "Flight Number: F4027025, from Eugene (Oregon) to Oakland, Departure Time: 17:20, Arrival Time: 18:42", "breakfast": "-", "attraction": "-", "lunch": "-", "dinner": "-", "accommodation": "-"}]}]