[{"gpt-4-1106-preview_direct_sole-planning_results": "Travel Plan:\n\nDays: 1,\nCurrent City: from San Jose to Boise (Idaho),\nTransportation: Flight Number: F3858398, from San Jose to Boise (Idaho), Departure Time: 15:20, Arrival Time: 17:47, cost: 216\nBreakfast: -,\nAttraction: -,\nLunch: -,\nDinner: Gopala Hari, Boise (Idaho), cost: 28, cuisines: \u201cTea, Pizza, Italian, Fast Food, Mediterranean, Seafood\u201d\nAccommodation: Modern & Cozy 2 BR Private Apartment in Brooklyn, Boise (Idaho), cost: 843, room type: Entire home/apt, house rules: No children under 10, minimum nights: 2645, maximum occupancy: 7\n\nNumber of people = 7\nTotal cost = (216 * 7) + 28 * 7 + 843 = 2,367\nAccommodation minimum nights:  1/2645\n\nDays: 2,\nCurrent City: Boise (Idaho),\nTransportation: -,\nBreakfast: TGI Friday's, Boise (Idaho), cost: 33, cuisines: \u201cCafe, Mexican, BBQ, Fast Food\u201d\nAttraction: Zoo Boise, Boise (Idaho); Idaho State Museum, Boise (Idaho);,\nLunch: California Pizza Kitchen, Boise (Idaho), cost: 15, cuisines: \u201cTea, BBQ, Fast Food, Chinese, Indian\u201d\nDinner: Dhaba By Claridges, Boise (Idaho), cost: 65, cuisines: \u201cDesserts, Italian, Fast Food, Chinese, Seafood\u201d\nAccommodation: Modern & Cozy 2 BR Private Apartment in Brooklyn, Boise (Idaho), cost: 843, room type: Entire home/apt, house rules: No children under 10, minimum nights: 2645, maximum occupancy: 7\n\nNumber of people = 7\nTotal cost = (33 + 15 + 65) * 7 + 843 = 1,757\nAccommodation minimum nights:  2/2645\n\nDays: 3,\nCurrent City: from Boise (Idaho) to Idaho Falls (Idaho),\nTransportation: self-driving, from Boise (Idaho) to Idaho Falls (Idaho), duration: 4 hours 1 min, distance: 451 km, cost: 22\nBreakfast: -,\nAttraction: -,\nLunch: -,\nDinner: Dhuaan, Idaho Falls (Idaho), cost: 97, cuisines: \u201cTea, Pizza, Mexican, BBQ, Fast Food, American\u201d\nAccommodation: Sunny & Spacious 2 bdrm apt, Idaho Falls (Idaho), cost: 914, room type: Entire home/apt, house rules: No smoking, minimum nights: 4, maximum occupancy: 9\n\nNumber of people = 7\nTotal cost = 22 * 7 + 97 * 7 + 914 = 1,673\nAccommodation minimum nights:  1/4\n\nDays: 4,\nCurrent City: Idaho Falls (Idaho),\nTransportation: -,\nBreakfast: Shiv Restaurant, Idaho Falls (Idaho), cost: 42, cuisines: \u201cBakery, Mexican, Pizza, Desserts\u201d\nAttraction: Museum of Idaho, Idaho Falls (Idaho); Giant Eagle Waterfall Nest, Idaho Falls (Idaho);,\nLunch: Taste of China, Idaho Falls (Idaho), cost: 19, cuisines: \u201cFrench, Bakery, Fast Food, Indian, Seafood\u201d\nDinner: The Fusion Food Stand, Idaho Falls (Idaho), cost: 49, cuisines: \u201cDesserts, Cafe, Italian, BBQ, Chinese, Seafood\u201d\nAccommodation: Sunny & Spacious 2 bdrm apt, Idaho Falls (Idaho), cost: 914, room type: Entire home/apt, house rules: No smoking, minimum nights: 4, maximum occupancy: 9\n\nNumber of people = 7\nTotal cost = (42 + 19 + 49) * 7 + 914 = 1,645\nAccommodation minimum nights:  2/4\n\nDays: 5,\nCurrent City: from Idaho Falls (Idaho) to San Jose,\nTransportation: self-driving, from Idaho Falls (Idaho) to San Jose, duration: 12 hours 56 mins, distance: 1,388 km, cost: 69\nBreakfast: -,\nAttraction: -,\nLunch: -,\nDinner: -,\nAccommodation: -\n\nNumber of people = 7\nTotal cost = 69 * 7 = 483\n\nTotal cost across all days = 2,367 + 1,757 + 1,673 + 1,645 + 483 = 7,925\nCuisines: The prompt specifies Indian and French, and both of these cuisines have been represented in the restaurants chosen.\n\nPlease note that the accommodation in Boise has a minimum stay of 2645 nights, which is not feasible for this itinerary. However, since this is the only accommodation option provided in the reference information, it has been included in the plan. Adjustments would need to be made to find suitable accommodation.", "gpt-4-1106-preview_direct_sole-planning_parsed_results": [{"day": 1, "current_city": "from San Jose to Boise", "transportation": "Flight Number: F3858398, from San Jose to Boise, Departure Time: 15:20, Arrival Time: 17:47", "breakfast": "-", "attraction": "-", "lunch": "-", "dinner": "Gopala Hari, Boise", "accommodation": "Modern & Cozy 2 BR Private Apartment in Brooklyn, Boise"}, {"day": 2, "current_city": "Boise", "transportation": "-", "breakfast": "TGI Friday's, Boise", "attraction": "Zoo Boise, Boise;Idaho State Museum, Boise;", "lunch": "California Pizza Kitchen, Boise", "dinner": "Dhaba By Claridges, Boise", "accommodation": "Modern & Cozy 2 BR Private Apartment in Brooklyn, Boise"}, {"day": 3, "current_city": "from Boise to Idaho Falls", "transportation": "self-driving, from Boise to Idaho Falls, duration: 4 hours 1 min, distance: 451 km", "breakfast": "-", "attraction": "-", "lunch": "-", "dinner": "Dhuaan, Idaho Falls", "accommodation": "Sunny & Spacious 2 bdrm apt, Idaho Falls"}, {"day": 4, "current_city": "Idaho Falls", "transportation": "-", "breakfast": "Shiv Restaurant, Idaho Falls", "attraction": "Museum of Idaho, Idaho Falls;Giant Eagle Waterfall Nest, Idaho Falls;", "lunch": "Taste of China, Idaho Falls", "dinner": "The Fusion Food Stand, Idaho Falls", "accommodation": "Sunny & Spacious 2 bdrm apt, Idaho Falls"}, {"day": 5, "current_city": "from Idaho Falls to San Jose", "transportation": "self-driving, from Idaho Falls to San Jose, duration: 12 hours 56 mins, distance: 1,388 km", "breakfast": "-", "attraction": "-", "lunch": "-", "dinner": "-", "accommodation": "-"}]}]