[{"gpt-4-1106-preview_direct_sole-planning_results": "Travel Plan:\nNumber of people = 3\nTotal budget = $7,900\n\nDays: 1\nCurrent City: from Atlanta to Bemidji (Minnesota)\nTransportation: Taxi, from Atlanta to Bemidji, duration: 19 hours 53 mins, distance: 2,166 km, cost: $2,166\nBreakfast: -\nAttraction: -\nLunch: -\nDinner: Pig and Whistle, Bemidji (Minnesota), cost: $39, cuisines: \u201cFast Food, Mexican, Bakery, Seafood\u201d\nAccommodation: A beautiful Cozy 1 BR Apartment., Bemidji (Minnesota), cost: $198, maximum occupancy: 2, house rules: No children under 10, minimum nights: 2\n\nTotal cost for Day 1 = $2,166 + ($39 * 3) + $198 = $2,481\nAccommodation minimum nights: 1/2\n\nDays: 2\nCurrent City: Bemidji (Minnesota)\nTransportation: -\nBreakfast: Flying Cakes, Bemidji (Minnesota), cost: $43, cuisines: \u201cTea, Seafood\u201d\nAttraction: Paul Bunyan & Babe the Blue Ox Statues, Bemidji (Minnesota); Headwaters Science Center, Bemidji (Minnesota);\nLunch: Outback Bar and Grill - Leisure Inn, Bemidji (Minnesota), cost: $59, cuisines: \u201cIndian, Desserts, Fast Food\u201d\nDinner: The Chocolate Haven, Bemidji (Minnesota), cost: $23, cuisines: \u201cDesserts, Tea, Italian, BBQ, Fast Food, Chinese\u201d\nAccommodation: A beautiful Cozy 1 BR Apartment., Bemidji (Minnesota), cost: $198, maximum occupancy: 2, house rules: No children under 10, minimum nights: 2\n\nTotal cost for Day 2 = ($43 + $59 + $23) * 3 + $198 = $567\nAccommodation minimum nights: 2/2\n\nDays: 3\nCurrent City: from Bemidji (Minnesota) to Minneapolis (Minnesota)\nTransportation: Flight Number: F3849472, from Bemidji (Minnesota) to Minneapolis (Minnesota), Departure Time: 08:21, Arrival Time: 09:23, cost: $86\nBreakfast: -\nAttraction: Minneapolis Sculpture Garden, Minneapolis (Minnesota); Minneapolis Institute of Art, Minneapolis (Minnesota);\nLunch: The Cafe, Minneapolis (Minnesota), cost: $14, cuisines: \u201cIndian, Mediterranean, Desserts, Seafood\u201d\nDinner: Malo, Minneapolis (Minnesota), cost: $80, cuisines: \u201cTea, Chinese, Indian, Cafe\u201d\nAccommodation: Entire 1 Bedroom Apartment in Midtown Manhattan, Minneapolis (Minnesota), cost: $107, maximum occupancy: 3, house rules: No visitors, minimum nights: 4\n\nTotal cost for Day 3 = $86 * 3 + ($14 + $80) * 3 + $107 = $695\nAccommodation minimum nights: 1/4\n\nDays: 4\nCurrent City: Minneapolis (Minnesota)\nTransportation: -\nBreakfast: Court Avenue Brewing Company, Minneapolis (Minnesota), cost: $31, cuisines: \u201cPizza, French, Bakery, BBQ, Seafood\u201d\nAttraction: Mill City Museum, Minneapolis (Minnesota); Weisman Art Museum, Minneapolis (Minnesota);\nLunch: Troll Tavern, Minneapolis (Minnesota), cost: $71, cuisines: \u201cTea, BBQ, Mediterranean\u201d\nDinner: Monkeypod Kitchen by Merriman, Minneapolis (Minnesota), cost: $50, cuisines: \u201cDesserts, Pizza, Bakery, Fast Food, Indian, Mediterranean\u201d\nAccommodation: Entire 1 Bedroom Apartment in Midtown Manhattan, Minneapolis (Minnesota), cost: $107, maximum occupancy: 3, house rules: No visitors, minimum nights: 4\n\nTotal cost for Day 4 = ($31 + $71 + $50) * 3 + $107 = $590\nAccommodation minimum nights: 2/4\n\nDays: 5\nCurrent City: from Minneapolis to Atlanta\nTransportation: Flight Number: F3781043, from Minneapolis to Atlanta, Departure Time: 07:28, Arrival Time: 10:49, cost: $205\nBreakfast: -\nAttraction: -\nLunch: -\nDinner: -\nAccommodation: -\n\nTotal cost for Day 5 = $205 * 3 = $615\n\nTotal cost across all days = $2,481 + $567 + $695 + $590 + $615 = $4,948\n\nCuisines: No specific cuisines were requested, but a variety of cuisines have been included in the chosen restaurants.\n\nNote: The accommodation chosen allows for parties as requested and is an entire room/apt. The transportation does not include self-driving as per the request. The total cost is within the specified budget of $7,900.", "gpt-4-1106-preview_direct_sole-planning_parsed_results": [{"day": 1, "current_city": "from Atlanta to Bemidji", "transportation": "Taxi, from Atlanta to Bemidji, duration: 19 hours 53 mins, distance: 2,166 km", "breakfast": "-", "attraction": "-", "lunch": "-", "dinner": "Pig and Whistle, Bemidji", "accommodation": "A beautiful Cozy 1 BR Apartment., Bemidji"}, {"day": 2, "current_city": "Bemidji", "transportation": "-", "breakfast": "Flying Cakes, Bemidji", "attraction": "Paul Bunyan & Babe the Blue Ox Statues, Bemidji;Headwaters Science Center, Bemidji;", "lunch": "Outback Bar and Grill - Leisure Inn, Bemidji", "dinner": "The Chocolate Haven, Bemidji", "accommodation": "A beautiful Cozy 1 BR Apartment., Bemidji"}, {"day": 3, "current_city": "from Bemidji to Minneapolis", "transportation": "Flight Number: F3849472, from Bemidji to Minneapolis, Departure Time: 08:21, Arrival Time: 09:23", "breakfast": "-", "attraction": "Minneapolis Sculpture Garden, Minneapolis;Minneapolis Institute of Art, Minneapolis;", "lunch": "The Cafe, Minneapolis", "dinner": "Malo, Minneapolis", "accommodation": "Entire 1 Bedroom Apartment in Midtown Manhattan, Minneapolis"}, {"day": 4, "current_city": "Minneapolis", "transportation": "-", "breakfast": "Court Avenue Brewing Company, Minneapolis", "attraction": "Mill City Museum, Minneapolis;Weisman Art Museum, Minneapolis;", "lunch": "Troll Tavern, Minneapolis", "dinner": "Monkeypod Kitchen by Merriman, Minneapolis", "accommodation": "Entire 1 Bedroom Apartment in Midtown Manhattan, Minneapolis"}, {"day": 5, "current_city": "from Minneapolis to Atlanta", "transportation": "Flight Number: F3781043, from Minneapolis to Atlanta, Departure Time: 07:28, Arrival Time: 10:49", "breakfast": "-", "attraction": "-", "lunch": "-", "dinner": "-", "accommodation": "-"}]}]