[{"gpt-4-1106-preview_direct_sole-planning_results": "Based on the provided query and reference information, here is a crafted 7-day travel plan for two individuals:\n\n**Travel Plan:**\n\n**Day 1: St. Louis to San Diego (California)**\n- Transportation: Flight Number: F4025732, from St. Louis to San Diego, Departure Time: 16:42, Arrival Time: 18:31, Cost: $430 per person\n- Breakfast: Not applicable (presumably in St. Louis)\n- Attraction: Not applicable (arrival in the evening)\n- Lunch: Not applicable (presumably in St. Louis)\n- Dinner: Burgrill, San Diego, Cost: $54, Cuisines: \u201cDesserts, Tea, Pizza, Fast Food, Chinese\u201d\n- Accommodation: Spacious Room in Large 2 Bedroom Prewar Apartment, San Diego, Cost: $585, Maximum Occupancy: 2, House Rules: No parties & No visitors, Minimum Nights: 1\n\n**Day 2: San Diego (California)**\n- Transportation: Not applicable (staying in San Diego)\n- Breakfast: Burger King, San Diego, Cost: $20, Cuisines: \u201cPizza, Italian, French, Fast Food, Seafood\u201d\n- Attraction: La Jolla Shores Park, San Diego; Cabrillo National Monument, San Diego\n- Lunch: Gopala, San Diego, Cost: $98, Cuisines: \u201cPizza, Mexican, BBQ, American, Seafood\u201d\n- Dinner: Bikaner Sweets, San Diego, Cost: $37, Cuisines: \u201cBakery, Pizza, Indian, Fast Food\u201d\n- Accommodation: Spacious Room in Large 2 Bedroom Prewar Apartment, San Diego, Cost: $585, Maximum Occupancy: 2, House Rules: No parties & No visitors, Minimum Nights: 1\n\n**Day 3: San Diego to San Francisco (California)**\n- Transportation: Flight Number: F3746772, from San Diego to San Francisco, Departure Time: 08:09, Arrival Time: 09:43, Cost: $112 per person\n- Breakfast: Not applicable (early flight)\n- Attraction: Golden Gate Park, San Francisco; Golden Gate Bridge, San Francisco\n- Lunch: Bonne Bouche, San Francisco, Cost: $21, Cuisines: \u201cTea, Chinese, American, Cafe\u201d\n- Dinner: Kream's, San Francisco, Cost: $67, Cuisines: \u201cTea, Pizza, BBQ, Chinese, Seafood\u201d\n- Accommodation: Great 1 Bedroom on Upper East, San Francisco, Cost: $484, Maximum Occupancy: 2, House Rules: No parties, Minimum Nights: 2\n\n**Day 4: San Francisco (California)**\n- Transportation: Not applicable (staying in San Francisco)\n- Breakfast: Coffee & Chai Co., San Francisco, Cost: $10, Cuisines: \u201cTea, Mexican, BBQ, Cafe, Seafood\u201d\n- Attraction: California Academy of Sciences, San Francisco; San Francisco Museum of Modern Art, San Francisco\n- Lunch: Sudarshan, San Francisco, Cost: $53, Cuisines: \u201cFast Food, Bakery, Mediterranean, Italian\u201d\n- Dinner: Green Chick Chop, San Francisco, Cost: $39, Cuisines: \u201cTea, Pizza, Italian, BBQ, Mediterranean, Seafood\u201d\n- Accommodation: Great 1 Bedroom on Upper East, San Francisco, Cost: $484, Maximum Occupancy: 2, House Rules: No parties, Minimum Nights: 2\n\n**Day 5: San Francisco to Long Beach (California)**\n- Transportation: Taxi, from San Francisco to Long Beach, Duration: 6 hours 15 mins, Distance: 652 km, Cost: $652\n- Breakfast: Gupta\u2019s Rasoi, San Francisco, Cost: $13, Cuisines: \u201cCafe, Bakery, BBQ, Mediterranean\u201d\n- Attraction: The Queen Mary, Long Beach\n- Lunch: Not applicable (traveling)\n- Dinner: Tsing Tsao South, Long Beach, Cost: $56, Cuisines: \u201cTea, Cafe, BBQ\u201d\n- Accommodation: Cozy Two Bedrooms Home Away From Home Getaway., Long Beach, Cost: $914, Maximum Occupancy: 3, House Rules: No pets & No children under 10, Minimum Nights: 2\n\n**Day 6: Long Beach (California)**\n- Transportation: Not applicable (staying in Long Beach)\n- Breakfast: Winifreds, Long Beach, Cost: $23, Cuisines: \u201cBakery, BBQ, Fast Food\u201d\n- Attraction: Aquarium of the Pacific, Long Beach; Rainbow Lagoon Park, Long Beach\n- Lunch: ChandChini, Long Beach, Cost: $19, Cuisines: \u201cCafe, Pizza, Desserts, Seafood\u201d\n- Dinner: Giuseppe\u2019s Pizza & Italian Specialities, Long Beach, Cost: $72, Cuisines: \u201cBakery, Fast Food, Cafe, Indian, Mediterranean, Seafood\u201d\n- Accommodation: Cozy Two Bedrooms Home Away From Home Getaway., Long Beach, Cost: $914, Maximum Occupancy: 3, House Rules: No pets & No children under 10, Minimum Nights: 2\n\n**Day 7: Long Beach to St. Louis**\n- Transportation: Flight Number: F3986547, from Long Beach to St. Louis, Departure Time: 07:04, Arrival Time: 12:37, Cost: $370 per person\n- Breakfast: Not applicable (early flight)\n- Attraction: Not applicable (departing)\n- Lunch: Not applicable (in flight)\n- Dinner: Not applicable (arrival in St. Louis)\n- Accommodation: Not applicable (returning home)\n\n**Total Cost Calculation:**\n- Day 1: (2 * $430) + (2 * $54) + $585 = $1,553\n- Day 2: (2 * $20) + (2 * $98) + (2 * $37) + $585 = $895\n- Day 3: (2 * $112) + (2 * $21) + (2 * $67) + $484 = $884\n- Day 4: (2 * $10) + (2 * $53) + (2 * $39) + $484 = $688\n- Day 5: $652 + (2 * $13) + (2 * $56) + $914 = $1,704\n- Day 6: (2 * $23) + (2 * $19) + (2 * $72) + $914 = $1,142\n- Day 7: (2 * $370) = $740\n\n**Total cost across all days:** $1,553 + $895 + $884 + $688 + $1,704 + $1,142 + $740 = $7,606\n\n**Remaining Budget:** $9,500 - $7,606 = $1,894\n\n**Cuisines:** American and Chinese cuisines have been included in the selected restaurants.\n\n**Notes:**\n- The travel plan includes all required details for each day, adhering to the constraints.\n- The total cost is within the specified budget of $9,500.\n- The accommodations chosen do not have shared rooms and adhere to the house rules specified.\n- The transportation modes are consistent and do not conflict with each other.\n- The plan includes a variety of attractions and dining options, ensuring no repetition across days.\n- The city sequence forms a closed loop, starting and ending in St. Louis, with each city visited once except for the starting and ending city.", "gpt-4-1106-preview_direct_sole-planning_parsed_results": [{"day": 1, "current_city": "from St. Louis to San Diego", "transportation": "Flight Number: F4025732, from St. Louis to San Diego, Departure Time: 16:42, Arrival Time: 18:31", "breakfast": "-", "attraction": "-", "lunch": "-", "dinner": "Burgrill, San Diego", "accommodation": "Spacious Room in Large 2 Bedroom Prewar Apartment, San Diego"}, {"day": 2, "current_city": "San Diego", "transportation": "-", "breakfast": "Burger King, San Diego", "attraction": "La Jolla Shores Park, San Diego;Cabrillo National Monument, San Diego;", "lunch": "Gopala, San Diego", "dinner": "Bikaner Sweets, San Diego", "accommodation": "Spacious Room in Large 2 Bedroom Prewar Apartment, San Diego"}, {"day": 3, "current_city": "from San Diego to San Francisco", "transportation": "Flight Number: F3746772, from San Diego to San Francisco, Departure Time: 08:09, Arrival Time: 09:43", "breakfast": "-", "attraction": "Golden Gate Park, San Francisco;Golden Gate Bridge, San Francisco;", "lunch": "Bonne Bouche, San Francisco", "dinner": "Kream's, San Francisco", "accommodation": "Great 1 Bedroom on Upper East, San Francisco"}, {"day": 4, "current_city": "San Francisco", "transportation": "-", "breakfast": "Coffee & Chai Co., San Francisco", "attraction": "California Academy of Sciences, San Francisco;San Francisco Museum of Modern Art, San Francisco;", "lunch": "Sudarshan, San Francisco", "dinner": "Green Chick Chop, San Francisco", "accommodation": "Great 1 Bedroom on Upper East, San Francisco"}, {"day": 5, "current_city": "from San Francisco to Long Beach", "transportation": "Taxi, from San Francisco to Long Beach, Duration: 6 hours 15 mins, Distance: 652 km", "breakfast": "Gupta\u2019s Rasoi, San Francisco", "attraction": "The Queen Mary, Long Beach", "lunch": "-", "dinner": "Tsing Tsao South, Long Beach", "accommodation": "Cozy Two Bedrooms Home Away From Home Getaway., Long Beach"}, {"day": 6, "current_city": "Long Beach", "transportation": "-", "breakfast": "Winifreds, Long Beach", "attraction": "Aquarium of the Pacific, Long Beach;Rainbow Lagoon Park, Long Beach;", "lunch": "ChandChini, Long Beach", "dinner": "Giuseppe\u2019s Pizza & Italian Specialities, Long Beach", "accommodation": "Cozy Two Bedrooms Home Away From Home Getaway., Long Beach"}, {"day": 7, "current_city": "from Long Beach to St. Louis", "transportation": "Flight Number: F3986547, from Long Beach to St. Louis, Departure Time: 07:04, Arrival Time: 12:37", "breakfast": "-", "attraction": "-", "lunch": "-", "dinner": "-", "accommodation": "-"}]}]